Workbook

Sheet Lisez-moi
A1: Canapoil — classeur de pilotage
A3: Rôle | B3: Tenir chaque semaine les chiffres qui décident : portes, trésorerie, stock, délais, créateurs, réclamations. Importable dans Google Sheets (Fichier > Importer).
A4: Saisies | B4: Cellules en bleu. Les autres cellules sont des formules.
A5: Alertes | B5: Trésorerie : réserve disponible < 300 € → aucune commande fournisseur ni échantillon avant le prochain encaissement. Stock : < 5 unités → précommande ou indisponible sur le site (brand.json) ; < 10 en pic viral → réassort express. Délais : 90e centile > 6 jours ouvrés → revoir la promesse.
A6: Sources | B6: strategie/brand.json (prix, seuils, micro-stock), strategie/04-strategie.md (portes, tableau de bord §6.7), marketing/07-plan-organique-90j.md (KPI §8), finance/05-analyse-financiere.md (trésorerie §5).
A7: Rythme | B7: Chaque lundi matin : KPI hebdo, Trésorerie, Stock. Chaque jour : Commandes et Mouvements stock. À la porte 1 : Décisions et Dates précommande.
A8: Option de trésorerie | B8: À signer avant S1 (Décisions!B4) : a = apport de 2 400 € ; b = TikTok Shop plafonné au stock payé, sans affiliés avant le premier règlement (910 € à la porte 1) ; c = arrêt à 45 €.

Sheet Décisions
A1: Portes de décision (brand.json → lancement)
A3: Trésorerie
A4: Option retenue (a, b ou c), signée le
A6: Porte 1 (15/11/2026), sur 14 jours
A7: Vues de la meilleure vidéo du produit | B7: 0
A8: Taux de clics de cette vidéo (%) | B8: 0
A9: Inscrits qualifiés sur la liste d'attente (attribut PRODUIT) | B9: 0
A10: Taux de clics produit moyen des vidéos de démonstration (%) | B10: 0
A11: Commentaires d'intention, comptes uniques hors entourage | B11: 0
A12: Décision porte 1 | B12: =IF(AND(OR(AND(B7>=50000,B8>=1),B9>=150),B10>=1.5,B11>=20),"GO : commander le micro-stock, puis ouvrir les précommandes","NO-GO : 2 semaines de contenu de plus, ou produit suivant")
A14: Porte stock (fin de la précommande)
A15: Précommandes payées hors entourage (noms et adresses vérifiés) | B15: 0
A16: Inscrits confirmés sur la liste d'attente à l'ouverture | B16: 0
A17: Précommandes venant de la liste (utm_source=email) | B17: 0
A18: Conversion liste → précommande | B18: =IF(B16>0,B17/B16,0)
A19: Décision porte stock | B19: =IF(AND(B15>=20,B18>=0.08),"GO : réassort et stock principal (fin janvier 2027)","NO-GO : aucun réassort, écouler le micro-stock")
A21: Duel (porte 1) : inscrits qualifiés rouleau / tapis de fouille
A22: Rouleau | B22: 0
A23: Tapis de fouille | B23: 0
A24: Héros retenu | B24: =IF(B23>=1.5*B22,"Tapis de fouille (≥ 50 % de mieux)","Rouleau")
A26: Prix du rouleau (relevé TikTok Shop) | B26: ='Prix TikTok Shop'!B26

Sheet Dates précommande
A1: Calcul des dates de précommande (brand.json → livraison.precommande.regle_dates)
A3: Date de commande et de paiement du micro-stock | B3: 46342
A4: 90e centile du transit mesuré sur les échantillons (jours calendaires) | B4: 12
A5: Date d'ouverture des précommandes | B5: 46344
A7: Arrivée estimée du stock en France | B7: =B3+B4
A8: Expédition à partir du (+ 3 jours ouvrés : dédouanement, contrôle, étiquetage) | B8: =WORKDAY(B7,3,Fériés!A2:A40)
A9: Livraison au plus tard le (+ 6 jours ouvrés) | B9: =WORKDAY(B8,6,Fériés!A2:A40)
A10: Contrôle J-10 : colis fournisseur en France au plus tard le | B10: =B9-10
A11: Plafond de 30 jours respecté ? | B11: =IF(B9-B5<=30,"Oui","NON : décaler l'ouverture ou choisir un envoi plus rapide")
A12: Argument Noël utilisable (livraison au plus tard le 23/12/2026) ? | B12: =IF(B9<=DATE(2026,12,23),"Oui","Non : aucune mention de Noël")
A14: Recopier B8 et B9 dans brand.json → livraison.precommande, puis lancer python3 site/outils/generer.py --publication

Sheet Fériés
A1: Jours fériés (France métropolitaine)
A2: 46023
A3: 46118
A4: 46143
A5: 46150
A6: 46156
A7: 46167
A8: 46217
A9: 46249
A10: 46327
A11: 46337
A12: 46381
A13: 46388
... A23: 46746

Sheet Trésorerie
A1: Réserve de trésorerie hebdomadaire (alerte < 300 €)
A3: Semaine (lundi) | B3: Solde bancaire (€) | C3: Fournisseurs à payer à 30 j (€) | D3: TVA à reverser (€) | E3: Autres dettes (€) | F3: Réserve disponible (€) | G3: Alerte | H3: Encaissement TikTok Shop attendu (date) | I3: Commentaire
A4: 46307 | F4: =IF(B4="","",B4-C4-D4-E4) | G4: =IF(F4="","",IF(F4<300,"ALERTE : aucune commande fournisseur ni échantillon","OK"))
A5: 46314 | F5: =IF(B5="","",B5-C5-D5-E5) | G5: =IF(F5="","",IF(F5<300,"ALERTE : aucune commande fournisseur ni échantillon","OK"))
A6: 46321 | F6: =IF(B6="","",B6-C6-D6-E6) | G6: =IF(F6="","",IF(F6<300,"ALERTE : aucune commande fournisseur ni échantillon","OK"))
A7: 46328 | F7: =IF(B7="","",B7-C7-D7-E7) | G7: =IF(F7="","",IF(F7<300,"ALERTE : aucune commande fournisseur ni échantillon","OK"))
A8: 46335 | F8: =IF(B8="","",B8-C8-D8-E8) | G8: =IF(F8="","",IF(F8<300,"ALERTE : aucune commande fournisseur ni échantillon","OK"))
A9: 46342 | F9: =IF(B9="","",B9-C9-D9-E9) | G9: =IF(F9="","",IF(F9<300,"ALERTE : aucune commande fournisseur ni échantillon","OK"))
A10: 46349 | F10: =IF(B10="","",B10-C10-D10-E10) | G10: =IF(F10="","",IF(F10<300,"ALERTE : aucune commande fournisseur ni échantillon","OK"))
A11: 46356 | F11: =IF(B11="","",B11-C11-D11-E11) | G11: =IF(F11="","",IF(F11<300,"ALERTE : aucune commande fournisseur ni échantillon","OK"))
A12: 46363 | F12: =IF(B12="","",B12-C12-D12-E12) | G12: =IF(F12="","",IF(F12<300,"ALERTE : aucune commande fournisseur ni échantillon","OK"))
A13: 46370 | F13: =IF(B13="","",B13-C13-D13-E13) | G13: =IF(F13="","",IF(F13<300,"ALERTE : aucune commande fournisseur ni échantillon","OK"))
A14: 46377 | F14: =IF(B14="","",B14-C14-D14-E14) | G14: =IF(F14="","",IF(F14<300,"ALERTE : aucune commande fournisseur ni échantillon","OK"))
A15: 46384 | F15: =IF(B15="","",B15-C15-D15-E15) | G15: =IF(F15="","",IF(F15<300,"ALERTE : aucune commande fournisseur ni échantillon","OK"))
... A29: 46482 | F29: =IF(B29="","",B29-C29-D29-E29) | G29: =IF(F29="","",IF(F29<300,"ALERTE : aucune commande fournisseur ni échantillon","OK"))
A31: Repères (05 §5) : 910 € à avancer avant le premier encaissement ; creux réaliste de 2 000 € en février 2027 ; optimiste 4 539 €.

Sheet Commandes
A1: Commandes (site, TikTok Shop) et délais réels
A3: N° commande | B3: Canal | C3: Date de commande | D3: Produits (SKU × qté) | E3: Montant TTC (€) | F3: Précommande (oui/non) | G3: Expédition prévue | H3: Livraison au plus tard | I3: Expédition réelle | J3: Livraison réelle | K3: Délai réel (jours ouvrés) | L3: Dans les délais ? | M3: Gant offert (prime) | N3: Entourage (oui/non) | O3: utm_content | P3: Statut | R3: Gants de prime attribués | S3: =COUNTIF(M4:M503,"oui")
K4: =IF(OR(C4="",J4=""),"",NETWORKDAYS(C4,J4,Fériés!$A$2:$A$40)-1) | L4: =IF(J4="","",IF(H4<>"",IF(J4<=H4,"Oui","NON"),IF(K4<=6,"Oui","NON"))) | R4: Restants (30 réservés) | S4: =30-S3
K5: =IF(OR(C5="",J5=""),"",NETWORKDAYS(C5,J5,Fériés!$A$2:$A$40)-1) | L5: =IF(J5="","",IF(H5<>"",IF(J5<=H5,"Oui","NON"),IF(K5<=6,"Oui","NON"))) | R5: Précommandes hors entourage | S5: =COUNTIFS(F4:F503,"oui",N4:N503,"non")
K6: =IF(OR(C6="",J6=""),"",NETWORKDAYS(C6,J6,Fériés!$A$2:$A$40)-1) | L6: =IF(J6="","",IF(H6<>"",IF(J6<=H6,"Oui","NON"),IF(K6<=6,"Oui","NON")))
K7: =IF(OR(C7="",J7=""),"",NETWORKDAYS(C7,J7,Fériés!$A$2:$A$40)-1) | L7: =IF(J7="","",IF(H7<>"",IF(J7<=H7,"Oui","NON"),IF(K7<=6,"Oui","NON")))
K8: =IF(OR(C8="",J8=""),"",NETWORKDAYS(C8,J8,Fériés!$A$2:$A$40)-1) | L8: =IF(J8="","",IF(H8<>"",IF(J8<=H8,"Oui","NON"),IF(K8<=6,"Oui","NON")))
K9: =IF(OR(C9="",J9=""),"",NETWORKDAYS(C9,J9,Fériés!$A$2:$A$40)-1) | L9: =IF(J9="","",IF(H9<>"",IF(J9<=H9,"Oui","NON"),IF(K9<=6,"Oui","NON")))
K10: =IF(OR(C10="",J10=""),"",NETWORKDAYS(C10,J10,Fériés!$A$2:$A$40)-1) | L10: =IF(J10="","",IF(H10<>"",IF(J10<=H10,"Oui","NON"),IF(K10<=6,"Oui","NON")))
K11: =IF(OR(C11="",J11=""),"",NETWORKDAYS(C11,J11,Fériés!$A$2:$A$40)-1) | L11: =IF(J11="","",IF(H11<>"",IF(J11<=H11,"Oui","NON"),IF(K11<=6,"Oui","NON")))
K12: =IF(OR(C12="",J12=""),"",NETWORKDAYS(C12,J12,Fériés!$A$2:$A$40)-1) | L12: =IF(J12="","",IF(H12<>"",IF(J12<=H12,"Oui","NON"),IF(K12<=6,"Oui","NON")))
K13: =IF(OR(C13="",J13=""),"",NETWORKDAYS(C13,J13,Fériés!$A$2:$A$40)-1) | L13: =IF(J13="","",IF(H13<>"",IF(J13<=H13,"Oui","NON"),IF(K13<=6,"Oui","NON")))
K14: =IF(OR(C14="",J14=""),"",NETWORKDAYS(C14,J14,Fériés!$A$2:$A$40)-1) | L14: =IF(J14="","",IF(H14<>"",IF(J14<=H14,"Oui","NON"),IF(K14<=6,"Oui","NON")))
K15: =IF(OR(C15="",J15=""),"",NETWORKDAYS(C15,J15,Fériés!$A$2:$A$40)-1) | L15: =IF(J15="","",IF(H15<>"",IF(J15<=H15,"Oui","NON"),IF(K15<=6,"Oui","NON")))
K16: =IF(OR(C16="",J16=""),"",NETWORKDAYS(C16,J16,Fériés!$A$2:$A$40)-1) | L16: =IF(J16="","",IF(H16<>"",IF(J16<=H16,"Oui","NON"),IF(K16<=6,"Oui","NON")))
K17: =IF(OR(C17="",J17=""),"",NETWORKDAYS(C17,J17,Fériés!$A$2:$A$40)-1) | L17: =IF(J17="","",IF(H17<>"",IF(J17<=H17,"Oui","NON"),IF(K17<=6,"Oui","NON")))
... K503: =IF(OR(C503="",J503=""),"",NETWORKDAYS(C503,J503,Fériés!$A$2:$A$40)-1) | L503: =IF(J503="","",IF(H503<>"",IF(J503<=H503,"Oui","NON"),IF(K503<=6,"Oui","NON")))

Sheet Délais
A1: Délai de livraison réel (brand.json → livraison.regle_recalcul)
A3: Livraisons mesurées | B3: =COUNT(Commandes!K4:K503)
A4: Délai moyen (jours ouvrés après la commande) | B4: =IF(B3=0,"",AVERAGE(Commandes!K4:K503))
A5: 90e centile (jours ouvrés) | B5: =IF(B3=0,"",PERCENTILE(Commandes!K4:K503,0.9))
A6: Délai à afficher après 30 livraisons (90e centile + 2 jours ouvrés) | B6: =IF(B3<30,"Attendre 30 livraisons (afficher 3 à 6 jours ouvrés)",ROUNDUP(B5,0)+2)
A7: Alerte | B7: =IF(B5="","",IF(B5>6,"ALERTE : 90e centile > 6 jours ouvrés, revoir la promesse ou le transporteur","OK"))
A8: Commandes hors délai | B8: =COUNTIF(Commandes!L4:L503,"NON")
A10: TikTok Shop en expédition par le vendeur : livraison sous 4 jours ouvrés exigée. Mondial Relay interdit tant que le 90e centile mesuré dépasse 4.

Sheet Mouvements stock
A1: Mouvements de stock (une ligne par mouvement)
A3: Date | B3: SKU | C3: Type | D3: Quantité (+ entrée / − sortie) | E3: Lot (AAMM) | F3: Commentaire
A4: 46357 | B4: CNP-ROU-01 | C4: réception | D4: 40 | F4: Micro-stock initial (exemple, à corriger à réception)
A5: 46357 | B5: CNP-GAN-01 | C5: réception | D5: 45 | F5: Micro-stock initial (exemple, à corriger à réception)
A6: 46357 | B6: CNP-RAC-01 | C6: réception | D6: 12 | F6: Micro-stock initial (exemple, à corriger à réception)
A7: 46357 | B7: CNP-TAP-01 | C7: réception | D7: 8 | F7: Micro-stock initial (exemple, à corriger à réception)

Sheet Stock
A1: Stock par produit (à recopier chaque matin dans brand.json → produits[].stock_disponible)
A3: SKU | B3: Produit | C3: Stock réel | D3: Stock à saisir sur le site (brand.json) | E3: Stock à saisir sur TikTok Shop (réel − 2) | F3: État sur le site | G3: Alerte réassort
A4: CNP-ROU-01 | B4: Le Rouleau anti-poils réutilisable | C4: =SUMIFS('Mouvements stock'!D:D,'Mouvements stock'!B:B,A4) | D4: =C4 | E4: =MAX(0,C4-2) | F4: =IF(C4>=5,"disponible",IF(C4>0,"précommande (dates de réassort) ou indisponible","indisponible")) | G4: =IF(C4<10,"Réassort à décider (express en pic viral)","OK")
A5: CNP-GAN-01 | B5: Le Gant de toilettage en silicone | C5: =SUMIFS('Mouvements stock'!D:D,'Mouvements stock'!B:B,A5) | D5: =C5 | E5: =MAX(0,C5-2) | F5: =IF(C5>=5,"disponible",IF(C5>0,"précommande (dates de réassort) ou indisponible","indisponible")) | G5: =IF(C5<10,"Réassort à décider (express en pic viral)","OK")
A6: CNP-RAC-01 | B6: La Raclette anti-poils tapis et voiture | C6: =SUMIFS('Mouvements stock'!D:D,'Mouvements stock'!B:B,A6) | D6: =C6 | E6: =MAX(0,C6-2) | F6: =IF(C6>=5,"disponible",IF(C6>0,"précommande (dates de réassort) ou indisponible","indisponible")) | G6: =IF(C6<10,"Réassort à décider (express en pic viral)","OK")
A7: CNP-TAP-01 | B7: Le Tapis de fenêtre thermique | C7: =SUMIFS('Mouvements stock'!D:D,'Mouvements stock'!B:B,A7) | D7: =C7 | E7: =MAX(0,C7-2) | F7: =IF(C7>=5,"disponible",IF(C7>0,"précommande (dates de réassort) ou indisponible","indisponible")) | G7: =IF(C7<10,"Réassort à décider (express en pic viral)","OK")
A10: Grand kit (composant le plus rare) | C10: =MIN(C4,INT(C5),C6)

Sheet KPI hebdo
A1: Tableau de bord hebdomadaire (04 §6.7, 07 §8)
A3: KPI | B3: Cible | C3: Seuil d'alerte | D3: S1 | E3: S2 | F3: S3 | G3: S4 | H3: S5 | I3: S6 | J3: S7 | K3: S8 | L3: S9 | M3: S10 | N3: S11 | O3: S12 | P3: S13
A4: Vidéos publiées | B4: 14 | C4: < 10
A5: Vues médianes par vidéo (J+7) | B5: 2 000 à J+60 | C5: < 500 après S6
A6: Taux de clics produit (%) | B6: ≥ 1,5 (porte 1) | C6: < 0,5
A7: Inscrits confirmés (cumul) | B7: 150 à la porte 1 | C7: —
A8: Commentaires d'intention (14 j, hors entourage) | B8: ≥ 20 | C8: < 20
A9: Sessions du site | B9: 1 000 à S13 | C9: < 200
A10: Conversion du site (%) | B10: ≥ 1,5 | C10: < 0,8
A11: Commandes par jour (moyenne 7 j) | B11: 5 (palier 1) | C11: < 3 sur 14 j
A12: Marge moyenne par commande (€) | B12: ≥ 6,30 | C12: < 5
A13: Réserve de trésorerie (€) | B13: ≥ 300 | C13: < 300
A14: Stock le plus bas (unités) | B14: ≥ 5 | C14: < 5
A15: Délai de livraison, 90e centile (jours ouvrés) | B15: ≤ 6 | C15: > 7
... A19: Heures travaillées | B19: 25 | C19: > 30 ou < 15

Sheet Prix TikTok Shop
A1: Relevé de 20 rouleaux anti-poils réutilisables sur TikTok Shop (onglet Boutique, avant la porte 1)
A3: Rang | B3: Prix TTC (€) | C3: Nom affiché | D3: Vendeur | E3: Ventes affichées | F3: Délai annoncé | G3: Date du relevé | H3: Capture (nom du fichier)
A4: 1
A5: 2
A6: 3
A7: 4
A8: 5
A9: 6
A10: 7
A11: 8
A12: 9
A13: 10
A14: 11
A15: 12
... A23: 20
A25: Médiane | B25: =IF(COUNT(B4:B23)=0,"",MEDIAN(B4:B23))
A26: Décision | B26: =IF(B25="","Relevé à faire",IF(B25<16,"Rouleau à 19,90 € et Grand kit seul mis en avant","Rouleau à 24,90 €"))

Sheet Réclamations GPSR
A1: Registre des réclamations et incidents de sécurité (règlement (UE) 2023/988), conservé 10 ans
A3: Date | B3: Commande | C3: SKU | D3: Lot | E3: Description | F3: Blessure ou dommage (oui/non) | G3: Gravité | H3: Mesure prise | I3: Fabricant informé le | J3: Safety Business Gateway (si accident grave) le | K3: Clôture le

Sheet Registre RGPD
A1: Registre des traitements (art. 30 RGPD) : base de départ, à compléter
A3: Traitement | B3: Finalité | C3: Base légale | D3: Données | E3: Destinataires | F3: Durée de conservation | G3: Sécurité
A4: Commandes | B4: Gestion des commandes, livraisons, retours | C4: Contrat | D4: Identité, adresse, e-mail, téléphone, commande | E4: Stripe, Mondial Relay, Brevo, hébergeur | F4: 5 ans (10 ans pour la comptabilité) | G4: Accès protégé, double authentification
A5: Liste d'attente et e-mails | B5: Annonce du lancement, tests, nouveautés | C5: Consentement (case non pré-cochée, date dans Brevo) | D5: E-mail, produit d'intérêt, date et texte du consentement, UTM | E5: Brevo | F5: 3 ans après le dernier contact actif | G5: Double opt-in
A6: Rétractation en ligne | B6: Accusé de réception de la déclaration | C6: Obligation légale | D6: Nom, prénom, commande, e-mail, IP (anti-abus) | E6: Brevo, service client | F6: 5 ans | G6: Vérification de la commande Stripe
A7: Anti-abus des formulaires | B7: Turnstile, limite de 3 envois par heure | C7: Intérêt légitime | D7: Adresse IP, jeton Turnstile | E7: Cloudflare | F7: 1 heure (compteur) | G7: —
A8: Créateurs | B8: Recrutement et suivi des affiliés | C8: Intérêt légitime ; contrat | D8: Pseudo, contact, statistiques publiques, adresse d'envoi | E8: TikTok | F8: 3 ans après la fin de la collaboration | G8: —
A9: Réclamations GPSR | B9: Sécurité des produits | C9: Obligation légale | D9: Commande, description, photos | E9: Fabricant, autorités | F9: 10 ans | G9: —

Sheet Créateurs
A1: Suivi des créateurs (marketing/createurs-affiliation.md)
A3: Pseudo | B3: Plateforme | C3: Abonnés | D3: Score (/100) | E3: Contacté le | F3: Modèle (M1-M5) | G3: Réponse | H3: Taux (%) | I3: Échantillon envoyé le | J3: Vidéos publiées | K3: Mention « Collaboration commerciale » vérifiée | L3: Commandes attribuées | M3: Statut
