Workbook
Name h_TVA: 'Hypothèses'!$C$6
Name h_IS_TAUX_REDUIT: 'Hypothèses'!$C$7
Name h_IS_SEUIL: 'Hypothèses'!$C$8
Name h_IS_TAUX_NORMAL: 'Hypothèses'!$C$9
Name h_FRANCHISE_SEUIL: 'Hypothèses'!$C$10
Name h_FRANCHISE_SEUIL_MAJORE: 'Hypothèses'!$C$11
Name h_MICRO_COTIS: 'Hypothèses'!$C$12
Name h_MICRO_VL: 'Hypothèses'!$C$13
Name h_MICRO_PLAFOND: 'Hypothèses'!$C$14
Name h_PFU: 'Hypothèses'!$C$15
Name h_CHARGES_SASU: 'Hypothèses'!$C$16
Name h_CHARGES_TNS: 'Hypothèses'!$C$17
Name h_TNS_MINIMUM: 'Hypothèses'!$C$18
Name h_SMIC_NET_H: 'Hypothèses'!$C$19
Name h_HEURES_FONDATEUR: 'Hypothèses'!$C$20
Name h_TAP_PRIX: 'Hypothèses'!$C$22
Name h_TAP_PROD: 'Hypothèses'!$C$23
Name h_TAP_DROITS: 'Hypothèses'!$C$24
Name h_TAP_POIDS: 'Hypothèses'!$C$25
Name h_RAC_PRIX: 'Hypothèses'!$C$27
Name h_RAC_PROD: 'Hypothèses'!$C$28
Name h_RAC_DROITS: 'Hypothèses'!$C$29
Name h_RAC_POIDS: 'Hypothèses'!$C$30
Name h_GAN_PRIX: 'Hypothèses'!$C$32
Name h_GAN_PROD: 'Hypothèses'!$C$33
Name h_GAN_DROITS: 'Hypothèses'!$C$34
Name h_GAN_POIDS: 'Hypothèses'!$C$35
Name h_ROU_PRIX: 'Hypothèses'!$C$37
Name h_ROU_PROD: 'Hypothèses'!$C$38
Name h_ROU_DROITS: 'Hypothèses'!$C$39
Name h_ROU_POIDS: 'Hypothèses'!$C$40
Name h_KAP_PRIX: 'Hypothèses'!$C$42
Name h_GK_PRIX: 'Hypothèses'!$C$43
Name h_DUO_PRIX: 'Hypothèses'!$C$44
Name h_HIV_PRIX: 'Hypothèses'!$C$45
Name h_PORT_CLIENT_TTC: 'Hypothèses'!$C$47
Name h_SEUIL_GRATUIT: 'Hypothèses'!$C$48
Name h_PORT_500: 'Hypothèses'!$C$49
Name h_PORT_1KG: 'Hypothèses'!$C$50
Name h_PORT_2KG: 'Hypothèses'!$C$51
Name h_EMB_PETIT: 'Hypothèses'!$C$52
Name h_EMB_GRAND: 'Hypothèses'!$C$53
Name h_STRIPE_PCT: 'Hypothèses'!$C$54
Name h_STRIPE_FIXE: 'Hypothèses'!$C$55
Name h_STRIPE_LITIGE: 'Hypothèses'!$C$56
Name h_PAYPAL_PCT: 'Hypothèses'!$C$57
Name h_PAYPAL_FIXE: 'Hypothèses'!$C$58
Name h_TTS_COMM: 'Hypothèses'!$C$59
Name h_TTS_COMM_LANCEMENT: 'Hypothèses'!$C$60
Name h_CREA_COMM: 'Hypothèses'!$C$61
Name h_PROV_RETOURS: 'Hypothèses'!$C$62
Name h_MIX_AFF: 'Hypothèses'!$C$64
Name h_MIX_PROPRE: 'Hypothèses'!$C$65
Name h_MIX_SITE: 'Hypothèses'!$C$66
Name h_SITE_ROU: 'Hypothèses'!$C$67
Name h_SITE_KAP: 'Hypothèses'!$C$68
Name h_SITE_GK: 'Hypothèses'!$C$69
Name h_SITE_DUO: 'Hypothèses'!$C$70
Name h_TTS_ROU: 'Hypothèses'!$C$71
Name h_TTS_KAP: 'Hypothèses'!$C$72

Sheet Hypothèses
A1: Canapoil — hypothèses du modèle financier
A2: Toutes les valeurs en bleu sont des saisies ; chaque cellule de la colonne C porte un nom défini « h_NOM » utilisé par les autres onglets. Prix et coûts produits = brand.json.
A4: Nom Excel | B4: Hypothèse | C4: Valeur | D4: Unité | E4: Source / confiance
A5: Fiscalité
A6: h_TVA | B6: Taux normal de TVA | C6: 0.2 | D6: % | E6: 03 §3.1 ; https://entreprendre.service-public.gouv.fr/vosdroits/F21746 (vérifié le 01/01/2026)
A7: h_IS_TAUX_REDUIT | B7: IS, taux réduit PME | C7: 0.15 | D7: % | E7: https://entreprendre.service-public.gouv.fr/vosdroits/F23575 ; LF 2026 inchangée : https://hayot-expertise.fr/blog/is-2026-taux-normal-taux-reduit-15-seuils
A8: h_IS_SEUIL | B8: IS, plafond du bénéfice au taux réduit | C8: 42500 | D8: € / exercice | E8: https://entreprendre.service-public.gouv.fr/vosdroits/F23575 ; LF 2026 inchangée : https://hayot-expertise.fr/blog/is-2026-taux-normal-taux-reduit-15-seuils
A9: h_IS_TAUX_NORMAL | B9: IS, taux normal | C9: 0.25 | D9: % | E9: https://entreprendre.service-public.gouv.fr/vosdroits/F23575 ; LF 2026 inchangée : https://hayot-expertise.fr/blog/is-2026-taux-normal-taux-reduit-15-seuils
A10: h_FRANCHISE_SEUIL | B10: Franchise en base de TVA : seuil (CA N-1, ventes) | C10: 85000 | D10: € / an | E10: https://entreprendre.service-public.gouv.fr/vosdroits/F21746 (vérifié le 01/01/2026)
A11: h_FRANCHISE_SEUIL_MAJORE | B11: Franchise en base de TVA : seuil majoré (année en cours) | C11: 93500 | D11: € / an | E11: https://entreprendre.service-public.gouv.fr/vosdroits/F21746 (vérifié le 01/01/2026)
A12: h_MICRO_COTIS | B12: Micro-entreprise : cotisations sociales (ventes) | C12: 0.123 | D12: % du CA | E12: https://entreprendre.service-public.gouv.fr/vosdroits/F32353 (03 §3.6)
A13: h_MICRO_VL | B13: Micro-entreprise : versement libératoire (ventes) | C13: 0.01 | D13: % du CA | E13: https://entreprendre.service-public.gouv.fr/vosdroits/F32353 (03 §3.6)
A14: h_MICRO_PLAFOND | B14: Micro-entreprise : plafond de CA (ventes) | C14: 203100 | D14: € / an | E14: https://entreprendre.service-public.gouv.fr/vosdroits/F32353 (03 §3.6)
A15: h_PFU | B15: Prélèvement forfaitaire unique sur dividendes 2026 (12,8 % + 18,6 %) | C15: 0.314 | D15: % | E15: https://www.lafinancepourtous.com/2025/12/17/csg-un-taux-a-double-vitesse-pour-2026/
A16: h_CHARGES_SASU | B16: Président de SASU : cotisations / salaire net | C16: 0.8 | D16: ratio | E16: Fourchette 75-82 % : https://hayot-expertise.fr/blog/charges-sociales-sasu ; https://www.keobiz.fr/le-mag/sasu-charge-sociale/
A17: h_CHARGES_TNS | B17: Gérant majoritaire d'EURL (TNS) : cotisations / rémunération nette | C17: 0.45 | D17: ratio | E17: Fourchette 33-45 % : https://hayot-expertise.fr/blog/charges-sociales-sasu ; https://www.keobiz.fr/le-mag/sasu-charge-sociale/
... A20: h_HEURES_FONDATEUR | B20: Temps du fondateur | C20: 22.5 | D20: h / semaine | E20: 04 §7 risque 8 : 20-25 h par semaine
A21: Produit CNP-TAP-01 — Tapis de fenêtre thermique (brand.json)
A22: h_TAP_PRIX | B22: Prix de vente | C22: 24.9 | D22: € TTC | E22: strategie/brand.json (12/10/2026)
A23: h_TAP_PROD | B23: Coût produit rendu France (produit + fret entrant) | C23: 5 | D23: € HT | E23: strategie/brand.json (12/10/2026) cout_produit_ht
A24: h_TAP_DROITS | B24: Droits et redevance répartis sur le lot | C24: 0.35 | D24: € HT | E24: strategie/brand.json (12/10/2026) droits_douane_estimes
A25: h_TAP_POIDS | B25: Poids | C25: 400 | D25: g | E25: strategie/brand.json (12/10/2026) poids_g
A26: Produit CNP-RAC-01 — Raclette anti-poils (brand.json)
A27: h_RAC_PRIX | B27: Prix de vente | C27: 12.9 | D27: € TTC | E27: strategie/brand.json (12/10/2026)
A28: h_RAC_PROD | B28: Coût produit rendu France (produit + fret entrant) | C28: 1.9 | D28: € HT | E28: strategie/brand.json (12/10/2026) cout_produit_ht
A29: h_RAC_DROITS | B29: Droits et redevance répartis sur le lot | C29: 0.15 | D29: € HT | E29: strategie/brand.json (12/10/2026) droits_douane_estimes
A30: h_RAC_POIDS | B30: Poids | C30: 150 | D30: g | E30: strategie/brand.json (12/10/2026) poids_g
A31: Produit CNP-GAN-01 — Gant de toilettage (brand.json)
A32: h_GAN_PRIX | B32: Prix de vente | C32: 9.9 | D32: € TTC | E32: strategie/brand.json (12/10/2026)
A33: h_GAN_PROD | B33: Coût produit rendu France (produit + fret entrant) | C33: 1.3 | D33: € HT | E33: strategie/brand.json (12/10/2026) cout_produit_ht
A34: h_GAN_DROITS | B34: Droits et redevance répartis sur le lot | C34: 0.1 | D34: € HT | E34: strategie/brand.json (12/10/2026) droits_douane_estimes
A35: h_GAN_POIDS | B35: Poids | C35: 70 | D35: g | E35: strategie/brand.json (12/10/2026) poids_g
A36: Produit CNP-ROU-01 — Rouleau anti-poils (brand.json)
A37: h_ROU_PRIX | B37: Prix de vente | C37: 24.9 | D37: € TTC | E37: strategie/brand.json (12/10/2026)
A38: h_ROU_PROD | B38: Coût produit rendu France (produit + fret entrant) | C38: 4.5 | D38: € HT | E38: strategie/brand.json (12/10/2026) cout_produit_ht
A39: h_ROU_DROITS | B39: Droits et redevance répartis sur le lot | C39: 0.25 | D39: € HT | E39: strategie/brand.json (12/10/2026) droits_douane_estimes
A40: h_ROU_POIDS | B40: Poids | C40: 280 | D40: g | E40: strategie/brand.json (12/10/2026) poids_g
A41: Kits (brand.json)
A42: h_KAP_PRIX | B42: Kit anti-poils : prix | C42: 29.9 | D42: € TTC | E42: strategie/brand.json (12/10/2026) bundles
A43: h_GK_PRIX | B43: Grand kit : prix | C43: 39.9 | D43: € TTC | E43: strategie/brand.json (12/10/2026) bundles
A44: h_DUO_PRIX | B44: Duo maison + voiture : prix | C44: 39.9 | D44: € TTC | E44: strategie/brand.json (12/10/2026) bundles
A45: h_HIV_PRIX | B45: Kit chat d'hiver : prix | C45: 44.9 | D45: € TTC | E45: strategie/brand.json (12/10/2026) bundles
A46: Livraison, paiement, plateformes
A47: h_PORT_CLIENT_TTC | B47: Frais de port facturés au client sous le seuil | C47: 3.9 | D47: € TTC | E47: strategie/brand.json (12/10/2026) livraison.frais_ttc
A48: h_SEUIL_GRATUIT | B48: Seuil de livraison offerte | C48: 35 | D48: € TTC | E48: strategie/brand.json (12/10/2026) livraison.seuil_gratuite_ttc
A49: h_PORT_500 | B49: Port point relais HT, jusqu'à 500 g | C49: 4.5 | D49: € HT | E49: strategie/brand.json (12/10/2026) hypotheses_cles.port_ht
A50: h_PORT_1KG | B50: Port point relais HT, 500 g à 1 kg | C50: 5.5 | D50: € HT | E50: strategie/brand.json (12/10/2026) hypotheses_cles.port_ht
A51: h_PORT_2KG | B51: Port point relais HT, 1 à 2 kg | C51: 7 | D51: € HT | E51: strategie/brand.json (12/10/2026) hypotheses_cles.port_ht
A52: h_EMB_PETIT | B52: Emballage, colis jusqu'à 500 g | C52: 0.3 | D52: € HT | E52: strategie/brand.json (12/10/2026) cout_emballage_ht
A53: h_EMB_GRAND | B53: Emballage, colis de plus de 500 g | C53: 0.4 | D53: € HT | E53: 04 §4.1 (0,30-0,40 €), estimation, confiance moyenne
A54: h_STRIPE_PCT | B54: Stripe / Shopify Payments : part variable (carte standard EEE) | C54: 0.015 | D54: % | E54: https://stripe.com/fr/pricing
A55: h_STRIPE_FIXE | B55: Stripe / Shopify Payments : part fixe | C55: 0.25 | D55: € | E55: https://stripe.com/fr/pricing
A56: h_STRIPE_LITIGE | B56: Frais de litige Stripe | C56: 20 | D56: € / litige | E56: https://stripe.com/fr/pricing
A57: h_PAYPAL_PCT | B57: PayPal : part variable | C57: 0.029 | D57: % | E57: 03 §4.1 [S26]
A58: h_PAYPAL_FIXE | B58: PayPal : part fixe | C58: 0.35 | D58: € | E58: 03 §4.1 [S26]
... A62: h_PROV_RETOURS | B62: Provision retours, SAV et litiges | C62: 0.05 | D62: % du CA HT | E62: strategie/brand.json (12/10/2026) hypotheses_cles.taux_retour ; 02 §4.1
A63: Mix de ventes
A64: h_MIX_AFF | B64: Part des commandes TikTok Shop par affiliés | C64: 0.58 | D64: % | E64: strategie/brand.json (12/10/2026) canaux.repartition_commandes_hypothese
A65: h_MIX_PROPRE | B65: Part des commandes TikTok Shop en contenu propre | C65: 0.22 | D65: % | E65: strategie/brand.json (12/10/2026)
A66: h_MIX_SITE | B66: Part des commandes du site | C66: 0.2 | D66: % | E66: strategie/brand.json (12/10/2026)
A67: h_SITE_ROU | B67: Site : part Rouleau seul | C67: 0.35 | D67: % | E67: strategie/brand.json (12/10/2026) panier_moyen_ttc_note
A68: h_SITE_KAP | B68: Site : part Kit anti-poils | C68: 0.2 | D68: % | E68: strategie/brand.json (12/10/2026)
A69: h_SITE_GK | B69: Site : part Grand kit | C69: 0.3 | D69: % | E69: strategie/brand.json (12/10/2026)
A70: h_SITE_DUO | B70: Site : part Duo | C70: 0.15 | D70: % | E70: strategie/brand.json (12/10/2026)
A71: h_TTS_ROU | B71: TikTok Shop : part Rouleau seul | C71: 0.7 | D71: % | E71: Estimation finance, confiance faible : seule répartition qui redonne la marge moyenne de 7,55 € de brand.json
A72: h_TTS_KAP | B72: TikTok Shop : part Kit anti-poils | C72: 0.3 | D72: % | E72: Idem
A73: Phase import groupé + 3PL (palier 2)
A74: h_IMP_ROU | B74: Rouleau : coût rendu entrepôt, droits inclus | C74: 2 | D74: € HT | E74: Estimation finance, confiance faible, calée sur 04 §6.4 (Grand kit ≈ 3,80 €)
A75: h_IMP_GAN | B75: Gant : coût rendu entrepôt, droits inclus | C75: 0.65 | D75: € HT | E75: Idem
A76: h_IMP_RAC | B76: Raclette : coût rendu entrepôt, droits inclus | C76: 1.15 | D76: € HT | E76: Idem
A77: h_IMP_TAP | B77: Tapis thermique : coût rendu entrepôt, droits inclus | C77: 2.6 | D77: € HT | E77: Idem
A78: h_TPL_PREP | B78: 3PL : préparation par colis (emballage inclus) | C78: 2.4 | D78: € HT | E78: 03 §5.1 [S52], source faible
A79: h_IMP_FRAIS_MOIS | B79: Import : transitaire, inspection AQL, agent (lissés) | C79: 160 | D79: € / mois | E79: 03 §3.5 et §5.2 : ≈ 400 € par lot tous les 2,5 mois, estimation
A80: h_TPL_STOCKAGE | B80: 3PL : stockage | C80: 50 | D80: € / mois | E80: 03 §5.1 : 10-25 € par palette, estimation
A81: Publicité
A82: h_CPA_REALISTE | B82: CPA scénario réaliste (Grand kit, Meta) | C82: 21 | D82: € | E82: Entre favorable (10,67 €) et central (30 €) de 02 §5.3 D ; estimation, confiance faible
A83: h_CPA_OPTIMISTE | B83: CPA scénario optimiste | C83: 14 | D83: € | E83: Idem, créatives du premier quartile
A84: h_MER_MARGE | B84: Marge de sécurité exigée sur le MER de rentabilité | C84: 1.2 | D84: × | E84: 02 §5.2
A85: Frais fixes et ponctuels
A86: h_COMPTABLE | B86: Expert-comptable en ligne, société à l'IS (lancement) | C86: 90 | D86: € / mois | E86: 03 §0.4 : 1 000-2 500 € par an ; bas de fourchette
A87: h_COMPTABLE_P2 | B87: Expert-comptable, phase import et publicité | C87: 200 | D87: € / mois | E87: Estimation, confiance moyenne
A88: h_BANQUE | B88: Compte bancaire professionnel | C88: 10 | D88: € / mois | E88: Estimation
A89: h_OUTILS | B89: Plateforme de facturation électronique, outils | C89: 10 | D89: € / mois | E89: 03 §0.5 : 0-15 € par mois
A90: h_RC | B90: Assurance RC professionnelle et produits | C90: 25 | D90: € / mois | E90: 03 §0.5 : 150-500 € par an
A91: h_DOMICILIATION | B91: Domiciliation avec réception de colis (dès 150 commandes / mois) | C91: 25 | D91: € / mois | E91: 03 §5.5 : 15-40 € par mois
A92: h_SHOPIFY_ESSAI | B92: Shopify, 3 premiers mois (1 $) | C92: 0.86 | D92: € / mois | E92: https://speed-ecom.eu/blog/combien-coute-reellement-shopify/
A93: h_SHOPIFY_BASIC | B93: Shopify Basic | C93: 36 | D93: € / mois | E93: https://speed-ecom.eu/blog/combien-coute-reellement-shopify/
A94: h_SHOPIFY_GROW | B94: Shopify Grow | C94: 105 | D94: € / mois | E94: 04 §5.2
A95: h_SHOPIFY_GROW_SEUIL | B95: CA HT mensuel à partir duquel Grow est retenu | C95: 34500 | D95: € | E95: 04 §5.2
A96: h_APPS | B96: Applications Shopify (avis, e-mail) | C96: 50 | D96: € / mois | E96: Estimation
A97: h_ASSISTANT | B97: Assistant SAV à mi-temps, coût employeur (dès 1 000 commandes / mois) | C97: 1300 | D97: € / mois | E97: Estimation, confiance moyenne
... A106: h_ECH_UNIT | B106: Coût d'un échantillon envoyé à un créateur | C106: 12 | D106: € | E106: 02 §3.6, central
A107: Trésorerie
A108: h_TRESO_INITIALE | B108: Trésorerie de départ affectée au projet | C108: 0 | D108: € | E108: Hypothèse « 0 € » du client
A109: h_STRIPE_DELAI_INITIAL | B109: Stripe : délai du premier versement | C109: 7 | D109: jours | E109: https://docs.stripe.com/payouts (France : 7 jours calendaires au premier versement, 3 jours ouvrés ensuite)
A110: h_STRIPE_DELAI | B110: Stripe / Shopify Payments : délai courant (3 jours ouvrés) | C110: 5 | D110: jours calendaires | E110: https://docs.stripe.com/payouts (France : 7 jours calendaires au premier versement, 3 jours ouvrés ensuite)
A111: h_PAYPAL_RETENUE | B111: PayPal : retenue possible des premiers paiements | C111: 21 | D111: jours | E111: https://www.paypal.com/fr/brc/article/funds-availability
A112: h_TTS_LIVRAISON | B112: TikTok Shop : délai commande → livraison | C112: 4 | D112: jours | E112: 02 §1.3 (livraison sous 4 jours ouvrés)
A113: h_TTS_DEBUTANT | B113: TikTok Shop : règlement d'un vendeur débutant | C113: 31 | D113: jours après livraison | E113: https://seller-fr.tiktok.com/university/essay?knowledge_id=747695670282004 (page du 09/10/2026)
A114: h_TTS_STANDARD | B114: TikTok Shop : règlement standard | C114: 8 | D114: jours après livraison | E114: https://seller-fr.tiktok.com/university/essay?knowledge_id=747695670282004 (page du 09/10/2026)
...

Sheet Unit economics
A1: Unit economics par commande (€)
A2: Marge de contribution = CA HT − coûts variables (produit, droits, livraison, paiement, commissions, provision 5 % du CA HT). En franchise et en micro-entreprise, le CA est le prix payé et les coûts portent la TVA non récupérable (×1,2), sauf les frais de paiement.
A4: Société assujettie à la TVA (SASU ou EURL à l'IS) — micro-stock en France (lancement)
A5: Cas | B5: Canal | C5: Poids (g) | D5: Prix payé TTC | E5: TVA collectée | F5: CA HT (base) | G5: Coût produit | H5: Droits de douane | I5: Livraison + emballage | J5: Frais de paiement | K5: Commission TikTok Shop | L5: Commission créateur ou pub | M5: Provision retours / litiges | N5: Cotisations micro | O5: Marge de contribution | P5: % du CA HT | Q5: ROAS de rentabilité HT | R5: ROAS de rentabilité TTC | S5: CPA maximal
A6: Site — Rouleau seul (+3,90 € de port) | B6: Site | C6: =h_ROU_POIDS | D6: =h_ROU_PRIX+IF(h_ROU_PRIX<h_SEUIL_GRATUIT,h_PORT_CLIENT_TTC,0) | E6: =D6-D6/(1+h_TVA) | F6: =D6-E6 | G6: =(h_ROU_PROD) | H6: =(h_ROU_DROITS) | I6: =IF(C6<=500,h_PORT_500+h_EMB_PETIT,IF(C6<=1000,h_PORT_1KG+h_EMB_GRAND,h_PORT_2KG+h_EMB_GRAND)) | J6: =h_STRIPE_PCT*D6+h_STRIPE_FIXE | K6: =0 | L6: =0 | M6: =h_PROV_RETOURS*F6 | N6: =0 | O6: =F6-SUM(G6:N6) | P6: =O6/F6 | Q6: =F6/O6 | R6: =D6/O6 | S6: =O6
A7: Site — Gant seul (+3,90 € de port) | B7: Site | C7: =h_GAN_POIDS | D7: =h_GAN_PRIX+IF(h_GAN_PRIX<h_SEUIL_GRATUIT,h_PORT_CLIENT_TTC,0) | E7: =D7-D7/(1+h_TVA) | F7: =D7-E7 | G7: =(h_GAN_PROD) | H7: =(h_GAN_DROITS) | I7: =IF(C7<=500,h_PORT_500+h_EMB_PETIT,IF(C7<=1000,h_PORT_1KG+h_EMB_GRAND,h_PORT_2KG+h_EMB_GRAND)) | J7: =h_STRIPE_PCT*D7+h_STRIPE_FIXE | K7: =0 | L7: =0 | M7: =h_PROV_RETOURS*F7 | N7: =0 | O7: =F7-SUM(G7:N7) | P7: =O7/F7 | Q7: =F7/O7 | R7: =D7/O7 | S7: =O7
A8: Site — Raclette seule (+3,90 € de port) | B8: Site | C8: =h_RAC_POIDS | D8: =h_RAC_PRIX+IF(h_RAC_PRIX<h_SEUIL_GRATUIT,h_PORT_CLIENT_TTC,0) | E8: =D8-D8/(1+h_TVA) | F8: =D8-E8 | G8: =(h_RAC_PROD) | H8: =(h_RAC_DROITS) | I8: =IF(C8<=500,h_PORT_500+h_EMB_PETIT,IF(C8<=1000,h_PORT_1KG+h_EMB_GRAND,h_PORT_2KG+h_EMB_GRAND)) | J8: =h_STRIPE_PCT*D8+h_STRIPE_FIXE | K8: =0 | L8: =0 | M8: =h_PROV_RETOURS*F8 | N8: =0 | O8: =F8-SUM(G8:N8) | P8: =O8/F8 | Q8: =F8/O8 | R8: =D8/O8 | S8: =O8
A9: Site — Tapis thermique seul (+3,90 € de port) | B9: Site | C9: =h_TAP_POIDS | D9: =h_TAP_PRIX+IF(h_TAP_PRIX<h_SEUIL_GRATUIT,h_PORT_CLIENT_TTC,0) | E9: =D9-D9/(1+h_TVA) | F9: =D9-E9 | G9: =(h_TAP_PROD) | H9: =(h_TAP_DROITS) | I9: =IF(C9<=500,h_PORT_500+h_EMB_PETIT,IF(C9<=1000,h_PORT_1KG+h_EMB_GRAND,h_PORT_2KG+h_EMB_GRAND)) | J9: =h_STRIPE_PCT*D9+h_STRIPE_FIXE | K9: =0 | L9: =0 | M9: =h_PROV_RETOURS*F9 | N9: =0 | O9: =F9-SUM(G9:N9) | P9: =O9/F9 | Q9: =F9/O9 | R9: =D9/O9 | S9: =O9
A10: Site — Kit anti-poils (+3,90 € de port) | B10: Site | C10: =h_ROU_POIDS+h_GAN_POIDS | D10: =h_KAP_PRIX+IF(h_KAP_PRIX<h_SEUIL_GRATUIT,h_PORT_CLIENT_TTC,0) | E10: =D10-D10/(1+h_TVA) | F10: =D10-E10 | G10: =(h_ROU_PROD+h_GAN_PROD) | H10: =(h_ROU_DROITS+h_GAN_DROITS) | I10: =IF(C10<=500,h_PORT_500+h_EMB_PETIT,IF(C10<=1000,h_PORT_1KG+h_EMB_GRAND,h_PORT_2KG+h_EMB_GRAND)) | J10: =h_STRIPE_PCT*D10+h_STRIPE_FIXE | K10: =0 | L10: =0 | M10: =h_PROV_RETOURS*F10 | N10: =0 | O10: =F10-SUM(G10:N10) | P10: =O10/F10 | Q10: =F10/O10 | R10: =D10/O10 | S10: =O10
A11: Site — Grand kit (port offert) | B11: Site | C11: =h_ROU_POIDS+h_RAC_POIDS+h_GAN_POIDS | D11: =h_GK_PRIX+IF(h_GK_PRIX<h_SEUIL_GRATUIT,h_PORT_CLIENT_TTC,0) | E11: =D11-D11/(1+h_TVA) | F11: =D11-E11 | G11: =(h_ROU_PROD+h_RAC_PROD+h_GAN_PROD) | H11: =(h_ROU_DROITS+h_RAC_DROITS+h_GAN_DROITS) | I11: =IF(C11<=500,h_PORT_500+h_EMB_PETIT,IF(C11<=1000,h_PORT_1KG+h_EMB_GRAND,h_PORT_2KG+h_EMB_GRAND)) | J11: =h_STRIPE_PCT*D11+h_STRIPE_FIXE | K11: =0 | L11: =0 | M11: =h_PROV_RETOURS*F11 | N11: =0 | O11: =F11-SUM(G11:N11) | P11: =O11/F11 | Q11: =F11/O11 | R11: =D11/O11 | S11: =O11
A12: Site — Duo 2 rouleaux (port offert) | B12: Site | C12: =h_ROU_POIDS+h_ROU_POIDS | D12: =h_DUO_PRIX+IF(h_DUO_PRIX<h_SEUIL_GRATUIT,h_PORT_CLIENT_TTC,0) | E12: =D12-D12/(1+h_TVA) | F12: =D12-E12 | G12: =(h_ROU_PROD+h_ROU_PROD) | H12: =(h_ROU_DROITS+h_ROU_DROITS) | I12: =IF(C12<=500,h_PORT_500+h_EMB_PETIT,IF(C12<=1000,h_PORT_1KG+h_EMB_GRAND,h_PORT_2KG+h_EMB_GRAND)) | J12: =h_STRIPE_PCT*D12+h_STRIPE_FIXE | K12: =0 | L12: =0 | M12: =h_PROV_RETOURS*F12 | N12: =0 | O12: =F12-SUM(G12:N12) | P12: =O12/F12 | Q12: =F12/O12 | R12: =D12/O12 | S12: =O12
A13: Site — Kit chat d'hiver (port offert) | B13: Site | C13: =h_ROU_POIDS+h_TAP_POIDS | D13: =h_HIV_PRIX+IF(h_HIV_PRIX<h_SEUIL_GRATUIT,h_PORT_CLIENT_TTC,0) | E13: =D13-D13/(1+h_TVA) | F13: =D13-E13 | G13: =(h_ROU_PROD+h_TAP_PROD) | H13: =(h_ROU_DROITS+h_TAP_DROITS) | I13: =IF(C13<=500,h_PORT_500+h_EMB_PETIT,IF(C13<=1000,h_PORT_1KG+h_EMB_GRAND,h_PORT_2KG+h_EMB_GRAND)) | J13: =h_STRIPE_PCT*D13+h_STRIPE_FIXE | K13: =0 | L13: =0 | M13: =h_PROV_RETOURS*F13 | N13: =0 | O13: =F13-SUM(G13:N13) | P13: =O13/F13 | Q13: =F13/O13 | R13: =D13/O13 | S13: =O13
A14: TikTok Shop, contenu propre — Rouleau | B14: TikTok Shop | C14: =h_ROU_POIDS | D14: =h_ROU_PRIX | E14: =D14-D14/(1+h_TVA) | F14: =D14-E14 | G14: =(h_ROU_PROD) | H14: =(h_ROU_DROITS) | I14: =IF(C14<=500,h_PORT_500+h_EMB_PETIT,IF(C14<=1000,h_PORT_1KG+h_EMB_GRAND,h_PORT_2KG+h_EMB_GRAND)) | J14: =0 | K14: =h_TTS_COMM*D14 | L14: =0 | M14: =h_PROV_RETOURS*F14 | N14: =0 | O14: =F14-SUM(G14:N14) | P14: =O14/F14 | Q14: =F14/O14 | R14: =D14/O14 | S14: =O14
A15: TikTok Shop, contenu propre — Kit anti-poils | B15: TikTok Shop | C15: =h_ROU_POIDS+h_GAN_POIDS | D15: =h_KAP_PRIX | E15: =D15-D15/(1+h_TVA) | F15: =D15-E15 | G15: =(h_ROU_PROD+h_GAN_PROD) | H15: =(h_ROU_DROITS+h_GAN_DROITS) | I15: =IF(C15<=500,h_PORT_500+h_EMB_PETIT,IF(C15<=1000,h_PORT_1KG+h_EMB_GRAND,h_PORT_2KG+h_EMB_GRAND)) | J15: =0 | K15: =h_TTS_COMM*D15 | L15: =0 | M15: =h_PROV_RETOURS*F15 | N15: =0 | O15: =F15-SUM(G15:N15) | P15: =O15/F15 | Q15: =F15/O15 | R15: =D15/O15 | S15: =O15
A16: TikTok Shop, contenu propre, commission 4 % — Rouleau | B16: TikTok Shop | C16: =h_ROU_POIDS | D16: =h_ROU_PRIX | E16: =D16-D16/(1+h_TVA) | F16: =D16-E16 | G16: =(h_ROU_PROD) | H16: =(h_ROU_DROITS) | I16: =IF(C16<=500,h_PORT_500+h_EMB_PETIT,IF(C16<=1000,h_PORT_1KG+h_EMB_GRAND,h_PORT_2KG+h_EMB_GRAND)) | J16: =0 | K16: =h_TTS_COMM_LANCEMENT*D16 | L16: =0 | M16: =h_PROV_RETOURS*F16 | N16: =0 | O16: =F16-SUM(G16:N16) | P16: =O16/F16 | Q16: =F16/O16 | R16: =D16/O16 | S16: =O16
A17: TikTok Shop, affilié 15 % — Rouleau | B17: TikTok Shop | C17: =h_ROU_POIDS | D17: =h_ROU_PRIX | E17: =D17-D17/(1+h_TVA) | F17: =D17-E17 | G17: =(h_ROU_PROD) | H17: =(h_ROU_DROITS) | I17: =IF(C17<=500,h_PORT_500+h_EMB_PETIT,IF(C17<=1000,h_PORT_1KG+h_EMB_GRAND,h_PORT_2KG+h_EMB_GRAND)) | J17: =0 | K17: =h_TTS_COMM*D17 | L17: =h_CREA_COMM*D17 | M17: =h_PROV_RETOURS*F17 | N17: =0 | O17: =F17-SUM(G17:N17) | P17: =O17/F17
A18: TikTok Shop, affilié 15 % — Kit anti-poils | B18: TikTok Shop | C18: =h_ROU_POIDS+h_GAN_POIDS | D18: =h_KAP_PRIX | E18: =D18-D18/(1+h_TVA) | F18: =D18-E18 | G18: =(h_ROU_PROD+h_GAN_PROD) | H18: =(h_ROU_DROITS+h_GAN_DROITS) | I18: =IF(C18<=500,h_PORT_500+h_EMB_PETIT,IF(C18<=1000,h_PORT_1KG+h_EMB_GRAND,h_PORT_2KG+h_EMB_GRAND)) | J18: =0 | K18: =h_TTS_COMM*D18 | L18: =h_CREA_COMM*D18 | M18: =h_PROV_RETOURS*F18 | N18: =0 | O18: =F18-SUM(G18:N18) | P18: =O18/F18
A19: Site — Grand kit si le colis dépasse 500 g emballage compris | B19: Site | C19: =h_ROU_POIDS+h_RAC_POIDS+h_GAN_POIDS | D19: =h_GK_PRIX+IF(h_GK_PRIX<h_SEUIL_GRATUIT,h_PORT_CLIENT_TTC,0) | E19: =D19-D19/(1+h_TVA) | F19: =D19-E19 | G19: =(h_ROU_PROD+h_RAC_PROD+h_GAN_PROD) | H19: =(h_ROU_DROITS+h_RAC_DROITS+h_GAN_DROITS) | I19: =(h_PORT_1KG+h_EMB_GRAND) | J19: =h_STRIPE_PCT*D19+h_STRIPE_FIXE | K19: =0 | L19: =0 | M19: =h_PROV_RETOURS*F19 | N19: =0 | O19: =F19-SUM(G19:N19) | P19: =O19/F19 | Q19: =F19/O19 | R19: =D19/O19 | S19: =O19
A21: Société assujettie — import groupé + 3PL (palier 2)
A22: Cas | B22: Canal | C22: Poids (g) | D22: Prix payé TTC | E22: TVA collectée | F22: CA HT (base) | G22: Coût produit | H22: Droits de douane | I22: Livraison + emballage | J22: Frais de paiement | K22: Commission TikTok Shop | L22: Commission créateur ou pub | M22: Provision retours / litiges | N22: Cotisations micro | O22: Marge de contribution | P22: % du CA HT | Q22: ROAS de rentabilité HT | R22: ROAS de rentabilité TTC | S22: CPA maximal
A23: Site — Rouleau seul | B23: Site | C23: =h_ROU_POIDS | D23: =h_ROU_PRIX+IF(h_ROU_PRIX<h_SEUIL_GRATUIT,h_PORT_CLIENT_TTC,0) | E23: =D23-D23/(1+h_TVA) | F23: =D23-E23 | G23: =h_IMP_ROU | H23: =0 | I23: =IF(C23<=500,h_PORT_500,IF(C23<=1000,h_PORT_1KG,h_PORT_2KG))+h_TPL_PREP | J23: =h_STRIPE_PCT*D23+h_STRIPE_FIXE | K23: =0 | L23: =0 | M23: =h_PROV_RETOURS*F23 | N23: =0 | O23: =F23-SUM(G23:N23) | P23: =O23/F23 | Q23: =F23/O23 | R23: =D23/O23 | S23: =O23
A24: Site — Kit anti-poils | B24: Site | C24: =h_ROU_POIDS+h_GAN_POIDS | D24: =h_KAP_PRIX+IF(h_KAP_PRIX<h_SEUIL_GRATUIT,h_PORT_CLIENT_TTC,0) | E24: =D24-D24/(1+h_TVA) | F24: =D24-E24 | G24: =h_IMP_ROU+h_IMP_GAN | H24: =0 | I24: =IF(C24<=500,h_PORT_500,IF(C24<=1000,h_PORT_1KG,h_PORT_2KG))+h_TPL_PREP | J24: =h_STRIPE_PCT*D24+h_STRIPE_FIXE | K24: =0 | L24: =0 | M24: =h_PROV_RETOURS*F24 | N24: =0 | O24: =F24-SUM(G24:N24) | P24: =O24/F24 | Q24: =F24/O24 | R24: =D24/O24 | S24: =O24
A25: Site — Grand kit | B25: Site | C25: =h_ROU_POIDS+h_RAC_POIDS+h_GAN_POIDS | D25: =h_GK_PRIX+IF(h_GK_PRIX<h_SEUIL_GRATUIT,h_PORT_CLIENT_TTC,0) | E25: =D25-D25/(1+h_TVA) | F25: =D25-E25 | G25: =h_IMP_ROU+h_IMP_RAC+h_IMP_GAN | H25: =0 | I25: =IF(C25<=500,h_PORT_500,IF(C25<=1000,h_PORT_1KG,h_PORT_2KG))+h_TPL_PREP | J25: =h_STRIPE_PCT*D25+h_STRIPE_FIXE | K25: =0 | L25: =0 | M25: =h_PROV_RETOURS*F25 | N25: =0 | O25: =F25-SUM(G25:N25) | P25: =O25/F25 | Q25: =F25/O25 | R25: =D25/O25 | S25: =O25
A26: Site — Duo 2 rouleaux | B26: Site | C26: =h_ROU_POIDS+h_ROU_POIDS | D26: =h_DUO_PRIX+IF(h_DUO_PRIX<h_SEUIL_GRATUIT,h_PORT_CLIENT_TTC,0) | E26: =D26-D26/(1+h_TVA) | F26: =D26-E26 | G26: =h_IMP_ROU+h_IMP_ROU | H26: =0 | I26: =IF(C26<=500,h_PORT_500,IF(C26<=1000,h_PORT_1KG,h_PORT_2KG))+h_TPL_PREP | J26: =h_STRIPE_PCT*D26+h_STRIPE_FIXE | K26: =0 | L26: =0 | M26: =h_PROV_RETOURS*F26 | N26: =0 | O26: =F26-SUM(G26:N26) | P26: =O26/F26 | Q26: =F26/O26 | R26: =D26/O26 | S26: =O26
A27: TikTok Shop, contenu propre — Rouleau | B27: TikTok Shop | C27: =h_ROU_POIDS | D27: =h_ROU_PRIX | E27: =D27-D27/(1+h_TVA) | F27: =D27-E27 | G27: =h_IMP_ROU | H27: =0 | I27: =IF(C27<=500,h_PORT_500,IF(C27<=1000,h_PORT_1KG,h_PORT_2KG))+h_TPL_PREP | J27: =0 | K27: =h_TTS_COMM*D27 | L27: =0 | M27: =h_PROV_RETOURS*F27 | N27: =0 | O27: =F27-SUM(G27:N27) | P27: =O27/F27 | Q27: =F27/O27 | R27: =D27/O27 | S27: =O27
A28: TikTok Shop, contenu propre — Kit anti-poils | B28: TikTok Shop | C28: =h_ROU_POIDS+h_GAN_POIDS | D28: =h_KAP_PRIX | E28: =D28-D28/(1+h_TVA) | F28: =D28-E28 | G28: =h_IMP_ROU+h_IMP_GAN | H28: =0 | I28: =IF(C28<=500,h_PORT_500,IF(C28<=1000,h_PORT_1KG,h_PORT_2KG))+h_TPL_PREP | J28: =0 | K28: =h_TTS_COMM*D28 | L28: =0 | M28: =h_PROV_RETOURS*F28 | N28: =0 | O28: =F28-SUM(G28:N28) | P28: =O28/F28 | Q28: =F28/O28 | R28: =D28/O28 | S28: =O28
A29: TikTok Shop, affilié — Rouleau | B29: TikTok Shop | C29: =h_ROU_POIDS | D29: =h_ROU_PRIX | E29: =D29-D29/(1+h_TVA) | F29: =D29-E29 | G29: =h_IMP_ROU | H29: =0 | I29: =IF(C29<=500,h_PORT_500,IF(C29<=1000,h_PORT_1KG,h_PORT_2KG))+h_TPL_PREP | J29: =0 | K29: =h_TTS_COMM*D29 | L29: =h_CREA_COMM*D29 | M29: =h_PROV_RETOURS*F29 | N29: =0 | O29: =F29-SUM(G29:N29) | P29: =O29/F29
A30: TikTok Shop, affilié — Kit anti-poils | B30: TikTok Shop | C30: =h_ROU_POIDS+h_GAN_POIDS | D30: =h_KAP_PRIX | E30: =D30-D30/(1+h_TVA) | F30: =D30-E30 | G30: =h_IMP_ROU+h_IMP_GAN | H30: =0 | I30: =IF(C30<=500,h_PORT_500,IF(C30<=1000,h_PORT_1KG,h_PORT_2KG))+h_TPL_PREP | J30: =0 | K30: =h_TTS_COMM*D30 | L30: =h_CREA_COMM*D30 | M30: =h_PROV_RETOURS*F30 | N30: =0 | O30: =F30-SUM(G30:N30) | P30: =O30/F30
A31: Site, publicité au CPA réaliste — Grand kit | B31: Site + publicité | C31: =h_ROU_POIDS+h_RAC_POIDS+h_GAN_POIDS | D31: =h_GK_PRIX+IF(h_GK_PRIX<h_SEUIL_GRATUIT,h_PORT_CLIENT_TTC,0) | E31: =D31-D31/(1+h_TVA) | F31: =D31-E31 | G31: =h_IMP_ROU+h_IMP_RAC+h_IMP_GAN | H31: =0 | I31: =IF(C31<=500,h_PORT_500,IF(C31<=1000,h_PORT_1KG,h_PORT_2KG))+h_TPL_PREP | J31: =h_STRIPE_PCT*D31+h_STRIPE_FIXE | K31: =0 | L31: =h_CPA_REALISTE | M31: =h_PROV_RETOURS*F31 | N31: =0 | O31: =F31-SUM(G31:N31) | P31: =O31/F31 | Q31: =F31/(O31+L31) | R31: =D31/(O31+L31) | S31: =(O31+L31)
A32: Site, publicité au CPA optimiste — Grand kit | B32: Site + publicité | C32: =h_ROU_POIDS+h_RAC_POIDS+h_GAN_POIDS | D32: =h_GK_PRIX+IF(h_GK_PRIX<h_SEUIL_GRATUIT,h_PORT_CLIENT_TTC,0) | E32: =D32-D32/(1+h_TVA) | F32: =D32-E32 | G32: =h_IMP_ROU+h_IMP_RAC+h_IMP_GAN | H32: =0 | I32: =IF(C32<=500,h_PORT_500,IF(C32<=1000,h_PORT_1KG,h_PORT_2KG))+h_TPL_PREP | J32: =h_STRIPE_PCT*D32+h_STRIPE_FIXE | K32: =0 | L32: =h_CPA_OPTIMISTE | M32: =h_PROV_RETOURS*F32 | N32: =0 | O32: =F32-SUM(G32:N32) | P32: =O32/F32 | Q32: =F32/(O32+L32) | R32: =D32/(O32+L32) | S32: =(O32+L32)
A34: Société en franchise en base de TVA — micro-stock
A35: Cas | B35: Canal | C35: Poids (g) | D35: Prix payé TTC | E35: TVA collectée | F35: CA HT (base) | G35: Coût produit | H35: Droits de douane | I35: Livraison + emballage | J35: Frais de paiement | K35: Commission TikTok Shop | L35: Commission créateur ou pub | M35: Provision retours / litiges | N35: Cotisations micro | O35: Marge de contribution | P35: % du CA HT | Q35: ROAS de rentabilité HT | R35: ROAS de rentabilité TTC | S35: CPA maximal
A36: Site — Rouleau seul (+3,90 € de port) | B36: Site | C36: =h_ROU_POIDS | D36: =h_ROU_PRIX+IF(h_ROU_PRIX<h_SEUIL_GRATUIT,h_PORT_CLIENT_TTC,0) | E36: =0 | F36: =D36-E36 | G36: =(h_ROU_PROD)*(1+h_TVA) | H36: =(h_ROU_DROITS)*(1+h_TVA) | I36: =IF(C36<=500,h_PORT_500+h_EMB_PETIT,IF(C36<=1000,h_PORT_1KG+h_EMB_GRAND,h_PORT_2KG+h_EMB_GRAND))*(1+h_TVA) | J36: =h_STRIPE_PCT*D36+h_STRIPE_FIXE | K36: =0 | L36: =0 | M36: =h_PROV_RETOURS*F36 | N36: =0 | O36: =F36-SUM(G36:N36) | P36: =O36/F36 | Q36: =F36/O36 | R36: =D36/O36 | S36: =O36
A37: Site — Kit anti-poils (+3,90 € de port) | B37: Site | C37: =h_ROU_POIDS+h_GAN_POIDS | D37: =h_KAP_PRIX+IF(h_KAP_PRIX<h_SEUIL_GRATUIT,h_PORT_CLIENT_TTC,0) | E37: =0 | F37: =D37-E37 | G37: =(h_ROU_PROD+h_GAN_PROD)*(1+h_TVA) | H37: =(h_ROU_DROITS+h_GAN_DROITS)*(1+h_TVA) | I37: =IF(C37<=500,h_PORT_500+h_EMB_PETIT,IF(C37<=1000,h_PORT_1KG+h_EMB_GRAND,h_PORT_2KG+h_EMB_GRAND))*(1+h_TVA) | J37: =h_STRIPE_PCT*D37+h_STRIPE_FIXE | K37: =0 | L37: =0 | M37: =h_PROV_RETOURS*F37 | N37: =0 | O37: =F37-SUM(G37:N37) | P37: =O37/F37 | Q37: =F37/O37 | R37: =D37/O37 | S37: =O37
A38: Site — Grand kit (port offert) | B38: Site | C38: =h_ROU_POIDS+h_RAC_POIDS+h_GAN_POIDS | D38: =h_GK_PRIX+IF(h_GK_PRIX<h_SEUIL_GRATUIT,h_PORT_CLIENT_TTC,0) | E38: =0 | F38: =D38-E38 | G38: =(h_ROU_PROD+h_RAC_PROD+h_GAN_PROD)*(1+h_TVA) | H38: =(h_ROU_DROITS+h_RAC_DROITS+h_GAN_DROITS)*(1+h_TVA) | I38: =IF(C38<=500,h_PORT_500+h_EMB_PETIT,IF(C38<=1000,h_PORT_1KG+h_EMB_GRAND,h_PORT_2KG+h_EMB_GRAND))*(1+h_TVA) | J38: =h_STRIPE_PCT*D38+h_STRIPE_FIXE | K38: =0 | L38: =0 | M38: =h_PROV_RETOURS*F38 | N38: =0 | O38: =F38-SUM(G38:N38) | P38: =O38/F38 | Q38: =F38/O38 | R38: =D38/O38 | S38: =O38
A39: Site — Duo 2 rouleaux (port offert) | B39: Site | C39: =h_ROU_POIDS+h_ROU_POIDS | D39: =h_DUO_PRIX+IF(h_DUO_PRIX<h_SEUIL_GRATUIT,h_PORT_CLIENT_TTC,0) | E39: =0 | F39: =D39-E39 | G39: =(h_ROU_PROD+h_ROU_PROD)*(1+h_TVA) | H39: =(h_ROU_DROITS+h_ROU_DROITS)*(1+h_TVA) | I39: =IF(C39<=500,h_PORT_500+h_EMB_PETIT,IF(C39<=1000,h_PORT_1KG+h_EMB_GRAND,h_PORT_2KG+h_EMB_GRAND))*(1+h_TVA) | J39: =h_STRIPE_PCT*D39+h_STRIPE_FIXE | K39: =0 | L39: =0 | M39: =h_PROV_RETOURS*F39 | N39: =0 | O39: =F39-SUM(G39:N39) | P39: =O39/F39 | Q39: =F39/O39 | R39: =D39/O39 | S39: =O39
A40: TikTok Shop, contenu propre — Rouleau | B40: TikTok Shop | C40: =h_ROU_POIDS | D40: =h_ROU_PRIX | E40: =0 | F40: =D40-E40 | G40: =(h_ROU_PROD)*(1+h_TVA) | H40: =(h_ROU_DROITS)*(1+h_TVA) | I40: =IF(C40<=500,h_PORT_500+h_EMB_PETIT,IF(C40<=1000,h_PORT_1KG+h_EMB_GRAND,h_PORT_2KG+h_EMB_GRAND))*(1+h_TVA) | J40: =0 | K40: =h_TTS_COMM*D40*(1+h_TVA) | L40: =0 | M40: =h_PROV_RETOURS*F40 | N40: =0 | O40: =F40-SUM(G40:N40) | P40: =O40/F40 | Q40: =F40/O40 | R40: =D40/O40 | S40: =O40
A41: TikTok Shop, contenu propre — Kit anti-poils | B41: TikTok Shop | C41: =h_ROU_POIDS+h_GAN_POIDS | D41: =h_KAP_PRIX | E41: =0 | F41: =D41-E41 | G41: =(h_ROU_PROD+h_GAN_PROD)*(1+h_TVA) | H41: =(h_ROU_DROITS+h_GAN_DROITS)*(1+h_TVA) | I41: =IF(C41<=500,h_PORT_500+h_EMB_PETIT,IF(C41<=1000,h_PORT_1KG+h_EMB_GRAND,h_PORT_2KG+h_EMB_GRAND))*(1+h_TVA) | J41: =0 | K41: =h_TTS_COMM*D41*(1+h_TVA) | L41: =0 | M41: =h_PROV_RETOURS*F41 | N41: =0 | O41: =F41-SUM(G41:N41) | P41: =O41/F41 | Q41: =F41/O41 | R41: =D41/O41 | S41: =O41
A42: TikTok Shop, affilié 15 % — Rouleau | B42: TikTok Shop | C42: =h_ROU_POIDS | D42: =h_ROU_PRIX | E42: =0 | F42: =D42-E42 | G42: =(h_ROU_PROD)*(1+h_TVA) | H42: =(h_ROU_DROITS)*(1+h_TVA) | I42: =IF(C42<=500,h_PORT_500+h_EMB_PETIT,IF(C42<=1000,h_PORT_1KG+h_EMB_GRAND,h_PORT_2KG+h_EMB_GRAND))*(1+h_TVA) | J42: =0 | K42: =h_TTS_COMM*D42*(1+h_TVA) | L42: =h_CREA_COMM*D42*(1+h_TVA) | M42: =h_PROV_RETOURS*F42 | N42: =0 | O42: =F42-SUM(G42:N42) | P42: =O42/F42
A43: TikTok Shop, affilié 15 % — Kit anti-poils | B43: TikTok Shop | C43: =h_ROU_POIDS+h_GAN_POIDS | D43: =h_KAP_PRIX | E43: =0 | F43: =D43-E43 | G43: =(h_ROU_PROD+h_GAN_PROD)*(1+h_TVA) | H43: =(h_ROU_DROITS+h_GAN_DROITS)*(1+h_TVA) | I43: =IF(C43<=500,h_PORT_500+h_EMB_PETIT,IF(C43<=1000,h_PORT_1KG+h_EMB_GRAND,h_PORT_2KG+h_EMB_GRAND))*(1+h_TVA) | J43: =0 | K43: =h_TTS_COMM*D43*(1+h_TVA) | L43: =h_CREA_COMM*D43*(1+h_TVA) | M43: =h_PROV_RETOURS*F43 | N43: =0 | O43: =F43-SUM(G43:N43) | P43: =O43/F43
A45: Micro-entreprise en franchise de TVA — micro-stock (après cotisations de 12,3 %)
A46: Cas | B46: Canal | C46: Poids (g) | D46: Prix payé TTC | E46: TVA collectée | F46: CA HT (base) | G46: Coût produit | H46: Droits de douane | I46: Livraison + emballage | J46: Frais de paiement | K46: Commission TikTok Shop | L46: Commission créateur ou pub | M46: Provision retours / litiges | N46: Cotisations micro | O46: Marge de contribution | P46: % du CA HT | Q46: ROAS de rentabilité HT | R46: ROAS de rentabilité TTC | S46: CPA maximal
A47: Site — Rouleau seul (+3,90 € de port) | B47: Site | C47: =h_ROU_POIDS | D47: =h_ROU_PRIX+IF(h_ROU_PRIX<h_SEUIL_GRATUIT,h_PORT_CLIENT_TTC,0) | E47: =0 | F47: =D47-E47 | G47: =(h_ROU_PROD)*(1+h_TVA) | H47: =(h_ROU_DROITS)*(1+h_TVA) | I47: =IF(C47<=500,h_PORT_500+h_EMB_PETIT,IF(C47<=1000,h_PORT_1KG+h_EMB_GRAND,h_PORT_2KG+h_EMB_GRAND))*(1+h_TVA) | J47: =h_STRIPE_PCT*D47+h_STRIPE_FIXE | K47: =0 | L47: =0 | M47: =h_PROV_RETOURS*F47 | N47: =h_MICRO_COTIS*D47 | O47: =F47-SUM(G47:N47) | P47: =O47/F47 | Q47: =F47/O47 | R47: =D47/O47 | S47: =O47
A48: Site — Kit anti-poils (+3,90 € de port) | B48: Site | C48: =h_ROU_POIDS+h_GAN_POIDS | D48: =h_KAP_PRIX+IF(h_KAP_PRIX<h_SEUIL_GRATUIT,h_PORT_CLIENT_TTC,0) | E48: =0 | F48: =D48-E48 | G48: =(h_ROU_PROD+h_GAN_PROD)*(1+h_TVA) | H48: =(h_ROU_DROITS+h_GAN_DROITS)*(1+h_TVA) | I48: =IF(C48<=500,h_PORT_500+h_EMB_PETIT,IF(C48<=1000,h_PORT_1KG+h_EMB_GRAND,h_PORT_2KG+h_EMB_GRAND))*(1+h_TVA) | J48: =h_STRIPE_PCT*D48+h_STRIPE_FIXE | K48: =0 | L48: =0 | M48: =h_PROV_RETOURS*F48 | N48: =h_MICRO_COTIS*D48 | O48: =F48-SUM(G48:N48) | P48: =O48/F48 | Q48: =F48/O48 | R48: =D48/O48 | S48: =O48
A49: Site — Grand kit (port offert) | B49: Site | C49: =h_ROU_POIDS+h_RAC_POIDS+h_GAN_POIDS | D49: =h_GK_PRIX+IF(h_GK_PRIX<h_SEUIL_GRATUIT,h_PORT_CLIENT_TTC,0) | E49: =0 | F49: =D49-E49 | G49: =(h_ROU_PROD+h_RAC_PROD+h_GAN_PROD)*(1+h_TVA) | H49: =(h_ROU_DROITS+h_RAC_DROITS+h_GAN_DROITS)*(1+h_TVA) | I49: =IF(C49<=500,h_PORT_500+h_EMB_PETIT,IF(C49<=1000,h_PORT_1KG+h_EMB_GRAND,h_PORT_2KG+h_EMB_GRAND))*(1+h_TVA) | J49: =h_STRIPE_PCT*D49+h_STRIPE_FIXE | K49: =0 | L49: =0 | M49: =h_PROV_RETOURS*F49 | N49: =h_MICRO_COTIS*D49 | O49: =F49-SUM(G49:N49) | P49: =O49/F49 | Q49: =F49/O49 | R49: =D49/O49 | S49: =O49
A50: Site — Duo 2 rouleaux (port offert) | B50: Site | C50: =h_ROU_POIDS+h_ROU_POIDS | D50: =h_DUO_PRIX+IF(h_DUO_PRIX<h_SEUIL_GRATUIT,h_PORT_CLIENT_TTC,0) | E50: =0 | F50: =D50-E50 | G50: =(h_ROU_PROD+h_ROU_PROD)*(1+h_TVA) | H50: =(h_ROU_DROITS+h_ROU_DROITS)*(1+h_TVA) | I50: =IF(C50<=500,h_PORT_500+h_EMB_PETIT,IF(C50<=1000,h_PORT_1KG+h_EMB_GRAND,h_PORT_2KG+h_EMB_GRAND))*(1+h_TVA) | J50: =h_STRIPE_PCT*D50+h_STRIPE_FIXE | K50: =0 | L50: =0 | M50: =h_PROV_RETOURS*F50 | N50: =h_MICRO_COTIS*D50 | O50: =F50-SUM(G50:N50) | P50: =O50/F50 | Q50: =F50/O50 | R50: =D50/O50 | S50: =O50
A51: TikTok Shop, contenu propre — Rouleau | B51: TikTok Shop | C51: =h_ROU_POIDS | D51: =h_ROU_PRIX | E51: =0 | F51: =D51-E51 | G51: =(h_ROU_PROD)*(1+h_TVA) | H51: =(h_ROU_DROITS)*(1+h_TVA) | I51: =IF(C51<=500,h_PORT_500+h_EMB_PETIT,IF(C51<=1000,h_PORT_1KG+h_EMB_GRAND,h_PORT_2KG+h_EMB_GRAND))*(1+h_TVA) | J51: =0 | K51: =h_TTS_COMM*D51*(1+h_TVA) | L51: =0 | M51: =h_PROV_RETOURS*F51 | N51: =h_MICRO_COTIS*D51 | O51: =F51-SUM(G51:N51) | P51: =O51/F51 | Q51: =F51/O51 | R51: =D51/O51 | S51: =O51
A52: TikTok Shop, contenu propre — Kit anti-poils | B52: TikTok Shop | C52: =h_ROU_POIDS+h_GAN_POIDS | D52: =h_KAP_PRIX | E52: =0 | F52: =D52-E52 | G52: =(h_ROU_PROD+h_GAN_PROD)*(1+h_TVA) | H52: =(h_ROU_DROITS+h_GAN_DROITS)*(1+h_TVA) | I52: =IF(C52<=500,h_PORT_500+h_EMB_PETIT,IF(C52<=1000,h_PORT_1KG+h_EMB_GRAND,h_PORT_2KG+h_EMB_GRAND))*(1+h_TVA) | J52: =0 | K52: =h_TTS_COMM*D52*(1+h_TVA) | L52: =0 | M52: =h_PROV_RETOURS*F52 | N52: =h_MICRO_COTIS*D52 | O52: =F52-SUM(G52:N52) | P52: =O52/F52 | Q52: =F52/O52 | R52: =D52/O52 | S52: =O52
A53: TikTok Shop, affilié 15 % — Rouleau | B53: TikTok Shop | C53: =h_ROU_POIDS | D53: =h_ROU_PRIX | E53: =0 | F53: =D53-E53 | G53: =(h_ROU_PROD)*(1+h_TVA) | H53: =(h_ROU_DROITS)*(1+h_TVA) | I53: =IF(C53<=500,h_PORT_500+h_EMB_PETIT,IF(C53<=1000,h_PORT_1KG+h_EMB_GRAND,h_PORT_2KG+h_EMB_GRAND))*(1+h_TVA) | J53: =0 | K53: =h_TTS_COMM*D53*(1+h_TVA) | L53: =h_CREA_COMM*D53*(1+h_TVA) | M53: =h_PROV_RETOURS*F53 | N53: =h_MICRO_COTIS*D53 | O53: =F53-SUM(G53:N53) | P53: =O53/F53
A54: TikTok Shop, affilié 15 % — Kit anti-poils | B54: TikTok Shop | C54: =h_ROU_POIDS+h_GAN_POIDS | D54: =h_KAP_PRIX | E54: =0 | F54: =D54-E54 | G54: =(h_ROU_PROD+h_GAN_PROD)*(1+h_TVA) | H54: =(h_ROU_DROITS+h_GAN_DROITS)*(1+h_TVA) | I54: =IF(C54<=500,h_PORT_500+h_EMB_PETIT,IF(C54<=1000,h_PORT_1KG+h_EMB_GRAND,h_PORT_2KG+h_EMB_GRAND))*(1+h_TVA) | J54: =0 | K54: =h_TTS_COMM*D54*(1+h_TVA) | L54: =h_CREA_COMM*D54*(1+h_TVA) | M54: =h_PROV_RETOURS*F54 | N54: =h_MICRO_COTIS*D54 | O54: =F54-SUM(G54:N54) | P54: =O54/F54
A56: Composantes moyennes par commande et par canal (utilisées par les scénarios)
A57: Nom Excel | B57: Définition | C57: Valeur
A58: ue_SITE_TTC | B58: Site organique : panier TTC | C58: =h_SITE_ROU*(D6)+h_SITE_KAP*(D10)+h_SITE_GK*(D11)+h_SITE_DUO*(D12)
A59: ue_SITE_HT | B59: Site organique : CA HT | C59: =h_SITE_ROU*(F6)+h_SITE_KAP*(F10)+h_SITE_GK*(F11)+h_SITE_DUO*(F12)
A60: ue_SITE_PAY | B60: Site organique : frais de paiement | C60: =h_SITE_ROU*(J6)+h_SITE_KAP*(J10)+h_SITE_GK*(J11)+h_SITE_DUO*(J12)
A61: ue_TTS_TTC | B61: TikTok Shop : panier TTC | C61: =h_TTS_ROU*(D14)+h_TTS_KAP*(D15)
A62: ue_TTS_HT | B62: TikTok Shop : CA HT | C62: =h_TTS_ROU*(F14)+h_TTS_KAP*(F15)
A63: ue_PUB_TTC | B63: Commande payante (Grand kit) : prix TTC | C63: =D11
A64: ue_PUB_HT | B64: Commande payante : CA HT | C64: =F11
A65: ue_PUB_PAY | B65: Commande payante : frais de paiement | C65: =J11
A66: ue_SITE_PROD_MS | B66: Site : produit + droits, micro-stock | C66: =h_SITE_ROU*(G6+H6)+h_SITE_KAP*(G10+H10)+h_SITE_GK*(G11+H11)+h_SITE_DUO*(G12+H12)
A67: ue_SITE_LOG_MS | B67: Site : livraison, micro-stock | C67: =h_SITE_ROU*(I6)+h_SITE_KAP*(I10)+h_SITE_GK*(I11)+h_SITE_DUO*(I12)
A68: ue_SITE_MARGE_MS | B68: Site : marge de contribution, micro-stock | C68: =h_SITE_ROU*(O6)+h_SITE_KAP*(O10)+h_SITE_GK*(O11)+h_SITE_DUO*(O12)
A69: ue_TTS_PROD_MS | B69: TikTok Shop : produit + droits, micro-stock | C69: =h_TTS_ROU*(G14+H14)+h_TTS_KAP*(G15+H15)
A70: ue_TTS_LOG_MS | B70: TikTok Shop : livraison, micro-stock | C70: =h_TTS_ROU*(I14)+h_TTS_KAP*(I15)
A71: ue_PROPRE_MARGE_MS | B71: TikTok Shop contenu propre (9 %) : marge, micro-stock | C71: =h_TTS_ROU*(O14)+h_TTS_KAP*(O15)
A72: ue_AFF_MARGE_MS | B72: TikTok Shop affilié (9 % + 15 %) : marge, micro-stock | C72: =h_TTS_ROU*(O17)+h_TTS_KAP*(O18)
A73: ue_PUB_PROD_MS | B73: Commande payante : produit + droits, micro-stock | C73: =G11+H11
A74: ue_PUB_LOG_MS | B74: Commande payante : livraison, micro-stock | C74: =I11
A75: ue_PUB_MARGE_AVANT_PUB_MS | B75: Commande payante : marge avant publicité, micro-stock | C75: =O11
A76: ue_MIX_MARGE_MS | B76: Mix de lancement (20/22/58) : marge moyenne, micro-stock | C76: =h_MIX_SITE*ue_SITE_MARGE_MS+h_MIX_PROPRE*ue_PROPRE_MARGE_MS+h_MIX_AFF*ue_AFF_MARGE_MS
A77: ue_MIX_PROD_MS | B77: Mix : produit + droits, micro-stock | C77: =h_MIX_SITE*ue_SITE_PROD_MS+(1-h_MIX_SITE)*ue_TTS_PROD_MS
A78: ue_MIX_LOG_MS | B78: Mix : livraison, micro-stock | C78: =h_MIX_SITE*ue_SITE_LOG_MS+(1-h_MIX_SITE)*ue_TTS_LOG_MS
A79: ue_SITE_PROD_IMP | B79: Site : produit + droits, import + 3PL | C79: =h_SITE_ROU*(G23+H23)+h_SITE_KAP*(G24+H24)+h_SITE_GK*(G25+H25)+h_SITE_DUO*(G26+H26)
A80: ue_SITE_LOG_IMP | B80: Site : livraison, import + 3PL | C80: =h_SITE_ROU*(I23)+h_SITE_KAP*(I24)+h_SITE_GK*(I25)+h_SITE_DUO*(I26)
A81: ue_SITE_MARGE_IMP | B81: Site : marge de contribution, import + 3PL | C81: =h_SITE_ROU*(O23)+h_SITE_KAP*(O24)+h_SITE_GK*(O25)+h_SITE_DUO*(O26)
A82: ue_TTS_PROD_IMP | B82: TikTok Shop : produit + droits, import + 3PL | C82: =h_TTS_ROU*(G27+H27)+h_TTS_KAP*(G28+H28)
A83: ue_TTS_LOG_IMP | B83: TikTok Shop : livraison, import + 3PL | C83: =h_TTS_ROU*(I27)+h_TTS_KAP*(I28)
A84: ue_PROPRE_MARGE_IMP | B84: TikTok Shop contenu propre (9 %) : marge, import + 3PL | C84: =h_TTS_ROU*(O27)+h_TTS_KAP*(O28)
A85: ue_AFF_MARGE_IMP | B85: TikTok Shop affilié (9 % + 15 %) : marge, import + 3PL | C85: =h_TTS_ROU*(O29)+h_TTS_KAP*(O30)
A86: ue_PUB_PROD_IMP | B86: Commande payante : produit + droits, import + 3PL | C86: =G25+H25
A87: ue_PUB_LOG_IMP | B87: Commande payante : livraison, import + 3PL | C87: =I25
A88: ue_PUB_MARGE_AVANT_PUB_IMP | B88: Commande payante : marge avant publicité, import + 3PL | C88: =O25
A89: ue_MIX_MARGE_IMP | B89: Mix de lancement (20/22/58) : marge moyenne, import + 3PL | C89: =h_MIX_SITE*ue_SITE_MARGE_IMP+h_MIX_PROPRE*ue_PROPRE_MARGE_IMP+h_MIX_AFF*ue_AFF_MARGE_IMP
A90: ue_MIX_PROD_IMP | B90: Mix : produit + droits, import + 3PL | C90: =h_MIX_SITE*ue_SITE_PROD_IMP+(1-h_MIX_SITE)*ue_TTS_PROD_IMP
A91: ue_MIX_LOG_IMP | B91: Mix : livraison, import + 3PL | C91: =h_MIX_SITE*ue_SITE_LOG_IMP+(1-h_MIX_SITE)*ue_TTS_LOG_IMP
A92: ue_MIX_TTC | B92: Mix : panier moyen TTC | C92: =h_MIX_SITE*ue_SITE_TTC+(1-h_MIX_SITE)*ue_TTS_TTC
A93: ue_MIX_HT | B93: Mix : CA HT moyen | C93: =h_MIX_SITE*ue_SITE_HT+(1-h_MIX_SITE)*ue_TTS_HT
A94: ue_SITE_MARGE_FR | B94: Site : marge, franchise de TVA | C94: =h_SITE_ROU*(O36)+h_SITE_KAP*(O37)+h_SITE_GK*(O38)+h_SITE_DUO*(O39)
A95: ue_PROPRE_MARGE_FR | B95: TikTok Shop contenu propre : marge, franchise de TVA | C95: =h_TTS_ROU*(O40)+h_TTS_KAP*(O41)
A96: ue_AFF_MARGE_FR | B96: TikTok Shop affilié : marge, franchise de TVA | C96: =h_TTS_ROU*(O42)+h_TTS_KAP*(O43)
A97: ue_MIX_MARGE_FR | B97: Mix de lancement : marge moyenne, franchise de TVA | C97: =h_MIX_SITE*ue_SITE_MARGE_FR+h_MIX_PROPRE*ue_PROPRE_MARGE_FR+h_MIX_AFF*ue_AFF_MARGE_FR
A98: ue_SITE_MARGE_MICRO | B98: Site : marge, micro-entreprise | C98: =h_SITE_ROU*(O47)+h_SITE_KAP*(O48)+h_SITE_GK*(O49)+h_SITE_DUO*(O50)
A99: ue_PROPRE_MARGE_MICRO | B99: TikTok Shop contenu propre : marge, micro-entreprise | C99: =h_TTS_ROU*(O51)+h_TTS_KAP*(O52)
A100: ue_AFF_MARGE_MICRO | B100: TikTok Shop affilié : marge, micro-entreprise | C100: =h_TTS_ROU*(O53)+h_TTS_KAP*(O54)
A101: ue_MIX_MARGE_MICRO | B101: Mix de lancement : marge moyenne, micro-entreprise | C101: =h_MIX_SITE*ue_SITE_MARGE_MICRO+h_MIX_PROPRE*ue_PROPRE_MARGE_MICRO+h_MIX_AFF*ue_AFF_MARGE_MICRO
A103: Seuils de rentabilité publicitaire et point mort
A104: Offre | B104: Marge avant pub (€) | C104: % du CA HT | D104: ROAS rentabilité HT | E104: ROAS rentabilité TTC | F104: CPA maximal (€) | G104: CPA cible MER ×1,2 (€) | H104: ROAS cible TTC
A105: Site — Rouleau seul (micro-stock) | B105: =O6 | C105: =O6/F6 | D105: =F6/O6 | E105: =D6/O6 | F105: =O6 | G105: =O6/h_MER_MARGE | H105: =D6/(O6/h_MER_MARGE)
A106: Site — Kit anti-poils (micro-stock) | B106: =O10 | C106: =O10/F10 | D106: =F10/O10 | E106: =D10/O10 | F106: =O10 | G106: =O10/h_MER_MARGE | H106: =D10/(O10/h_MER_MARGE)
...

Sheet Scénarios 18 mois
A1: Scénarios sur 18 mois (octobre 2026 → mars 2028) — société assujettie à la TVA
A2: Tous les calculs sont des formules. Les saisies (volumes, parts de canal, budgets, frais fixes) sont dans l'onglet Hypothèses. Bénéfice net = avant IS et avant rémunération du dirigeant.
A4: Scénario pessimiste — Porte 1 franchie de justesse ; moins d'une commande par jour hors Noël ; peu d'affiliés actifs ; ni import groupé ni publicité.
A5: Ligne | C5: oct. 2026 | D5: nov. 2026 | E5: déc. 2026 | F5: janv. 2027 | G5: févr. 2027 | H5: mars 2027 | I5: avr. 2027 | J5: mai 2027 | K5: juin 2027 | L5: juil. 2027 | M5: août 2027 | N5: sept. 2027 | O5: oct. 2027 | P5: nov. 2027 | Q5: déc. 2027 | R5: janv. 2028 | S5: févr. 2028 | T5: mars 2028 | U5: Total 18 mois
A6: Exercice | C6: ='Hypothèses'!C144 | D6: ='Hypothèses'!D144 | E6: ='Hypothèses'!E144 | F6: ='Hypothèses'!F144 | G6: ='Hypothèses'!G144 | H6: ='Hypothèses'!H144 | I6: ='Hypothèses'!I144 | J6: ='Hypothèses'!J144 | ... T6: ='Hypothèses'!T144
A7: Commandes site (organique) | C7: ='Hypothèses'!C145*'Hypothèses'!C146 | D7: ='Hypothèses'!D145*'Hypothèses'!D146 | E7: ='Hypothèses'!E145*'Hypothèses'!E146 | F7: ='Hypothèses'!F145*'Hypothèses'!F146 | G7: ='Hypothèses'!G145*'Hypothèses'!G146 | H7: ='Hypothèses'!H145*'Hypothèses'!H146 | I7: ='Hypothèses'!I145*'Hypothèses'!I146 | J7: ='Hypothèses'!J145*'Hypothèses'!J146 | ... T7: ='Hypothèses'!T145*'Hypothèses'!T146 | U7: =SUM(C7:T7)
A8: Commandes TikTok Shop, contenu propre | C8: ='Hypothèses'!C145*'Hypothèses'!C147 | D8: ='Hypothèses'!D145*'Hypothèses'!D147 | E8: ='Hypothèses'!E145*'Hypothèses'!E147 | F8: ='Hypothèses'!F145*'Hypothèses'!F147 | G8: ='Hypothèses'!G145*'Hypothèses'!G147 | H8: ='Hypothèses'!H145*'Hypothèses'!H147 | I8: ='Hypothèses'!I145*'Hypothèses'!I147 | J8: ='Hypothèses'!J145*'Hypothèses'!J147 | ... T8: ='Hypothèses'!T145*'Hypothèses'!T147 | U8: =SUM(C8:T8)
A9: Commandes TikTok Shop, affiliés | C9: ='Hypothèses'!C145*'Hypothèses'!C148 | D9: ='Hypothèses'!D145*'Hypothèses'!D148 | E9: ='Hypothèses'!E145*'Hypothèses'!E148 | F9: ='Hypothèses'!F145*'Hypothèses'!F148 | G9: ='Hypothèses'!G145*'Hypothèses'!G148 | H9: ='Hypothèses'!H145*'Hypothèses'!H148 | I9: ='Hypothèses'!I145*'Hypothèses'!I148 | J9: ='Hypothèses'!J145*'Hypothèses'!J148 | ... T9: ='Hypothèses'!T145*'Hypothèses'!T148 | U9: =SUM(C9:T9)
A10: Commandes issues de la publicité | C10: =IF('Hypothèses'!C152>0,'Hypothèses'!C151/'Hypothèses'!C152,0) | D10: =IF('Hypothèses'!D152>0,'Hypothèses'!D151/'Hypothèses'!D152,0) | E10: =IF('Hypothèses'!E152>0,'Hypothèses'!E151/'Hypothèses'!E152,0) | F10: =IF('Hypothèses'!F152>0,'Hypothèses'!F151/'Hypothèses'!F152,0) | G10: =IF('Hypothèses'!G152>0,'Hypothèses'!G151/'Hypothèses'!G152,0) | H10: =IF('Hypothèses'!H152>0,'Hypothèses'!H151/'Hypothèses'!H152,0) | I10: =IF('Hypothèses'!I152>0,'Hypothèses'!I151/'Hypothèses'!I152,0) | J10: =IF('Hypothèses'!J152>0,'Hypothèses'!J151/'Hypothèses'!J152,0) | ... T10: =IF('Hypothèses'!T152>0,'Hypothèses'!T151/'Hypothèses'!T152,0) | U10: =SUM(C10:T10)
A11: Commandes totales | C11: =C7+C8+C9+C10 | D11: =D7+D8+D9+D10 | E11: =E7+E8+E9+E10 | F11: =F7+F8+F9+F10 | G11: =G7+G8+G9+G10 | H11: =H7+H8+H9+H10 | I11: =I7+I8+I9+I10 | J11: =J7+J8+J9+J10 | ... T11: =T7+T8+T9+T10 | U11: =SUM(C11:T11)
A12: Commandes par jour | C12: =C11/30 | D12: =D11/30 | E12: =E11/30 | F12: =F11/30 | G12: =G11/30 | H12: =H11/30 | I12: =I11/30 | J12: =J11/30 | ... T12: =T11/30
A13: CA TTC | C13: =C7*ue_SITE_TTC+(C8+C9)*ue_TTS_TTC+C10*ue_PUB_TTC | D13: =D7*ue_SITE_TTC+(D8+D9)*ue_TTS_TTC+D10*ue_PUB_TTC | E13: =E7*ue_SITE_TTC+(E8+E9)*ue_TTS_TTC+E10*ue_PUB_TTC | F13: =F7*ue_SITE_TTC+(F8+F9)*ue_TTS_TTC+F10*ue_PUB_TTC | G13: =G7*ue_SITE_TTC+(G8+G9)*ue_TTS_TTC+G10*ue_PUB_TTC | H13: =H7*ue_SITE_TTC+(H8+H9)*ue_TTS_TTC+H10*ue_PUB_TTC | I13: =I7*ue_SITE_TTC+(I8+I9)*ue_TTS_TTC+I10*ue_PUB_TTC | J13: =J7*ue_SITE_TTC+(J8+J9)*ue_TTS_TTC+J10*ue_PUB_TTC | ... T13: =T7*ue_SITE_TTC+(T8+T9)*ue_TTS_TTC+T10*ue_PUB_TTC | U13: =SUM(C13:T13)
A14: CA HT | C14: =C13/(1+h_TVA) | D14: =D13/(1+h_TVA) | E14: =E13/(1+h_TVA) | F14: =F13/(1+h_TVA) | G14: =G13/(1+h_TVA) | H14: =H13/(1+h_TVA) | I14: =I13/(1+h_TVA) | J14: =J13/(1+h_TVA) | ... T14: =T13/(1+h_TVA) | U14: =SUM(C14:T14)
A15: TVA collectée | C15: =C13-C14 | D15: =D13-D14 | E15: =E13-E14 | F15: =F13-F14 | G15: =G13-G14 | H15: =H13-H14 | I15: =I13-I14 | J15: =J13-J14 | ... T15: =T13-T14 | U15: =SUM(C15:T15)
A16: Coût des produits et droits | C16: =C7*IF('Hypothèses'!C150=1,ue_SITE_PROD_IMP,ue_SITE_PROD_MS)+(C8+C9)*IF('Hypothèses'!C150=1,ue_TTS_PROD_IMP,ue_TTS_PROD_MS)+C10*IF('Hypothèses'!C150=1,ue_PUB_PROD_IMP,ue_PUB_PROD_MS) | D16: =D7*IF('Hypothèses'!D150=1,ue_SITE_PROD_IMP,ue_SITE_PROD_MS)+(D8+D9)*IF('Hypothèses'!D150=1,ue_TTS_PROD_IMP,ue_TTS_PROD_MS)+D10*IF('Hypothèses'!D150=1,ue_PUB_PROD_IMP,ue_PUB_PROD_MS) | E16: =E7*IF('Hypothèses'!E150=1,ue_SITE_PROD_IMP,ue_SITE_PROD_MS)+(E8+E9)*IF('Hypothèses'!E150=1,ue_TTS_PROD_IMP,ue_TTS_PROD_MS)+E10*IF('Hypothèses'!E150=1,ue_PUB_PROD_IMP,ue_PUB_PROD_MS) | F16: =F7*IF('Hypothèses'!F150=1,ue_SITE_PROD_IMP,ue_SITE_PROD_MS)+(F8+F9)*IF('Hypothèses'!F150=1,ue_TTS_PROD_IMP,ue_TTS_PROD_MS)+F10*IF('Hypothèses'!F150=1,ue_PUB_PROD_IMP,ue_PUB_PROD_MS) | G16: =G7*IF('Hypothèses'!G150=1,ue_SITE_PROD_IMP,ue_SITE_PROD_MS)+(G8+G9)*IF('Hypothèses'!G150=1,ue_TTS_PROD_IMP,ue_TTS_PROD_MS)+G10*IF('Hypothèses'!G150=1,ue_PUB_PROD_IMP,ue_PUB_PROD_MS) | H16: =H7*IF('Hypothèses'!H150=1,ue_SITE_PROD_IMP,ue_SITE_PROD_MS)+(H8+H9)*IF('Hypothèses'!H150=1,ue_TTS_PROD_IMP,ue_TTS_PROD_MS)+H10*IF('Hypothèses'!H150=1,ue_PUB_PROD_IMP,ue_PUB_PROD_MS) | I16: =I7*IF('Hypothèses'!I150=1,ue_SITE_PROD_IMP,ue_SITE_PROD_MS)+(I8+I9)*IF('Hypothèses'!I150=1,ue_TTS_PROD_IMP,ue_TTS_PROD_MS)+I10*IF('Hypothèses'!I150=1,ue_PUB_PROD_IMP,ue_PUB_PROD_MS) | J16: =J7*IF('Hypothèses'!J150=1,ue_SITE_PROD_IMP,ue_SITE_PROD_MS)+(J8+J9)*IF('Hypothèses'!J150=1,ue_TTS_PROD_IMP,ue_TTS_PROD_MS)+J10*IF('Hypothèses'!J150=1,ue_PUB_PROD_IMP,ue_PUB_PROD_MS) | ... T16: =T7*IF('Hypothèses'!T150=1,ue_SITE_PROD_IMP,ue_SITE_PROD_MS)+(T8+T9)*IF('Hypothèses'!T150=1,ue_TTS_PROD_IMP,ue_TTS_PROD_MS)+T10*IF('Hypothèses'!T150=1,ue_PUB_PROD_IMP,ue_PUB_PROD_MS) | U16: =SUM(C16:T16)
A17: Livraison, emballage, 3PL | C17: =C7*IF('Hypothèses'!C150=1,ue_SITE_LOG_IMP,ue_SITE_LOG_MS)+(C8+C9)*IF('Hypothèses'!C150=1,ue_TTS_LOG_IMP,ue_TTS_LOG_MS)+C10*IF('Hypothèses'!C150=1,ue_PUB_LOG_IMP,ue_PUB_LOG_MS) | D17: =D7*IF('Hypothèses'!D150=1,ue_SITE_LOG_IMP,ue_SITE_LOG_MS)+(D8+D9)*IF('Hypothèses'!D150=1,ue_TTS_LOG_IMP,ue_TTS_LOG_MS)+D10*IF('Hypothèses'!D150=1,ue_PUB_LOG_IMP,ue_PUB_LOG_MS) | E17: =E7*IF('Hypothèses'!E150=1,ue_SITE_LOG_IMP,ue_SITE_LOG_MS)+(E8+E9)*IF('Hypothèses'!E150=1,ue_TTS_LOG_IMP,ue_TTS_LOG_MS)+E10*IF('Hypothèses'!E150=1,ue_PUB_LOG_IMP,ue_PUB_LOG_MS) | F17: =F7*IF('Hypothèses'!F150=1,ue_SITE_LOG_IMP,ue_SITE_LOG_MS)+(F8+F9)*IF('Hypothèses'!F150=1,ue_TTS_LOG_IMP,ue_TTS_LOG_MS)+F10*IF('Hypothèses'!F150=1,ue_PUB_LOG_IMP,ue_PUB_LOG_MS) | G17: =G7*IF('Hypothèses'!G150=1,ue_SITE_LOG_IMP,ue_SITE_LOG_MS)+(G8+G9)*IF('Hypothèses'!G150=1,ue_TTS_LOG_IMP,ue_TTS_LOG_MS)+G10*IF('Hypothèses'!G150=1,ue_PUB_LOG_IMP,ue_PUB_LOG_MS) | H17: =H7*IF('Hypothèses'!H150=1,ue_SITE_LOG_IMP,ue_SITE_LOG_MS)+(H8+H9)*IF('Hypothèses'!H150=1,ue_TTS_LOG_IMP,ue_TTS_LOG_MS)+H10*IF('Hypothèses'!H150=1,ue_PUB_LOG_IMP,ue_PUB_LOG_MS) | I17: =I7*IF('Hypothèses'!I150=1,ue_SITE_LOG_IMP,ue_SITE_LOG_MS)+(I8+I9)*IF('Hypothèses'!I150=1,ue_TTS_LOG_IMP,ue_TTS_LOG_MS)+I10*IF('Hypothèses'!I150=1,ue_PUB_LOG_IMP,ue_PUB_LOG_MS) | J17: =J7*IF('Hypothèses'!J150=1,ue_SITE_LOG_IMP,ue_SITE_LOG_MS)+(J8+J9)*IF('Hypothèses'!J150=1,ue_TTS_LOG_IMP,ue_TTS_LOG_MS)+J10*IF('Hypothèses'!J150=1,ue_PUB_LOG_IMP,ue_PUB_LOG_MS) | ... T17: =T7*IF('Hypothèses'!T150=1,ue_SITE_LOG_IMP,ue_SITE_LOG_MS)+(T8+T9)*IF('Hypothèses'!T150=1,ue_TTS_LOG_IMP,ue_TTS_LOG_MS)+T10*IF('Hypothèses'!T150=1,ue_PUB_LOG_IMP,ue_PUB_LOG_MS) | U17: =SUM(C17:T17)
A18: Frais de paiement | C18: =C7*ue_SITE_PAY+C10*ue_PUB_PAY | D18: =D7*ue_SITE_PAY+D10*ue_PUB_PAY | E18: =E7*ue_SITE_PAY+E10*ue_PUB_PAY | F18: =F7*ue_SITE_PAY+F10*ue_PUB_PAY | G18: =G7*ue_SITE_PAY+G10*ue_PUB_PAY | H18: =H7*ue_SITE_PAY+H10*ue_PUB_PAY | I18: =I7*ue_SITE_PAY+I10*ue_PUB_PAY | J18: =J7*ue_SITE_PAY+J10*ue_PUB_PAY | ... T18: =T7*ue_SITE_PAY+T10*ue_PUB_PAY | U18: =SUM(C18:T18)
A19: Commission TikTok Shop | C19: =(C8+C9)*ue_TTS_TTC*'Hypothèses'!C149 | D19: =(D8+D9)*ue_TTS_TTC*'Hypothèses'!D149 | E19: =(E8+E9)*ue_TTS_TTC*'Hypothèses'!E149 | F19: =(F8+F9)*ue_TTS_TTC*'Hypothèses'!F149 | G19: =(G8+G9)*ue_TTS_TTC*'Hypothèses'!G149 | H19: =(H8+H9)*ue_TTS_TTC*'Hypothèses'!H149 | I19: =(I8+I9)*ue_TTS_TTC*'Hypothèses'!I149 | J19: =(J8+J9)*ue_TTS_TTC*'Hypothèses'!J149 | ... T19: =(T8+T9)*ue_TTS_TTC*'Hypothèses'!T149 | U19: =SUM(C19:T19)
A20: Commission des créateurs | C20: =C9*ue_TTS_TTC*h_CREA_COMM | D20: =D9*ue_TTS_TTC*h_CREA_COMM | E20: =E9*ue_TTS_TTC*h_CREA_COMM | F20: =F9*ue_TTS_TTC*h_CREA_COMM | G20: =G9*ue_TTS_TTC*h_CREA_COMM | H20: =H9*ue_TTS_TTC*h_CREA_COMM | I20: =I9*ue_TTS_TTC*h_CREA_COMM | J20: =J9*ue_TTS_TTC*h_CREA_COMM | ... T20: =T9*ue_TTS_TTC*h_CREA_COMM | U20: =SUM(C20:T20)
A21: Provision retours, SAV, litiges | C21: =h_PROV_RETOURS*C14 | D21: =h_PROV_RETOURS*D14 | E21: =h_PROV_RETOURS*E14 | F21: =h_PROV_RETOURS*F14 | G21: =h_PROV_RETOURS*G14 | H21: =h_PROV_RETOURS*H14 | I21: =h_PROV_RETOURS*I14 | J21: =h_PROV_RETOURS*J14 | ... T21: =h_PROV_RETOURS*T14 | U21: =SUM(C21:T21)
A22: Marge de contribution | C22: =C14-SUM(C16:C21) | D22: =D14-SUM(D16:D21) | E22: =E14-SUM(E16:E21) | F22: =F14-SUM(F16:F21) | G22: =G14-SUM(G16:G21) | H22: =H14-SUM(H16:H21) | I22: =I14-SUM(I16:I21) | J22: =J14-SUM(J16:J21) | ... T22: =T14-SUM(T16:T21) | U22: =SUM(C22:T22)
A23: Publicité | C23: ='Hypothèses'!C151 | D23: ='Hypothèses'!D151 | E23: ='Hypothèses'!E151 | F23: ='Hypothèses'!F151 | G23: ='Hypothèses'!G151 | H23: ='Hypothèses'!H151 | I23: ='Hypothèses'!I151 | J23: ='Hypothèses'!J151 | ... T23: ='Hypothèses'!T151 | U23: =SUM(C23:T23)
A24: Échantillons créateurs | C24: ='Hypothèses'!C153 | D24: ='Hypothèses'!D153 | E24: ='Hypothèses'!E153 | F24: ='Hypothèses'!F153 | G24: ='Hypothèses'!G153 | H24: ='Hypothèses'!H153 | I24: ='Hypothèses'!I153 | J24: ='Hypothèses'!J153 | ... T24: ='Hypothèses'!T153 | U24: =SUM(C24:T24)
A25: Frais fixes et ponctuels | C25: ='Hypothèses'!C157+'Hypothèses'!C158+'Hypothèses'!C159+'Hypothèses'!C160+'Hypothèses'!C161 | D25: ='Hypothèses'!D157+'Hypothèses'!D158+'Hypothèses'!D159+'Hypothèses'!D160+'Hypothèses'!D161 | E25: ='Hypothèses'!E157+'Hypothèses'!E158+'Hypothèses'!E159+'Hypothèses'!E160+'Hypothèses'!E161 | F25: ='Hypothèses'!F157+'Hypothèses'!F158+'Hypothèses'!F159+'Hypothèses'!F160+'Hypothèses'!F161 | G25: ='Hypothèses'!G157+'Hypothèses'!G158+'Hypothèses'!G159+'Hypothèses'!G160+'Hypothèses'!G161 | H25: ='Hypothèses'!H157+'Hypothèses'!H158+'Hypothèses'!H159+'Hypothèses'!H160+'Hypothèses'!H161 | I25: ='Hypothèses'!I157+'Hypothèses'!I158+'Hypothèses'!I159+'Hypothèses'!I160+'Hypothèses'!I161 | J25: ='Hypothèses'!J157+'Hypothèses'!J158+'Hypothèses'!J159+'Hypothèses'!J160+'Hypothèses'!J161 | ... T25: ='Hypothèses'!T157+'Hypothèses'!T158+'Hypothèses'!T159+'Hypothèses'!T160+'Hypothèses'!T161 | U25: =SUM(C25:T25)
A26: Bénéfice net (avant IS et rémunération du dirigeant) | C26: =C22-C23-C24-C25 | D26: =D22-D23-D24-D25 | E26: =E22-E23-E24-E25 | F26: =F22-F23-F24-F25 | G26: =G22-G23-G24-G25 | H26: =H22-H23-H24-H25 | I26: =I22-I23-I24-I25 | J26: =J22-J23-J24-J25 | ... T26: =T22-T23-T24-T25 | U26: =SUM(C26:T26)
A27: Bénéfice net cumulé | C27: =C26 | D27: =D26+C27 | E27: =E26+D27 | F27: =F26+E27 | G27: =G26+F27 | H27: =H26+G27 | I27: =I26+H27 | J27: =J26+I27 | K27: =K26+J27 | ... T27: =T26+S27
A28: Coûts totaux (CA HT − bénéfice net) | C28: =C14-C26 | D28: =D14-D26 | E28: =E14-E26 | F28: =F14-F26 | G28: =G14-G26 | H28: =H14-H26 | I28: =I14-I26 | J28: =J14-J26 | ... T28: =T14-T26 | U28: =SUM(C28:T28)
A29: Nouvel exercice (1 = oui) | C29: =1 | D29: =IF(D6<>C6,1,0) | E29: =IF(E6<>D6,1,0) | F29: =IF(F6<>E6,1,0) | G29: =IF(G6<>F6,1,0) | H29: =IF(H6<>G6,1,0) | I29: =IF(I6<>H6,1,0) | J29: =IF(J6<>I6,1,0) | K29: =IF(K6<>J6,1,0) | ... T29: =IF(T6<>S6,1,0)
A30: Base IS cumulée de l'exercice (déficit antérieur reporté) | C30: =C26 | D30: =IF(D29=1,MIN(0,C30)+D26,C30+D26) | E30: =IF(E29=1,MIN(0,D30)+E26,D30+E26) | F30: =IF(F29=1,MIN(0,E30)+F26,E30+F26) | G30: =IF(G29=1,MIN(0,F30)+G26,F30+G26) | H30: =IF(H29=1,MIN(0,G30)+H26,G30+H26) | I30: =IF(I29=1,MIN(0,H30)+I26,H30+I26) | J30: =IF(J29=1,MIN(0,I30)+J26,I30+J26) | K30: =IF(K29=1,MIN(0,J30)+K26,J30+K26) | ... T30: =IF(T29=1,MIN(0,S30)+T26,S30+T26)
A31: IS cumulé de l'exercice | C31: =h_IS_TAUX_REDUIT*MIN(MAX(C30,0),h_IS_SEUIL)+h_IS_TAUX_NORMAL*MAX(C30-h_IS_SEUIL,0) | D31: =h_IS_TAUX_REDUIT*MIN(MAX(D30,0),h_IS_SEUIL)+h_IS_TAUX_NORMAL*MAX(D30-h_IS_SEUIL,0) | E31: =h_IS_TAUX_REDUIT*MIN(MAX(E30,0),h_IS_SEUIL)+h_IS_TAUX_NORMAL*MAX(E30-h_IS_SEUIL,0) | F31: =h_IS_TAUX_REDUIT*MIN(MAX(F30,0),h_IS_SEUIL)+h_IS_TAUX_NORMAL*MAX(F30-h_IS_SEUIL,0) | G31: =h_IS_TAUX_REDUIT*MIN(MAX(G30,0),h_IS_SEUIL)+h_IS_TAUX_NORMAL*MAX(G30-h_IS_SEUIL,0) | H31: =h_IS_TAUX_REDUIT*MIN(MAX(H30,0),h_IS_SEUIL)+h_IS_TAUX_NORMAL*MAX(H30-h_IS_SEUIL,0) | I31: =h_IS_TAUX_REDUIT*MIN(MAX(I30,0),h_IS_SEUIL)+h_IS_TAUX_NORMAL*MAX(I30-h_IS_SEUIL,0) | J31: =h_IS_TAUX_REDUIT*MIN(MAX(J30,0),h_IS_SEUIL)+h_IS_TAUX_NORMAL*MAX(J30-h_IS_SEUIL,0) | ... T31: =h_IS_TAUX_REDUIT*MIN(MAX(T30,0),h_IS_SEUIL)+h_IS_TAUX_NORMAL*MAX(T30-h_IS_SEUIL,0)
A32: IS du mois (provision) | C32: =C31 | D32: =IF(D29=1,D31,D31-C31) | E32: =IF(E29=1,E31,E31-D31) | F32: =IF(F29=1,F31,F31-E31) | G32: =IF(G29=1,G31,G31-F31) | H32: =IF(H29=1,H31,H31-G31) | I32: =IF(I29=1,I31,I31-H31) | J32: =IF(J29=1,J31,J31-I31) | K32: =IF(K29=1,K31,K31-J31) | ... T32: =IF(T29=1,T31,T31-S31) | U32: =SUM(C32:T32)
A33: Résultat après IS | C33: =C26-C32 | D33: =D26-D32 | E33: =E26-E32 | F33: =F26-F32 | G33: =G26-G32 | H33: =H26-H32 | I33: =I26-I32 | J33: =J26-J32 | ... T33: =T26-T32 | U33: =SUM(C33:T33)
A36: Scénario réaliste — Croissance organique régulière ; palier 1 vers l'été 2027 ; import groupé en octobre 2027 ; test publicitaire de 3 mois arrêté faute de rentabilité.
A37: Ligne | C37: oct. 2026 | D37: nov. 2026 | E37: déc. 2026 | F37: janv. 2027 | G37: févr. 2027 | H37: mars 2027 | I37: avr. 2027 | J37: mai 2027 | K37: juin 2027 | L37: juil. 2027 | M37: août 2027 | N37: sept. 2027 | O37: oct. 2027 | P37: nov. 2027 | Q37: déc. 2027 | R37: janv. 2028 | S37: févr. 2028 | T37: mars 2028 | U37: Total 18 mois
A38: Exercice | C38: ='Hypothèses'!C165 | D38: ='Hypothèses'!D165 | E38: ='Hypothèses'!E165 | F38: ='Hypothèses'!F165 | G38: ='Hypothèses'!G165 | H38: ='Hypothèses'!H165 | I38: ='Hypothèses'!I165 | J38: ='Hypothèses'!J165 | ... T38: ='Hypothèses'!T165
A39: Commandes site (organique) | C39: ='Hypothèses'!C166*'Hypothèses'!C167 | D39: ='Hypothèses'!D166*'Hypothèses'!D167 | E39: ='Hypothèses'!E166*'Hypothèses'!E167 | F39: ='Hypothèses'!F166*'Hypothèses'!F167 | G39: ='Hypothèses'!G166*'Hypothèses'!G167 | H39: ='Hypothèses'!H166*'Hypothèses'!H167 | I39: ='Hypothèses'!I166*'Hypothèses'!I167 | J39: ='Hypothèses'!J166*'Hypothèses'!J167 | ... T39: ='Hypothèses'!T166*'Hypothèses'!T167 | U39: =SUM(C39:T39)
A40: Commandes TikTok Shop, contenu propre | C40: ='Hypothèses'!C166*'Hypothèses'!C168 | D40: ='Hypothèses'!D166*'Hypothèses'!D168 | E40: ='Hypothèses'!E166*'Hypothèses'!E168 | F40: ='Hypothèses'!F166*'Hypothèses'!F168 | G40: ='Hypothèses'!G166*'Hypothèses'!G168 | H40: ='Hypothèses'!H166*'Hypothèses'!H168 | I40: ='Hypothèses'!I166*'Hypothèses'!I168 | J40: ='Hypothèses'!J166*'Hypothèses'!J168 | ... T40: ='Hypothèses'!T166*'Hypothèses'!T168 | U40: =SUM(C40:T40)
A41: Commandes TikTok Shop, affiliés | C41: ='Hypothèses'!C166*'Hypothèses'!C169 | D41: ='Hypothèses'!D166*'Hypothèses'!D169 | E41: ='Hypothèses'!E166*'Hypothèses'!E169 | F41: ='Hypothèses'!F166*'Hypothèses'!F169 | G41: ='Hypothèses'!G166*'Hypothèses'!G169 | H41: ='Hypothèses'!H166*'Hypothèses'!H169 | I41: ='Hypothèses'!I166*'Hypothèses'!I169 | J41: ='Hypothèses'!J166*'Hypothèses'!J169 | ... T41: ='Hypothèses'!T166*'Hypothèses'!T169 | U41: =SUM(C41:T41)
A42: Commandes issues de la publicité | C42: =IF('Hypothèses'!C173>0,'Hypothèses'!C172/'Hypothèses'!C173,0) | D42: =IF('Hypothèses'!D173>0,'Hypothèses'!D172/'Hypothèses'!D173,0) | E42: =IF('Hypothèses'!E173>0,'Hypothèses'!E172/'Hypothèses'!E173,0) | F42: =IF('Hypothèses'!F173>0,'Hypothèses'!F172/'Hypothèses'!F173,0) | G42: =IF('Hypothèses'!G173>0,'Hypothèses'!G172/'Hypothèses'!G173,0) | H42: =IF('Hypothèses'!H173>0,'Hypothèses'!H172/'Hypothèses'!H173,0) | I42: =IF('Hypothèses'!I173>0,'Hypothèses'!I172/'Hypothèses'!I173,0) | J42: =IF('Hypothèses'!J173>0,'Hypothèses'!J172/'Hypothèses'!J173,0) | ... T42: =IF('Hypothèses'!T173>0,'Hypothèses'!T172/'Hypothèses'!T173,0) | U42: =SUM(C42:T42)
A43: Commandes totales | C43: =C39+C40+C41+C42 | D43: =D39+D40+D41+D42 | E43: =E39+E40+E41+E42 | F43: =F39+F40+F41+F42 | G43: =G39+G40+G41+G42 | H43: =H39+H40+H41+H42 | I43: =I39+I40+I41+I42 | J43: =J39+J40+J41+J42 | ... T43: =T39+T40+T41+T42 | U43: =SUM(C43:T43)
A44: Commandes par jour | C44: =C43/30 | D44: =D43/30 | E44: =E43/30 | F44: =F43/30 | G44: =G43/30 | H44: =H43/30 | I44: =I43/30 | J44: =J43/30 | ... T44: =T43/30
A45: CA TTC | C45: =C39*ue_SITE_TTC+(C40+C41)*ue_TTS_TTC+C42*ue_PUB_TTC | D45: =D39*ue_SITE_TTC+(D40+D41)*ue_TTS_TTC+D42*ue_PUB_TTC | E45: =E39*ue_SITE_TTC+(E40+E41)*ue_TTS_TTC+E42*ue_PUB_TTC | F45: =F39*ue_SITE_TTC+(F40+F41)*ue_TTS_TTC+F42*ue_PUB_TTC | G45: =G39*ue_SITE_TTC+(G40+G41)*ue_TTS_TTC+G42*ue_PUB_TTC | H45: =H39*ue_SITE_TTC+(H40+H41)*ue_TTS_TTC+H42*ue_PUB_TTC | I45: =I39*ue_SITE_TTC+(I40+I41)*ue_TTS_TTC+I42*ue_PUB_TTC | J45: =J39*ue_SITE_TTC+(J40+J41)*ue_TTS_TTC+J42*ue_PUB_TTC | ... T45: =T39*ue_SITE_TTC+(T40+T41)*ue_TTS_TTC+T42*ue_PUB_TTC | U45: =SUM(C45:T45)
A46: CA HT | C46: =C45/(1+h_TVA) | D46: =D45/(1+h_TVA) | E46: =E45/(1+h_TVA) | F46: =F45/(1+h_TVA) | G46: =G45/(1+h_TVA) | H46: =H45/(1+h_TVA) | I46: =I45/(1+h_TVA) | J46: =J45/(1+h_TVA) | ... T46: =T45/(1+h_TVA) | U46: =SUM(C46:T46)
A47: TVA collectée | C47: =C45-C46 | D47: =D45-D46 | E47: =E45-E46 | F47: =F45-F46 | G47: =G45-G46 | H47: =H45-H46 | I47: =I45-I46 | J47: =J45-J46 | ... T47: =T45-T46 | U47: =SUM(C47:T47)
A48: Coût des produits et droits | C48: =C39*IF('Hypothèses'!C171=1,ue_SITE_PROD_IMP,ue_SITE_PROD_MS)+(C40+C41)*IF('Hypothèses'!C171=1,ue_TTS_PROD_IMP,ue_TTS_PROD_MS)+C42*IF('Hypothèses'!C171=1,ue_PUB_PROD_IMP,ue_PUB_PROD_MS) | D48: =D39*IF('Hypothèses'!D171=1,ue_SITE_PROD_IMP,ue_SITE_PROD_MS)+(D40+D41)*IF('Hypothèses'!D171=1,ue_TTS_PROD_IMP,ue_TTS_PROD_MS)+D42*IF('Hypothèses'!D171=1,ue_PUB_PROD_IMP,ue_PUB_PROD_MS) | E48: =E39*IF('Hypothèses'!E171=1,ue_SITE_PROD_IMP,ue_SITE_PROD_MS)+(E40+E41)*IF('Hypothèses'!E171=1,ue_TTS_PROD_IMP,ue_TTS_PROD_MS)+E42*IF('Hypothèses'!E171=1,ue_PUB_PROD_IMP,ue_PUB_PROD_MS) | F48: =F39*IF('Hypothèses'!F171=1,ue_SITE_PROD_IMP,ue_SITE_PROD_MS)+(F40+F41)*IF('Hypothèses'!F171=1,ue_TTS_PROD_IMP,ue_TTS_PROD_MS)+F42*IF('Hypothèses'!F171=1,ue_PUB_PROD_IMP,ue_PUB_PROD_MS) | G48: =G39*IF('Hypothèses'!G171=1,ue_SITE_PROD_IMP,ue_SITE_PROD_MS)+(G40+G41)*IF('Hypothèses'!G171=1,ue_TTS_PROD_IMP,ue_TTS_PROD_MS)+G42*IF('Hypothèses'!G171=1,ue_PUB_PROD_IMP,ue_PUB_PROD_MS) | H48: =H39*IF('Hypothèses'!H171=1,ue_SITE_PROD_IMP,ue_SITE_PROD_MS)+(H40+H41)*IF('Hypothèses'!H171=1,ue_TTS_PROD_IMP,ue_TTS_PROD_MS)+H42*IF('Hypothèses'!H171=1,ue_PUB_PROD_IMP,ue_PUB_PROD_MS) | I48: =I39*IF('Hypothèses'!I171=1,ue_SITE_PROD_IMP,ue_SITE_PROD_MS)+(I40+I41)*IF('Hypothèses'!I171=1,ue_TTS_PROD_IMP,ue_TTS_PROD_MS)+I42*IF('Hypothèses'!I171=1,ue_PUB_PROD_IMP,ue_PUB_PROD_MS) | J48: =J39*IF('Hypothèses'!J171=1,ue_SITE_PROD_IMP,ue_SITE_PROD_MS)+(J40+J41)*IF('Hypothèses'!J171=1,ue_TTS_PROD_IMP,ue_TTS_PROD_MS)+J42*IF('Hypothèses'!J171=1,ue_PUB_PROD_IMP,ue_PUB_PROD_MS) | ... T48: =T39*IF('Hypothèses'!T171=1,ue_SITE_PROD_IMP,ue_SITE_PROD_MS)+(T40+T41)*IF('Hypothèses'!T171=1,ue_TTS_PROD_IMP,ue_TTS_PROD_MS)+T42*IF('Hypothèses'!T171=1,ue_PUB_PROD_IMP,ue_PUB_PROD_MS) | U48: =SUM(C48:T48)
A49: Livraison, emballage, 3PL | C49: =C39*IF('Hypothèses'!C171=1,ue_SITE_LOG_IMP,ue_SITE_LOG_MS)+(C40+C41)*IF('Hypothèses'!C171=1,ue_TTS_LOG_IMP,ue_TTS_LOG_MS)+C42*IF('Hypothèses'!C171=1,ue_PUB_LOG_IMP,ue_PUB_LOG_MS) | D49: =D39*IF('Hypothèses'!D171=1,ue_SITE_LOG_IMP,ue_SITE_LOG_MS)+(D40+D41)*IF('Hypothèses'!D171=1,ue_TTS_LOG_IMP,ue_TTS_LOG_MS)+D42*IF('Hypothèses'!D171=1,ue_PUB_LOG_IMP,ue_PUB_LOG_MS) | E49: =E39*IF('Hypothèses'!E171=1,ue_SITE_LOG_IMP,ue_SITE_LOG_MS)+(E40+E41)*IF('Hypothèses'!E171=1,ue_TTS_LOG_IMP,ue_TTS_LOG_MS)+E42*IF('Hypothèses'!E171=1,ue_PUB_LOG_IMP,ue_PUB_LOG_MS) | F49: =F39*IF('Hypothèses'!F171=1,ue_SITE_LOG_IMP,ue_SITE_LOG_MS)+(F40+F41)*IF('Hypothèses'!F171=1,ue_TTS_LOG_IMP,ue_TTS_LOG_MS)+F42*IF('Hypothèses'!F171=1,ue_PUB_LOG_IMP,ue_PUB_LOG_MS) | G49: =G39*IF('Hypothèses'!G171=1,ue_SITE_LOG_IMP,ue_SITE_LOG_MS)+(G40+G41)*IF('Hypothèses'!G171=1,ue_TTS_LOG_IMP,ue_TTS_LOG_MS)+G42*IF('Hypothèses'!G171=1,ue_PUB_LOG_IMP,ue_PUB_LOG_MS) | H49: =H39*IF('Hypothèses'!H171=1,ue_SITE_LOG_IMP,ue_SITE_LOG_MS)+(H40+H41)*IF('Hypothèses'!H171=1,ue_TTS_LOG_IMP,ue_TTS_LOG_MS)+H42*IF('Hypothèses'!H171=1,ue_PUB_LOG_IMP,ue_PUB_LOG_MS) | I49: =I39*IF('Hypothèses'!I171=1,ue_SITE_LOG_IMP,ue_SITE_LOG_MS)+(I40+I41)*IF('Hypothèses'!I171=1,ue_TTS_LOG_IMP,ue_TTS_LOG_MS)+I42*IF('Hypothèses'!I171=1,ue_PUB_LOG_IMP,ue_PUB_LOG_MS) | J49: =J39*IF('Hypothèses'!J171=1,ue_SITE_LOG_IMP,ue_SITE_LOG_MS)+(J40+J41)*IF('Hypothèses'!J171=1,ue_TTS_LOG_IMP,ue_TTS_LOG_MS)+J42*IF('Hypothèses'!J171=1,ue_PUB_LOG_IMP,ue_PUB_LOG_MS) | ... T49: =T39*IF('Hypothèses'!T171=1,ue_SITE_LOG_IMP,ue_SITE_LOG_MS)+(T40+T41)*IF('Hypothèses'!T171=1,ue_TTS_LOG_IMP,ue_TTS_LOG_MS)+T42*IF('Hypothèses'!T171=1,ue_PUB_LOG_IMP,ue_PUB_LOG_MS) | U49: =SUM(C49:T49)
A50: Frais de paiement | C50: =C39*ue_SITE_PAY+C42*ue_PUB_PAY | D50: =D39*ue_SITE_PAY+D42*ue_PUB_PAY | E50: =E39*ue_SITE_PAY+E42*ue_PUB_PAY | F50: =F39*ue_SITE_PAY+F42*ue_PUB_PAY | G50: =G39*ue_SITE_PAY+G42*ue_PUB_PAY | H50: =H39*ue_SITE_PAY+H42*ue_PUB_PAY | I50: =I39*ue_SITE_PAY+I42*ue_PUB_PAY | J50: =J39*ue_SITE_PAY+J42*ue_PUB_PAY | ... T50: =T39*ue_SITE_PAY+T42*ue_PUB_PAY | U50: =SUM(C50:T50)
A51: Commission TikTok Shop | C51: =(C40+C41)*ue_TTS_TTC*'Hypothèses'!C170 | D51: =(D40+D41)*ue_TTS_TTC*'Hypothèses'!D170 | E51: =(E40+E41)*ue_TTS_TTC*'Hypothèses'!E170 | F51: =(F40+F41)*ue_TTS_TTC*'Hypothèses'!F170 | G51: =(G40+G41)*ue_TTS_TTC*'Hypothèses'!G170 | H51: =(H40+H41)*ue_TTS_TTC*'Hypothèses'!H170 | I51: =(I40+I41)*ue_TTS_TTC*'Hypothèses'!I170 | J51: =(J40+J41)*ue_TTS_TTC*'Hypothèses'!J170 | ... T51: =(T40+T41)*ue_TTS_TTC*'Hypothèses'!T170 | U51: =SUM(C51:T51)
A52: Commission des créateurs | C52: =C41*ue_TTS_TTC*h_CREA_COMM | D52: =D41*ue_TTS_TTC*h_CREA_COMM | E52: =E41*ue_TTS_TTC*h_CREA_COMM | F52: =F41*ue_TTS_TTC*h_CREA_COMM | G52: =G41*ue_TTS_TTC*h_CREA_COMM | H52: =H41*ue_TTS_TTC*h_CREA_COMM | I52: =I41*ue_TTS_TTC*h_CREA_COMM | J52: =J41*ue_TTS_TTC*h_CREA_COMM | ... T52: =T41*ue_TTS_TTC*h_CREA_COMM | U52: =SUM(C52:T52)
A53: Provision retours, SAV, litiges | C53: =h_PROV_RETOURS*C46 | D53: =h_PROV_RETOURS*D46 | E53: =h_PROV_RETOURS*E46 | F53: =h_PROV_RETOURS*F46 | G53: =h_PROV_RETOURS*G46 | H53: =h_PROV_RETOURS*H46 | I53: =h_PROV_RETOURS*I46 | J53: =h_PROV_RETOURS*J46 | ... T53: =h_PROV_RETOURS*T46 | U53: =SUM(C53:T53)
A54: Marge de contribution | C54: =C46-SUM(C48:C53) | D54: =D46-SUM(D48:D53) | E54: =E46-SUM(E48:E53) | F54: =F46-SUM(F48:F53) | G54: =G46-SUM(G48:G53) | H54: =H46-SUM(H48:H53) | I54: =I46-SUM(I48:I53) | J54: =J46-SUM(J48:J53) | ... T54: =T46-SUM(T48:T53) | U54: =SUM(C54:T54)
A55: Publicité | C55: ='Hypothèses'!C172 | D55: ='Hypothèses'!D172 | E55: ='Hypothèses'!E172 | F55: ='Hypothèses'!F172 | G55: ='Hypothèses'!G172 | H55: ='Hypothèses'!H172 | I55: ='Hypothèses'!I172 | J55: ='Hypothèses'!J172 | ... T55: ='Hypothèses'!T172 | U55: =SUM(C55:T55)
A56: Échantillons créateurs | C56: ='Hypothèses'!C174 | D56: ='Hypothèses'!D174 | E56: ='Hypothèses'!E174 | F56: ='Hypothèses'!F174 | G56: ='Hypothèses'!G174 | H56: ='Hypothèses'!H174 | I56: ='Hypothèses'!I174 | J56: ='Hypothèses'!J174 | ... T56: ='Hypothèses'!T174 | U56: =SUM(C56:T56)
A57: Frais fixes et ponctuels | C57: ='Hypothèses'!C178+'Hypothèses'!C179+'Hypothèses'!C180+'Hypothèses'!C181+'Hypothèses'!C182 | D57: ='Hypothèses'!D178+'Hypothèses'!D179+'Hypothèses'!D180+'Hypothèses'!D181+'Hypothèses'!D182 | E57: ='Hypothèses'!E178+'Hypothèses'!E179+'Hypothèses'!E180+'Hypothèses'!E181+'Hypothèses'!E182 | F57: ='Hypothèses'!F178+'Hypothèses'!F179+'Hypothèses'!F180+'Hypothèses'!F181+'Hypothèses'!F182 | G57: ='Hypothèses'!G178+'Hypothèses'!G179+'Hypothèses'!G180+'Hypothèses'!G181+'Hypothèses'!G182 | H57: ='Hypothèses'!H178+'Hypothèses'!H179+'Hypothèses'!H180+'Hypothèses'!H181+'Hypothèses'!H182 | I57: ='Hypothèses'!I178+'Hypothèses'!I179+'Hypothèses'!I180+'Hypothèses'!I181+'Hypothèses'!I182 | J57: ='Hypothèses'!J178+'Hypothèses'!J179+'Hypothèses'!J180+'Hypothèses'!J181+'Hypothèses'!J182 | ... T57: ='Hypothèses'!T178+'Hypothèses'!T179+'Hypothèses'!T180+'Hypothèses'!T181+'Hypothèses'!T182 | U57: =SUM(C57:T57)
A58: Bénéfice net (avant IS et rémunération du dirigeant) | C58: =C54-C55-C56-C57 | D58: =D54-D55-D56-D57 | E58: =E54-E55-E56-E57 | F58: =F54-F55-F56-F57 | G58: =G54-G55-G56-G57 | H58: =H54-H55-H56-H57 | I58: =I54-I55-I56-I57 | J58: =J54-J55-J56-J57 | ... T58: =T54-T55-T56-T57 | U58: =SUM(C58:T58)
A59: Bénéfice net cumulé | C59: =C58 | D59: =D58+C59 | E59: =E58+D59 | F59: =F58+E59 | G59: =G58+F59 | H59: =H58+G59 | I59: =I58+H59 | J59: =J58+I59 | K59: =K58+J59 | ... T59: =T58+S59
A60: Coûts totaux (CA HT − bénéfice net) | C60: =C46-C58 | D60: =D46-D58 | E60: =E46-E58 | F60: =F46-F58 | G60: =G46-G58 | H60: =H46-H58 | I60: =I46-I58 | J60: =J46-J58 | ... T60: =T46-T58 | U60: =SUM(C60:T60)
A61: Nouvel exercice (1 = oui) | C61: =1 | D61: =IF(D38<>C38,1,0) | E61: =IF(E38<>D38,1,0) | F61: =IF(F38<>E38,1,0) | G61: =IF(G38<>F38,1,0) | H61: =IF(H38<>G38,1,0) | I61: =IF(I38<>H38,1,0) | J61: =IF(J38<>I38,1,0) | K61: =IF(K38<>J38,1,0) | ... T61: =IF(T38<>S38,1,0)
A62: Base IS cumulée de l'exercice (déficit antérieur reporté) | C62: =C58 | D62: =IF(D61=1,MIN(0,C62)+D58,C62+D58) | E62: =IF(E61=1,MIN(0,D62)+E58,D62+E58) | F62: =IF(F61=1,MIN(0,E62)+F58,E62+F58) | G62: =IF(G61=1,MIN(0,F62)+G58,F62+G58) | H62: =IF(H61=1,MIN(0,G62)+H58,G62+H58) | I62: =IF(I61=1,MIN(0,H62)+I58,H62+I58) | J62: =IF(J61=1,MIN(0,I62)+J58,I62+J58) | K62: =IF(K61=1,MIN(0,J62)+K58,J62+K58) | ... T62: =IF(T61=1,MIN(0,S62)+T58,S62+T58)
A63: IS cumulé de l'exercice | C63: =h_IS_TAUX_REDUIT*MIN(MAX(C62,0),h_IS_SEUIL)+h_IS_TAUX_NORMAL*MAX(C62-h_IS_SEUIL,0) | D63: =h_IS_TAUX_REDUIT*MIN(MAX(D62,0),h_IS_SEUIL)+h_IS_TAUX_NORMAL*MAX(D62-h_IS_SEUIL,0) | E63: =h_IS_TAUX_REDUIT*MIN(MAX(E62,0),h_IS_SEUIL)+h_IS_TAUX_NORMAL*MAX(E62-h_IS_SEUIL,0) | F63: =h_IS_TAUX_REDUIT*MIN(MAX(F62,0),h_IS_SEUIL)+h_IS_TAUX_NORMAL*MAX(F62-h_IS_SEUIL,0) | G63: =h_IS_TAUX_REDUIT*MIN(MAX(G62,0),h_IS_SEUIL)+h_IS_TAUX_NORMAL*MAX(G62-h_IS_SEUIL,0) | H63: =h_IS_TAUX_REDUIT*MIN(MAX(H62,0),h_IS_SEUIL)+h_IS_TAUX_NORMAL*MAX(H62-h_IS_SEUIL,0) | I63: =h_IS_TAUX_REDUIT*MIN(MAX(I62,0),h_IS_SEUIL)+h_IS_TAUX_NORMAL*MAX(I62-h_IS_SEUIL,0) | J63: =h_IS_TAUX_REDUIT*MIN(MAX(J62,0),h_IS_SEUIL)+h_IS_TAUX_NORMAL*MAX(J62-h_IS_SEUIL,0) | ... T63: =h_IS_TAUX_REDUIT*MIN(MAX(T62,0),h_IS_SEUIL)+h_IS_TAUX_NORMAL*MAX(T62-h_IS_SEUIL,0)
A64: IS du mois (provision) | C64: =C63 | D64: =IF(D61=1,D63,D63-C63) | E64: =IF(E61=1,E63,E63-D63) | F64: =IF(F61=1,F63,F63-E63) | G64: =IF(G61=1,G63,G63-F63) | H64: =IF(H61=1,H63,H63-G63) | I64: =IF(I61=1,I63,I63-H63) | J64: =IF(J61=1,J63,J63-I63) | K64: =IF(K61=1,K63,K63-J63) | ... T64: =IF(T61=1,T63,T63-S63) | U64: =SUM(C64:T64)
A65: Résultat après IS | C65: =C58-C64 | D65: =D58-D64 | E65: =E58-E64 | F65: =F58-F64 | G65: =G58-G64 | H65: =H58-H64 | I65: =I58-I64 | J65: =J58-J64 | ... T65: =T58-T64 | U65: =SUM(C65:T65)
A68: Scénario optimiste — Vidéo virale en décembre avec du stock ; affiliés nombreux ; import groupé en juin 2027 ; publicité rentable à 14 € de CPA dès juillet 2027.
A69: Ligne | C69: oct. 2026 | D69: nov. 2026 | E69: déc. 2026 | F69: janv. 2027 | G69: févr. 2027 | H69: mars 2027 | I69: avr. 2027 | J69: mai 2027 | K69: juin 2027 | L69: juil. 2027 | M69: août 2027 | N69: sept. 2027 | O69: oct. 2027 | P69: nov. 2027 | Q69: déc. 2027 | R69: janv. 2028 | S69: févr. 2028 | T69: mars 2028 | U69: Total 18 mois
A70: Exercice | C70: ='Hypothèses'!C186 | D70: ='Hypothèses'!D186 | E70: ='Hypothèses'!E186 | F70: ='Hypothèses'!F186 | G70: ='Hypothèses'!G186 | H70: ='Hypothèses'!H186 | I70: ='Hypothèses'!I186 | J70: ='Hypothèses'!J186 | ... T70: ='Hypothèses'!T186
A71: Commandes site (organique) | C71: ='Hypothèses'!C187*'Hypothèses'!C188 | D71: ='Hypothèses'!D187*'Hypothèses'!D188 | E71: ='Hypothèses'!E187*'Hypothèses'!E188 | F71: ='Hypothèses'!F187*'Hypothèses'!F188 | G71: ='Hypothèses'!G187*'Hypothèses'!G188 | H71: ='Hypothèses'!H187*'Hypothèses'!H188 | I71: ='Hypothèses'!I187*'Hypothèses'!I188 | J71: ='Hypothèses'!J187*'Hypothèses'!J188 | ... T71: ='Hypothèses'!T187*'Hypothèses'!T188 | U71: =SUM(C71:T71)
A72: Commandes TikTok Shop, contenu propre | C72: ='Hypothèses'!C187*'Hypothèses'!C189 | D72: ='Hypothèses'!D187*'Hypothèses'!D189 | E72: ='Hypothèses'!E187*'Hypothèses'!E189 | F72: ='Hypothèses'!F187*'Hypothèses'!F189 | G72: ='Hypothèses'!G187*'Hypothèses'!G189 | H72: ='Hypothèses'!H187*'Hypothèses'!H189 | I72: ='Hypothèses'!I187*'Hypothèses'!I189 | J72: ='Hypothèses'!J187*'Hypothèses'!J189 | ... T72: ='Hypothèses'!T187*'Hypothèses'!T189 | U72: =SUM(C72:T72)
A73: Commandes TikTok Shop, affiliés | C73: ='Hypothèses'!C187*'Hypothèses'!C190 | D73: ='Hypothèses'!D187*'Hypothèses'!D190 | E73: ='Hypothèses'!E187*'Hypothèses'!E190 | F73: ='Hypothèses'!F187*'Hypothèses'!F190 | G73: ='Hypothèses'!G187*'Hypothèses'!G190 | H73: ='Hypothèses'!H187*'Hypothèses'!H190 | I73: ='Hypothèses'!I187*'Hypothèses'!I190 | J73: ='Hypothèses'!J187*'Hypothèses'!J190 | ... T73: ='Hypothèses'!T187*'Hypothèses'!T190 | U73: =SUM(C73:T73)
A74: Commandes issues de la publicité | C74: =IF('Hypothèses'!C194>0,'Hypothèses'!C193/'Hypothèses'!C194,0) | D74: =IF('Hypothèses'!D194>0,'Hypothèses'!D193/'Hypothèses'!D194,0) | E74: =IF('Hypothèses'!E194>0,'Hypothèses'!E193/'Hypothèses'!E194,0) | F74: =IF('Hypothèses'!F194>0,'Hypothèses'!F193/'Hypothèses'!F194,0) | G74: =IF('Hypothèses'!G194>0,'Hypothèses'!G193/'Hypothèses'!G194,0) | H74: =IF('Hypothèses'!H194>0,'Hypothèses'!H193/'Hypothèses'!H194,0) | I74: =IF('Hypothèses'!I194>0,'Hypothèses'!I193/'Hypothèses'!I194,0) | J74: =IF('Hypothèses'!J194>0,'Hypothèses'!J193/'Hypothèses'!J194,0) | ... T74: =IF('Hypothèses'!T194>0,'Hypothèses'!T193/'Hypothèses'!T194,0) | U74: =SUM(C74:T74)
A75: Commandes totales | C75: =C71+C72+C73+C74 | D75: =D71+D72+D73+D74 | E75: =E71+E72+E73+E74 | F75: =F71+F72+F73+F74 | G75: =G71+G72+G73+G74 | H75: =H71+H72+H73+H74 | I75: =I71+I72+I73+I74 | J75: =J71+J72+J73+J74 | ... T75: =T71+T72+T73+T74 | U75: =SUM(C75:T75)
A76: Commandes par jour | C76: =C75/30 | D76: =D75/30 | E76: =E75/30 | F76: =F75/30 | G76: =G75/30 | H76: =H75/30 | I76: =I75/30 | J76: =J75/30 | ... T76: =T75/30
A77: CA TTC | C77: =C71*ue_SITE_TTC+(C72+C73)*ue_TTS_TTC+C74*ue_PUB_TTC | D77: =D71*ue_SITE_TTC+(D72+D73)*ue_TTS_TTC+D74*ue_PUB_TTC | E77: =E71*ue_SITE_TTC+(E72+E73)*ue_TTS_TTC+E74*ue_PUB_TTC | F77: =F71*ue_SITE_TTC+(F72+F73)*ue_TTS_TTC+F74*ue_PUB_TTC | G77: =G71*ue_SITE_TTC+(G72+G73)*ue_TTS_TTC+G74*ue_PUB_TTC | H77: =H71*ue_SITE_TTC+(H72+H73)*ue_TTS_TTC+H74*ue_PUB_TTC | I77: =I71*ue_SITE_TTC+(I72+I73)*ue_TTS_TTC+I74*ue_PUB_TTC | J77: =J71*ue_SITE_TTC+(J72+J73)*ue_TTS_TTC+J74*ue_PUB_TTC | ... T77: =T71*ue_SITE_TTC+(T72+T73)*ue_TTS_TTC+T74*ue_PUB_TTC | U77: =SUM(C77:T77)
A78: CA HT | C78: =C77/(1+h_TVA) | D78: =D77/(1+h_TVA) | E78: =E77/(1+h_TVA) | F78: =F77/(1+h_TVA) | G78: =G77/(1+h_TVA) | H78: =H77/(1+h_TVA) | I78: =I77/(1+h_TVA) | J78: =J77/(1+h_TVA) | ... T78: =T77/(1+h_TVA) | U78: =SUM(C78:T78)
A79: TVA collectée | C79: =C77-C78 | D79: =D77-D78 | E79: =E77-E78 | F79: =F77-F78 | G79: =G77-G78 | H79: =H77-H78 | I79: =I77-I78 | J79: =J77-J78 | ... T79: =T77-T78 | U79: =SUM(C79:T79)
A80: Coût des produits et droits | C80: =C71*IF('Hypothèses'!C192=1,ue_SITE_PROD_IMP,ue_SITE_PROD_MS)+(C72+C73)*IF('Hypothèses'!C192=1,ue_TTS_PROD_IMP,ue_TTS_PROD_MS)+C74*IF('Hypothèses'!C192=1,ue_PUB_PROD_IMP,ue_PUB_PROD_MS) | D80: =D71*IF('Hypothèses'!D192=1,ue_SITE_PROD_IMP,ue_SITE_PROD_MS)+(D72+D73)*IF('Hypothèses'!D192=1,ue_TTS_PROD_IMP,ue_TTS_PROD_MS)+D74*IF('Hypothèses'!D192=1,ue_PUB_PROD_IMP,ue_PUB_PROD_MS) | E80: =E71*IF('Hypothèses'!E192=1,ue_SITE_PROD_IMP,ue_SITE_PROD_MS)+(E72+E73)*IF('Hypothèses'!E192=1,ue_TTS_PROD_IMP,ue_TTS_PROD_MS)+E74*IF('Hypothèses'!E192=1,ue_PUB_PROD_IMP,ue_PUB_PROD_MS) | F80: =F71*IF('Hypothèses'!F192=1,ue_SITE_PROD_IMP,ue_SITE_PROD_MS)+(F72+F73)*IF('Hypothèses'!F192=1,ue_TTS_PROD_IMP,ue_TTS_PROD_MS)+F74*IF('Hypothèses'!F192=1,ue_PUB_PROD_IMP,ue_PUB_PROD_MS) | G80: =G71*IF('Hypothèses'!G192=1,ue_SITE_PROD_IMP,ue_SITE_PROD_MS)+(G72+G73)*IF('Hypothèses'!G192=1,ue_TTS_PROD_IMP,ue_TTS_PROD_MS)+G74*IF('Hypothèses'!G192=1,ue_PUB_PROD_IMP,ue_PUB_PROD_MS) | H80: =H71*IF('Hypothèses'!H192=1,ue_SITE_PROD_IMP,ue_SITE_PROD_MS)+(H72+H73)*IF('Hypothèses'!H192=1,ue_TTS_PROD_IMP,ue_TTS_PROD_MS)+H74*IF('Hypothèses'!H192=1,ue_PUB_PROD_IMP,ue_PUB_PROD_MS) | I80: =I71*IF('Hypothèses'!I192=1,ue_SITE_PROD_IMP,ue_SITE_PROD_MS)+(I72+I73)*IF('Hypothèses'!I192=1,ue_TTS_PROD_IMP,ue_TTS_PROD_MS)+I74*IF('Hypothèses'!I192=1,ue_PUB_PROD_IMP,ue_PUB_PROD_MS) | J80: =J71*IF('Hypothèses'!J192=1,ue_SITE_PROD_IMP,ue_SITE_PROD_MS)+(J72+J73)*IF('Hypothèses'!J192=1,ue_TTS_PROD_IMP,ue_TTS_PROD_MS)+J74*IF('Hypothèses'!J192=1,ue_PUB_PROD_IMP,ue_PUB_PROD_MS) | ... T80: =T71*IF('Hypothèses'!T192=1,ue_SITE_PROD_IMP,ue_SITE_PROD_MS)+(T72+T73)*IF('Hypothèses'!T192=1,ue_TTS_PROD_IMP,ue_TTS_PROD_MS)+T74*IF('Hypothèses'!T192=1,ue_PUB_PROD_IMP,ue_PUB_PROD_MS) | U80: =SUM(C80:T80)
A81: Livraison, emballage, 3PL | C81: =C71*IF('Hypothèses'!C192=1,ue_SITE_LOG_IMP,ue_SITE_LOG_MS)+(C72+C73)*IF('Hypothèses'!C192=1,ue_TTS_LOG_IMP,ue_TTS_LOG_MS)+C74*IF('Hypothèses'!C192=1,ue_PUB_LOG_IMP,ue_PUB_LOG_MS) | D81: =D71*IF('Hypothèses'!D192=1,ue_SITE_LOG_IMP,ue_SITE_LOG_MS)+(D72+D73)*IF('Hypothèses'!D192=1,ue_TTS_LOG_IMP,ue_TTS_LOG_MS)+D74*IF('Hypothèses'!D192=1,ue_PUB_LOG_IMP,ue_PUB_LOG_MS) | E81: =E71*IF('Hypothèses'!E192=1,ue_SITE_LOG_IMP,ue_SITE_LOG_MS)+(E72+E73)*IF('Hypothèses'!E192=1,ue_TTS_LOG_IMP,ue_TTS_LOG_MS)+E74*IF('Hypothèses'!E192=1,ue_PUB_LOG_IMP,ue_PUB_LOG_MS) | F81: =F71*IF('Hypothèses'!F192=1,ue_SITE_LOG_IMP,ue_SITE_LOG_MS)+(F72+F73)*IF('Hypothèses'!F192=1,ue_TTS_LOG_IMP,ue_TTS_LOG_MS)+F74*IF('Hypothèses'!F192=1,ue_PUB_LOG_IMP,ue_PUB_LOG_MS) | G81: =G71*IF('Hypothèses'!G192=1,ue_SITE_LOG_IMP,ue_SITE_LOG_MS)+(G72+G73)*IF('Hypothèses'!G192=1,ue_TTS_LOG_IMP,ue_TTS_LOG_MS)+G74*IF('Hypothèses'!G192=1,ue_PUB_LOG_IMP,ue_PUB_LOG_MS) | H81: =H71*IF('Hypothèses'!H192=1,ue_SITE_LOG_IMP,ue_SITE_LOG_MS)+(H72+H73)*IF('Hypothèses'!H192=1,ue_TTS_LOG_IMP,ue_TTS_LOG_MS)+H74*IF('Hypothèses'!H192=1,ue_PUB_LOG_IMP,ue_PUB_LOG_MS) | I81: =I71*IF('Hypothèses'!I192=1,ue_SITE_LOG_IMP,ue_SITE_LOG_MS)+(I72+I73)*IF('Hypothèses'!I192=1,ue_TTS_LOG_IMP,ue_TTS_LOG_MS)+I74*IF('Hypothèses'!I192=1,ue_PUB_LOG_IMP,ue_PUB_LOG_MS) | J81: =J71*IF('Hypothèses'!J192=1,ue_SITE_LOG_IMP,ue_SITE_LOG_MS)+(J72+J73)*IF('Hypothèses'!J192=1,ue_TTS_LOG_IMP,ue_TTS_LOG_MS)+J74*IF('Hypothèses'!J192=1,ue_PUB_LOG_IMP,ue_PUB_LOG_MS) | ... T81: =T71*IF('Hypothèses'!T192=1,ue_SITE_LOG_IMP,ue_SITE_LOG_MS)+(T72+T73)*IF('Hypothèses'!T192=1,ue_TTS_LOG_IMP,ue_TTS_LOG_MS)+T74*IF('Hypothèses'!T192=1,ue_PUB_LOG_IMP,ue_PUB_LOG_MS) | U81: =SUM(C81:T81)
A82: Frais de paiement | C82: =C71*ue_SITE_PAY+C74*ue_PUB_PAY | D82: =D71*ue_SITE_PAY+D74*ue_PUB_PAY | E82: =E71*ue_SITE_PAY+E74*ue_PUB_PAY | F82: =F71*ue_SITE_PAY+F74*ue_PUB_PAY | G82: =G71*ue_SITE_PAY+G74*ue_PUB_PAY | H82: =H71*ue_SITE_PAY+H74*ue_PUB_PAY | I82: =I71*ue_SITE_PAY+I74*ue_PUB_PAY | J82: =J71*ue_SITE_PAY+J74*ue_PUB_PAY | ... T82: =T71*ue_SITE_PAY+T74*ue_PUB_PAY | U82: =SUM(C82:T82)
A83: Commission TikTok Shop | C83: =(C72+C73)*ue_TTS_TTC*'Hypothèses'!C191 | D83: =(D72+D73)*ue_TTS_TTC*'Hypothèses'!D191 | E83: =(E72+E73)*ue_TTS_TTC*'Hypothèses'!E191 | F83: =(F72+F73)*ue_TTS_TTC*'Hypothèses'!F191 | G83: =(G72+G73)*ue_TTS_TTC*'Hypothèses'!G191 | H83: =(H72+H73)*ue_TTS_TTC*'Hypothèses'!H191 | I83: =(I72+I73)*ue_TTS_TTC*'Hypothèses'!I191 | J83: =(J72+J73)*ue_TTS_TTC*'Hypothèses'!J191 | ... T83: =(T72+T73)*ue_TTS_TTC*'Hypothèses'!T191 | U83: =SUM(C83:T83)
A84: Commission des créateurs | C84: =C73*ue_TTS_TTC*h_CREA_COMM | D84: =D73*ue_TTS_TTC*h_CREA_COMM | E84: =E73*ue_TTS_TTC*h_CREA_COMM | F84: =F73*ue_TTS_TTC*h_CREA_COMM | G84: =G73*ue_TTS_TTC*h_CREA_COMM | H84: =H73*ue_TTS_TTC*h_CREA_COMM | I84: =I73*ue_TTS_TTC*h_CREA_COMM | J84: =J73*ue_TTS_TTC*h_CREA_COMM | ... T84: =T73*ue_TTS_TTC*h_CREA_COMM | U84: =SUM(C84:T84)
A85: Provision retours, SAV, litiges | C85: =h_PROV_RETOURS*C78 | D85: =h_PROV_RETOURS*D78 | E85: =h_PROV_RETOURS*E78 | F85: =h_PROV_RETOURS*F78 | G85: =h_PROV_RETOURS*G78 | H85: =h_PROV_RETOURS*H78 | I85: =h_PROV_RETOURS*I78 | J85: =h_PROV_RETOURS*J78 | ... T85: =h_PROV_RETOURS*T78 | U85: =SUM(C85:T85)
A86: Marge de contribution | C86: =C78-SUM(C80:C85) | D86: =D78-SUM(D80:D85) | E86: =E78-SUM(E80:E85) | F86: =F78-SUM(F80:F85) | G86: =G78-SUM(G80:G85) | H86: =H78-SUM(H80:H85) | I86: =I78-SUM(I80:I85) | J86: =J78-SUM(J80:J85) | ... T86: =T78-SUM(T80:T85) | U86: =SUM(C86:T86)
A87: Publicité | C87: ='Hypothèses'!C193 | D87: ='Hypothèses'!D193 | E87: ='Hypothèses'!E193 | F87: ='Hypothèses'!F193 | G87: ='Hypothèses'!G193 | H87: ='Hypothèses'!H193 | I87: ='Hypothèses'!I193 | J87: ='Hypothèses'!J193 | ... T87: ='Hypothèses'!T193 | U87: =SUM(C87:T87)
A88: Échantillons créateurs | C88: ='Hypothèses'!C195 | D88: ='Hypothèses'!D195 | E88: ='Hypothèses'!E195 | F88: ='Hypothèses'!F195 | G88: ='Hypothèses'!G195 | H88: ='Hypothèses'!H195 | I88: ='Hypothèses'!I195 | J88: ='Hypothèses'!J195 | ... T88: ='Hypothèses'!T195 | U88: =SUM(C88:T88)
A89: Frais fixes et ponctuels | C89: ='Hypothèses'!C199+'Hypothèses'!C200+'Hypothèses'!C201+'Hypothèses'!C202+'Hypothèses'!C203 | D89: ='Hypothèses'!D199+'Hypothèses'!D200+'Hypothèses'!D201+'Hypothèses'!D202+'Hypothèses'!D203 | E89: ='Hypothèses'!E199+'Hypothèses'!E200+'Hypothèses'!E201+'Hypothèses'!E202+'Hypothèses'!E203 | F89: ='Hypothèses'!F199+'Hypothèses'!F200+'Hypothèses'!F201+'Hypothèses'!F202+'Hypothèses'!F203 | G89: ='Hypothèses'!G199+'Hypothèses'!G200+'Hypothèses'!G201+'Hypothèses'!G202+'Hypothèses'!G203 | H89: ='Hypothèses'!H199+'Hypothèses'!H200+'Hypothèses'!H201+'Hypothèses'!H202+'Hypothèses'!H203 | I89: ='Hypothèses'!I199+'Hypothèses'!I200+'Hypothèses'!I201+'Hypothèses'!I202+'Hypothèses'!I203 | J89: ='Hypothèses'!J199+'Hypothèses'!J200+'Hypothèses'!J201+'Hypothèses'!J202+'Hypothèses'!J203 | ... T89: ='Hypothèses'!T199+'Hypothèses'!T200+'Hypothèses'!T201+'Hypothèses'!T202+'Hypothèses'!T203 | U89: =SUM(C89:T89)
A90: Bénéfice net (avant IS et rémunération du dirigeant) | C90: =C86-C87-C88-C89 | D90: =D86-D87-D88-D89 | E90: =E86-E87-E88-E89 | F90: =F86-F87-F88-F89 | G90: =G86-G87-G88-G89 | H90: =H86-H87-H88-H89 | I90: =I86-I87-I88-I89 | J90: =J86-J87-J88-J89 | ... T90: =T86-T87-T88-T89 | U90: =SUM(C90:T90)
A91: Bénéfice net cumulé | C91: =C90 | D91: =D90+C91 | E91: =E90+D91 | F91: =F90+E91 | G91: =G90+F91 | H91: =H90+G91 | I91: =I90+H91 | J91: =J90+I91 | K91: =K90+J91 | ... T91: =T90+S91
A92: Coûts totaux (CA HT − bénéfice net) | C92: =C78-C90 | D92: =D78-D90 | E92: =E78-E90 | F92: =F78-F90 | G92: =G78-G90 | H92: =H78-H90 | I92: =I78-I90 | J92: =J78-J90 | ... T92: =T78-T90 | U92: =SUM(C92:T92)
A93: Nouvel exercice (1 = oui) | C93: =1 | D93: =IF(D70<>C70,1,0) | E93: =IF(E70<>D70,1,0) | F93: =IF(F70<>E70,1,0) | G93: =IF(G70<>F70,1,0) | H93: =IF(H70<>G70,1,0) | I93: =IF(I70<>H70,1,0) | J93: =IF(J70<>I70,1,0) | K93: =IF(K70<>J70,1,0) | ... T93: =IF(T70<>S70,1,0)
A94: Base IS cumulée de l'exercice (déficit antérieur reporté) | C94: =C90 | D94: =IF(D93=1,MIN(0,C94)+D90,C94+D90) | E94: =IF(E93=1,MIN(0,D94)+E90,D94+E90) | F94: =IF(F93=1,MIN(0,E94)+F90,E94+F90) | G94: =IF(G93=1,MIN(0,F94)+G90,F94+G90) | H94: =IF(H93=1,MIN(0,G94)+H90,G94+H90) | I94: =IF(I93=1,MIN(0,H94)+I90,H94+I90) | J94: =IF(J93=1,MIN(0,I94)+J90,I94+J90) | K94: =IF(K93=1,MIN(0,J94)+K90,J94+K90) | ... T94: =IF(T93=1,MIN(0,S94)+T90,S94+T90)
A95: IS cumulé de l'exercice | C95: =h_IS_TAUX_REDUIT*MIN(MAX(C94,0),h_IS_SEUIL)+h_IS_TAUX_NORMAL*MAX(C94-h_IS_SEUIL,0) | D95: =h_IS_TAUX_REDUIT*MIN(MAX(D94,0),h_IS_SEUIL)+h_IS_TAUX_NORMAL*MAX(D94-h_IS_SEUIL,0) | E95: =h_IS_TAUX_REDUIT*MIN(MAX(E94,0),h_IS_SEUIL)+h_IS_TAUX_NORMAL*MAX(E94-h_IS_SEUIL,0) | F95: =h_IS_TAUX_REDUIT*MIN(MAX(F94,0),h_IS_SEUIL)+h_IS_TAUX_NORMAL*MAX(F94-h_IS_SEUIL,0) | G95: =h_IS_TAUX_REDUIT*MIN(MAX(G94,0),h_IS_SEUIL)+h_IS_TAUX_NORMAL*MAX(G94-h_IS_SEUIL,0) | H95: =h_IS_TAUX_REDUIT*MIN(MAX(H94,0),h_IS_SEUIL)+h_IS_TAUX_NORMAL*MAX(H94-h_IS_SEUIL,0) | I95: =h_IS_TAUX_REDUIT*MIN(MAX(I94,0),h_IS_SEUIL)+h_IS_TAUX_NORMAL*MAX(I94-h_IS_SEUIL,0) | J95: =h_IS_TAUX_REDUIT*MIN(MAX(J94,0),h_IS_SEUIL)+h_IS_TAUX_NORMAL*MAX(J94-h_IS_SEUIL,0) | ... T95: =h_IS_TAUX_REDUIT*MIN(MAX(T94,0),h_IS_SEUIL)+h_IS_TAUX_NORMAL*MAX(T94-h_IS_SEUIL,0)
A96: IS du mois (provision) | C96: =C95 | D96: =IF(D93=1,D95,D95-C95) | E96: =IF(E93=1,E95,E95-D95) | F96: =IF(F93=1,F95,F95-E95) | G96: =IF(G93=1,G95,G95-F95) | H96: =IF(H93=1,H95,H95-G95) | I96: =IF(I93=1,I95,I95-H95) | J96: =IF(J93=1,J95,J95-I95) | K96: =IF(K93=1,K95,K95-J95) | ... T96: =IF(T93=1,T95,T95-S95) | U96: =SUM(C96:T96)
A97: Résultat après IS | C97: =C90-C96 | D97: =D90-D96 | E97: =E90-E96 | F97: =F90-F96 | G97: =G90-G96 | H97: =H90-H96 | I97: =I90-I96 | J97: =J90-J96 | ... T97: =T90-T96 | U97: =SUM(C97:T97)

Sheet Trésorerie
A1: Trésorerie mensuelle — départ à 0 €, fournisseurs payés à la commande
A2: Stripe : 7 jours au premier versement puis 3 jours ouvrés ; TikTok Shop : 31 jours après livraison pour un vendeur débutant, puis 8 jours ; TVA reversée le mois suivant ; stock détenu = couverture × coût des produits du mois suivant.
A4: Scénario pessimiste
A5: Ligne | C5: oct. 2026 | D5: nov. 2026 | E5: déc. 2026 | F5: janv. 2027 | G5: févr. 2027 | H5: mars 2027 | I5: avr. 2027 | J5: mai 2027 | K5: juin 2027 | L5: juil. 2027 | M5: août 2027 | N5: sept. 2027 | O5: oct. 2027 | P5: nov. 2027 | Q5: déc. 2027 | R5: janv. 2028 | S5: févr. 2028 | T5: mars 2028 | U5: Total
A6: Ventes du site nettes de frais de paiement (dues) | C6: ='Scénarios 18 mois'!C7*(ue_SITE_TTC-ue_SITE_PAY)+'Scénarios 18 mois'!C10*(ue_PUB_TTC-ue_PUB_PAY) | D6: ='Scénarios 18 mois'!D7*(ue_SITE_TTC-ue_SITE_PAY)+'Scénarios 18 mois'!D10*(ue_PUB_TTC-ue_PUB_PAY) | E6: ='Scénarios 18 mois'!E7*(ue_SITE_TTC-ue_SITE_PAY)+'Scénarios 18 mois'!E10*(ue_PUB_TTC-ue_PUB_PAY) | F6: ='Scénarios 18 mois'!F7*(ue_SITE_TTC-ue_SITE_PAY)+'Scénarios 18 mois'!F10*(ue_PUB_TTC-ue_PUB_PAY) | G6: ='Scénarios 18 mois'!G7*(ue_SITE_TTC-ue_SITE_PAY)+'Scénarios 18 mois'!G10*(ue_PUB_TTC-ue_PUB_PAY) | H6: ='Scénarios 18 mois'!H7*(ue_SITE_TTC-ue_SITE_PAY)+'Scénarios 18 mois'!H10*(ue_PUB_TTC-ue_PUB_PAY) | I6: ='Scénarios 18 mois'!I7*(ue_SITE_TTC-ue_SITE_PAY)+'Scénarios 18 mois'!I10*(ue_PUB_TTC-ue_PUB_PAY) | J6: ='Scénarios 18 mois'!J7*(ue_SITE_TTC-ue_SITE_PAY)+'Scénarios 18 mois'!J10*(ue_PUB_TTC-ue_PUB_PAY) | ... T6: ='Scénarios 18 mois'!T7*(ue_SITE_TTC-ue_SITE_PAY)+'Scénarios 18 mois'!T10*(ue_PUB_TTC-ue_PUB_PAY)
A7: Encaissement Stripe / Shopify Payments | C7: =C6*(1-'Hypothèses'!C155/30) | D7: =D6*(1-'Hypothèses'!D155/30)+C6*'Hypothèses'!C155/30 | E7: =E6*(1-'Hypothèses'!E155/30)+D6*'Hypothèses'!D155/30 | F7: =F6*(1-'Hypothèses'!F155/30)+E6*'Hypothèses'!E155/30 | G7: =G6*(1-'Hypothèses'!G155/30)+F6*'Hypothèses'!F155/30 | H7: =H6*(1-'Hypothèses'!H155/30)+G6*'Hypothèses'!G155/30 | I7: =I6*(1-'Hypothèses'!I155/30)+H6*'Hypothèses'!H155/30 | J7: =J6*(1-'Hypothèses'!J155/30)+I6*'Hypothèses'!I155/30 | K7: =K6*(1-'Hypothèses'!K155/30)+J6*'Hypothèses'!J155/30 | ... T7: =T6*(1-'Hypothèses'!T155/30)+S6*'Hypothèses'!S155/30 | U7: =SUM(C7:T7)
A8: Ventes TikTok Shop nettes de commissions (dues) | C8: =('Scénarios 18 mois'!C8+'Scénarios 18 mois'!C9)*ue_TTS_TTC*(1-'Hypothèses'!C149)-'Scénarios 18 mois'!C9*ue_TTS_TTC*h_CREA_COMM | D8: =('Scénarios 18 mois'!D8+'Scénarios 18 mois'!D9)*ue_TTS_TTC*(1-'Hypothèses'!D149)-'Scénarios 18 mois'!D9*ue_TTS_TTC*h_CREA_COMM | E8: =('Scénarios 18 mois'!E8+'Scénarios 18 mois'!E9)*ue_TTS_TTC*(1-'Hypothèses'!E149)-'Scénarios 18 mois'!E9*ue_TTS_TTC*h_CREA_COMM | F8: =('Scénarios 18 mois'!F8+'Scénarios 18 mois'!F9)*ue_TTS_TTC*(1-'Hypothèses'!F149)-'Scénarios 18 mois'!F9*ue_TTS_TTC*h_CREA_COMM | G8: =('Scénarios 18 mois'!G8+'Scénarios 18 mois'!G9)*ue_TTS_TTC*(1-'Hypothèses'!G149)-'Scénarios 18 mois'!G9*ue_TTS_TTC*h_CREA_COMM | H8: =('Scénarios 18 mois'!H8+'Scénarios 18 mois'!H9)*ue_TTS_TTC*(1-'Hypothèses'!H149)-'Scénarios 18 mois'!H9*ue_TTS_TTC*h_CREA_COMM | I8: =('Scénarios 18 mois'!I8+'Scénarios 18 mois'!I9)*ue_TTS_TTC*(1-'Hypothèses'!I149)-'Scénarios 18 mois'!I9*ue_TTS_TTC*h_CREA_COMM | J8: =('Scénarios 18 mois'!J8+'Scénarios 18 mois'!J9)*ue_TTS_TTC*(1-'Hypothèses'!J149)-'Scénarios 18 mois'!J9*ue_TTS_TTC*h_CREA_COMM | ... T8: =('Scénarios 18 mois'!T8+'Scénarios 18 mois'!T9)*ue_TTS_TTC*(1-'Hypothèses'!T149)-'Scénarios 18 mois'!T9*ue_TTS_TTC*h_CREA_COMM
A9: Délai d'encaissement TikTok Shop (jours) | C9: ='Hypothèses'!C156 | D9: ='Hypothèses'!D156 | E9: ='Hypothèses'!E156 | F9: ='Hypothèses'!F156 | G9: ='Hypothèses'!G156 | H9: ='Hypothèses'!H156 | I9: ='Hypothèses'!I156 | J9: ='Hypothèses'!J156 | ... T9: ='Hypothèses'!T156
A10: Part encaissée le mois même | C10: =MAX(0,1-C9/30) | D10: =MAX(0,1-D9/30) | E10: =MAX(0,1-E9/30) | F10: =MAX(0,1-F9/30) | G10: =MAX(0,1-G9/30) | H10: =MAX(0,1-H9/30) | I10: =MAX(0,1-I9/30) | J10: =MAX(0,1-J9/30) | ... T10: =MAX(0,1-T9/30)
A11: Part encaissée le mois suivant | C11: =IF(C9<=30,C9/30,(60-C9)/30) | D11: =IF(D9<=30,D9/30,(60-D9)/30) | E11: =IF(E9<=30,E9/30,(60-E9)/30) | F11: =IF(F9<=30,F9/30,(60-F9)/30) | G11: =IF(G9<=30,G9/30,(60-G9)/30) | H11: =IF(H9<=30,H9/30,(60-H9)/30) | I11: =IF(I9<=30,I9/30,(60-I9)/30) | J11: =IF(J9<=30,J9/30,(60-J9)/30) | ... T11: =IF(T9<=30,T9/30,(60-T9)/30)
A12: Part encaissée à M+2 | C12: =MAX(0,(C9-30)/30) | D12: =MAX(0,(D9-30)/30) | E12: =MAX(0,(E9-30)/30) | F12: =MAX(0,(F9-30)/30) | G12: =MAX(0,(G9-30)/30) | H12: =MAX(0,(H9-30)/30) | I12: =MAX(0,(I9-30)/30) | J12: =MAX(0,(J9-30)/30) | ... T12: =MAX(0,(T9-30)/30)
A13: Encaissement TikTok Shop | C13: =C8*C10 | D13: =D8*D10+C8*C11 | E13: =E8*E10+D8*D11+C8*C12 | F13: =F8*F10+E8*E11+D8*D12 | G13: =G8*G10+F8*F11+E8*E12 | H13: =H8*H10+G8*G11+F8*F12 | I13: =I8*I10+H8*H11+G8*G12 | J13: =J8*J10+I8*I11+H8*H12 | K13: =K8*K10+J8*J11+I8*I12 | L13: =L8*L10+K8*K11+J8*J12 | ... T13: =T8*T10+S8*S11+R8*R12 | U13: =SUM(C13:T13)
A14: Total des encaissements | C14: =C7+C13 | D14: =D7+D13 | E14: =E7+E13 | F14: =F7+F13 | G14: =G7+G13 | H14: =H7+H13 | I14: =I7+I13 | J14: =J7+J13 | ... T14: =T7+T13 | U14: =SUM(C14:T14)
A15: Stock en fin de mois (coût HT) | C15: ='Hypothèses'!C154*'Scénarios 18 mois'!D16 | D15: ='Hypothèses'!D154*'Scénarios 18 mois'!E16 | E15: ='Hypothèses'!E154*'Scénarios 18 mois'!F16 | F15: ='Hypothèses'!F154*'Scénarios 18 mois'!G16 | G15: ='Hypothèses'!G154*'Scénarios 18 mois'!H16 | H15: ='Hypothèses'!H154*'Scénarios 18 mois'!I16 | I15: ='Hypothèses'!I154*'Scénarios 18 mois'!J16 | J15: ='Hypothèses'!J154*'Scénarios 18 mois'!K16 | ... S15: ='Hypothèses'!S154*'Scénarios 18 mois'!T16 | T15: ='Hypothèses'!T154*'Scénarios 18 mois'!T16
A16: Achats de stock HT (payés à la commande) | C16: ='Scénarios 18 mois'!C16+C15 | D16: ='Scénarios 18 mois'!D16+D15-C15 | E16: ='Scénarios 18 mois'!E16+E15-D15 | F16: ='Scénarios 18 mois'!F16+F15-E15 | G16: ='Scénarios 18 mois'!G16+G15-F15 | H16: ='Scénarios 18 mois'!H16+H15-G15 | I16: ='Scénarios 18 mois'!I16+I15-H15 | J16: ='Scénarios 18 mois'!J16+J15-I15 | K16: ='Scénarios 18 mois'!K16+K15-J15 | ... T16: ='Scénarios 18 mois'!T16+T15-S15 | U16: =SUM(C16:T16)
A17: Achat en import groupé (TVA autoliquidée, 1 = oui) | C17: ='Hypothèses'!D150 | D17: ='Hypothèses'!E150 | E17: ='Hypothèses'!F150 | F17: ='Hypothèses'!G150 | G17: ='Hypothèses'!H150 | H17: ='Hypothèses'!I150 | I17: ='Hypothèses'!J150 | J17: ='Hypothèses'!K150 | ... S17: ='Hypothèses'!T150 | T17: ='Hypothèses'!T150
A18: TVA payée sur achats de micro-stock | C18: =h_TVA*C16*(1-C17) | D18: =h_TVA*D16*(1-D17) | E18: =h_TVA*E16*(1-E17) | F18: =h_TVA*F16*(1-F17) | G18: =h_TVA*G16*(1-G17) | H18: =h_TVA*H16*(1-H17) | I18: =h_TVA*I16*(1-I17) | J18: =h_TVA*J16*(1-J17) | ... T18: =h_TVA*T16*(1-T17) | U18: =SUM(C18:T18)
A19: Étiquettes, emballage, 3PL (TTC) | C19: ='Scénarios 18 mois'!C17*(1+h_TVA) | D19: ='Scénarios 18 mois'!D17*(1+h_TVA) | E19: ='Scénarios 18 mois'!E17*(1+h_TVA) | F19: ='Scénarios 18 mois'!F17*(1+h_TVA) | G19: ='Scénarios 18 mois'!G17*(1+h_TVA) | H19: ='Scénarios 18 mois'!H17*(1+h_TVA) | I19: ='Scénarios 18 mois'!I17*(1+h_TVA) | J19: ='Scénarios 18 mois'!J17*(1+h_TVA) | ... T19: ='Scénarios 18 mois'!T17*(1+h_TVA) | U19: =SUM(C19:T19)
A20: Publicité | C20: ='Scénarios 18 mois'!C23 | D20: ='Scénarios 18 mois'!D23 | E20: ='Scénarios 18 mois'!E23 | F20: ='Scénarios 18 mois'!F23 | G20: ='Scénarios 18 mois'!G23 | H20: ='Scénarios 18 mois'!H23 | I20: ='Scénarios 18 mois'!I23 | J20: ='Scénarios 18 mois'!J23 | ... T20: ='Scénarios 18 mois'!T23 | U20: =SUM(C20:T20)
A21: Échantillons créateurs | C21: ='Scénarios 18 mois'!C24 | D21: ='Scénarios 18 mois'!D24 | E21: ='Scénarios 18 mois'!E24 | F21: ='Scénarios 18 mois'!F24 | G21: ='Scénarios 18 mois'!G24 | H21: ='Scénarios 18 mois'!H24 | I21: ='Scénarios 18 mois'!I24 | J21: ='Scénarios 18 mois'!J24 | ... T21: ='Scénarios 18 mois'!T24 | U21: =SUM(C21:T21)
A22: Frais fixes et ponctuels | C22: ='Scénarios 18 mois'!C25 | D22: ='Scénarios 18 mois'!D25 | E22: ='Scénarios 18 mois'!E25 | F22: ='Scénarios 18 mois'!F25 | G22: ='Scénarios 18 mois'!G25 | H22: ='Scénarios 18 mois'!H25 | I22: ='Scénarios 18 mois'!I25 | J22: ='Scénarios 18 mois'!J25 | ... T22: ='Scénarios 18 mois'!T25 | U22: =SUM(C22:T22)
A23: Remboursements clients et SAV | C23: ='Scénarios 18 mois'!C21 | D23: ='Scénarios 18 mois'!D21 | E23: ='Scénarios 18 mois'!E21 | F23: ='Scénarios 18 mois'!F21 | G23: ='Scénarios 18 mois'!G21 | H23: ='Scénarios 18 mois'!H21 | I23: ='Scénarios 18 mois'!I21 | J23: ='Scénarios 18 mois'!J21 | ... T23: ='Scénarios 18 mois'!T21 | U23: =SUM(C23:T23)
A24: TVA déductible du mois | C24: =C18+h_TVA*'Scénarios 18 mois'!C17 | D24: =D18+h_TVA*'Scénarios 18 mois'!D17 | E24: =E18+h_TVA*'Scénarios 18 mois'!E17 | F24: =F18+h_TVA*'Scénarios 18 mois'!F17 | G24: =G18+h_TVA*'Scénarios 18 mois'!G17 | H24: =H18+h_TVA*'Scénarios 18 mois'!H17 | I24: =I18+h_TVA*'Scénarios 18 mois'!I17 | J24: =J18+h_TVA*'Scénarios 18 mois'!J17 | ... T24: =T18+h_TVA*'Scénarios 18 mois'!T17
A25: TVA nette reversée (mois suivant) | C25: =0 | D25: ='Scénarios 18 mois'!C15-C24 | E25: ='Scénarios 18 mois'!D15-D24 | F25: ='Scénarios 18 mois'!E15-E24 | G25: ='Scénarios 18 mois'!F15-F24 | H25: ='Scénarios 18 mois'!G15-G24 | I25: ='Scénarios 18 mois'!H15-H24 | J25: ='Scénarios 18 mois'!I15-I24 | K25: ='Scénarios 18 mois'!J15-J24 | ... T25: ='Scénarios 18 mois'!S15-S24 | U25: =SUM(C25:T25)
A26: IS payé (solde 2027 dû en mai 2028, hors horizon) | C26: =0 | D26: =0 | E26: =0 | F26: =0 | G26: =0 | H26: =0 | I26: =0 | J26: =0 | ... T26: =0
A27: Total des décaissements | C27: =C16+C18+C19+C20+C21+C22+C23+C25+C26 | D27: =D16+D18+D19+D20+D21+D22+D23+D25+D26 | E27: =E16+E18+E19+E20+E21+E22+E23+E25+E26 | F27: =F16+F18+F19+F20+F21+F22+F23+F25+F26 | G27: =G16+G18+G19+G20+G21+G22+G23+G25+G26 | H27: =H16+H18+H19+H20+H21+H22+H23+H25+H26 | I27: =I16+I18+I19+I20+I21+I22+I23+I25+I26 | J27: =J16+J18+J19+J20+J21+J22+J23+J25+J26 | ... T27: =T16+T18+T19+T20+T21+T22+T23+T25+T26 | U27: =SUM(C27:T27)
A28: Flux de trésorerie du mois | C28: =C14-C27 | D28: =D14-D27 | E28: =E14-E27 | F28: =F14-F27 | G28: =G14-G27 | H28: =H14-H27 | I28: =I14-I27 | J28: =J14-J27 | ... T28: =T14-T27 | U28: =SUM(C28:T28)
A29: Trésorerie en fin de mois (départ : h_TRESO_INITIALE) | C29: =h_TRESO_INITIALE+C28 | D29: =C29+D28 | E29: =D29+E28 | F29: =E29+F28 | G29: =F29+G28 | H29: =G29+H28 | I29: =H29+I28 | J29: =I29+J28 | K29: =J29+K28 | ... T29: =S29+T28
A30: Besoin de trésorerie (creux le plus bas, signe inversé) | C30: =-MIN(0,MIN(C29:T29))
A33: Scénario réaliste
A34: Ligne | C34: oct. 2026 | D34: nov. 2026 | E34: déc. 2026 | F34: janv. 2027 | G34: févr. 2027 | H34: mars 2027 | I34: avr. 2027 | J34: mai 2027 | K34: juin 2027 | L34: juil. 2027 | M34: août 2027 | N34: sept. 2027 | O34: oct. 2027 | P34: nov. 2027 | Q34: déc. 2027 | R34: janv. 2028 | S34: févr. 2028 | T34: mars 2028 | U34: Total
A35: Ventes du site nettes de frais de paiement (dues) | C35: ='Scénarios 18 mois'!C39*(ue_SITE_TTC-ue_SITE_PAY)+'Scénarios 18 mois'!C42*(ue_PUB_TTC-ue_PUB_PAY) | D35: ='Scénarios 18 mois'!D39*(ue_SITE_TTC-ue_SITE_PAY)+'Scénarios 18 mois'!D42*(ue_PUB_TTC-ue_PUB_PAY) | E35: ='Scénarios 18 mois'!E39*(ue_SITE_TTC-ue_SITE_PAY)+'Scénarios 18 mois'!E42*(ue_PUB_TTC-ue_PUB_PAY) | F35: ='Scénarios 18 mois'!F39*(ue_SITE_TTC-ue_SITE_PAY)+'Scénarios 18 mois'!F42*(ue_PUB_TTC-ue_PUB_PAY) | G35: ='Scénarios 18 mois'!G39*(ue_SITE_TTC-ue_SITE_PAY)+'Scénarios 18 mois'!G42*(ue_PUB_TTC-ue_PUB_PAY) | H35: ='Scénarios 18 mois'!H39*(ue_SITE_TTC-ue_SITE_PAY)+'Scénarios 18 mois'!H42*(ue_PUB_TTC-ue_PUB_PAY) | I35: ='Scénarios 18 mois'!I39*(ue_SITE_TTC-ue_SITE_PAY)+'Scénarios 18 mois'!I42*(ue_PUB_TTC-ue_PUB_PAY) | J35: ='Scénarios 18 mois'!J39*(ue_SITE_TTC-ue_SITE_PAY)+'Scénarios 18 mois'!J42*(ue_PUB_TTC-ue_PUB_PAY) | ... T35: ='Scénarios 18 mois'!T39*(ue_SITE_TTC-ue_SITE_PAY)+'Scénarios 18 mois'!T42*(ue_PUB_TTC-ue_PUB_PAY)
A36: Encaissement Stripe / Shopify Payments | C36: =C35*(1-'Hypothèses'!C176/30) | D36: =D35*(1-'Hypothèses'!D176/30)+C35*'Hypothèses'!C176/30 | E36: =E35*(1-'Hypothèses'!E176/30)+D35*'Hypothèses'!D176/30 | F36: =F35*(1-'Hypothèses'!F176/30)+E35*'Hypothèses'!E176/30 | G36: =G35*(1-'Hypothèses'!G176/30)+F35*'Hypothèses'!F176/30 | H36: =H35*(1-'Hypothèses'!H176/30)+G35*'Hypothèses'!G176/30 | I36: =I35*(1-'Hypothèses'!I176/30)+H35*'Hypothèses'!H176/30 | J36: =J35*(1-'Hypothèses'!J176/30)+I35*'Hypothèses'!I176/30 | K36: =K35*(1-'Hypothèses'!K176/30)+J35*'Hypothèses'!J176/30 | ... T36: =T35*(1-'Hypothèses'!T176/30)+S35*'Hypothèses'!S176/30 | U36: =SUM(C36:T36)
A37: Ventes TikTok Shop nettes de commissions (dues) | C37: =('Scénarios 18 mois'!C40+'Scénarios 18 mois'!C41)*ue_TTS_TTC*(1-'Hypothèses'!C170)-'Scénarios 18 mois'!C41*ue_TTS_TTC*h_CREA_COMM | D37: =('Scénarios 18 mois'!D40+'Scénarios 18 mois'!D41)*ue_TTS_TTC*(1-'Hypothèses'!D170)-'Scénarios 18 mois'!D41*ue_TTS_TTC*h_CREA_COMM | E37: =('Scénarios 18 mois'!E40+'Scénarios 18 mois'!E41)*ue_TTS_TTC*(1-'Hypothèses'!E170)-'Scénarios 18 mois'!E41*ue_TTS_TTC*h_CREA_COMM | F37: =('Scénarios 18 mois'!F40+'Scénarios 18 mois'!F41)*ue_TTS_TTC*(1-'Hypothèses'!F170)-'Scénarios 18 mois'!F41*ue_TTS_TTC*h_CREA_COMM | G37: =('Scénarios 18 mois'!G40+'Scénarios 18 mois'!G41)*ue_TTS_TTC*(1-'Hypothèses'!G170)-'Scénarios 18 mois'!G41*ue_TTS_TTC*h_CREA_COMM | H37: =('Scénarios 18 mois'!H40+'Scénarios 18 mois'!H41)*ue_TTS_TTC*(1-'Hypothèses'!H170)-'Scénarios 18 mois'!H41*ue_TTS_TTC*h_CREA_COMM | I37: =('Scénarios 18 mois'!I40+'Scénarios 18 mois'!I41)*ue_TTS_TTC*(1-'Hypothèses'!I170)-'Scénarios 18 mois'!I41*ue_TTS_TTC*h_CREA_COMM | J37: =('Scénarios 18 mois'!J40+'Scénarios 18 mois'!J41)*ue_TTS_TTC*(1-'Hypothèses'!J170)-'Scénarios 18 mois'!J41*ue_TTS_TTC*h_CREA_COMM | ... T37: =('Scénarios 18 mois'!T40+'Scénarios 18 mois'!T41)*ue_TTS_TTC*(1-'Hypothèses'!T170)-'Scénarios 18 mois'!T41*ue_TTS_TTC*h_CREA_COMM
A38: Délai d'encaissement TikTok Shop (jours) | C38: ='Hypothèses'!C177 | D38: ='Hypothèses'!D177 | E38: ='Hypothèses'!E177 | F38: ='Hypothèses'!F177 | G38: ='Hypothèses'!G177 | H38: ='Hypothèses'!H177 | I38: ='Hypothèses'!I177 | J38: ='Hypothèses'!J177 | ... T38: ='Hypothèses'!T177
A39: Part encaissée le mois même | C39: =MAX(0,1-C38/30) | D39: =MAX(0,1-D38/30) | E39: =MAX(0,1-E38/30) | F39: =MAX(0,1-F38/30) | G39: =MAX(0,1-G38/30) | H39: =MAX(0,1-H38/30) | I39: =MAX(0,1-I38/30) | J39: =MAX(0,1-J38/30) | ... T39: =MAX(0,1-T38/30)
A40: Part encaissée le mois suivant | C40: =IF(C38<=30,C38/30,(60-C38)/30) | D40: =IF(D38<=30,D38/30,(60-D38)/30) | E40: =IF(E38<=30,E38/30,(60-E38)/30) | F40: =IF(F38<=30,F38/30,(60-F38)/30) | G40: =IF(G38<=30,G38/30,(60-G38)/30) | H40: =IF(H38<=30,H38/30,(60-H38)/30) | I40: =IF(I38<=30,I38/30,(60-I38)/30) | J40: =IF(J38<=30,J38/30,(60-J38)/30) | ... T40: =IF(T38<=30,T38/30,(60-T38)/30)
A41: Part encaissée à M+2 | C41: =MAX(0,(C38-30)/30) | D41: =MAX(0,(D38-30)/30) | E41: =MAX(0,(E38-30)/30) | F41: =MAX(0,(F38-30)/30) | G41: =MAX(0,(G38-30)/30) | H41: =MAX(0,(H38-30)/30) | I41: =MAX(0,(I38-30)/30) | J41: =MAX(0,(J38-30)/30) | ... T41: =MAX(0,(T38-30)/30)
A42: Encaissement TikTok Shop | C42: =C37*C39 | D42: =D37*D39+C37*C40 | E42: =E37*E39+D37*D40+C37*C41 | F42: =F37*F39+E37*E40+D37*D41 | G42: =G37*G39+F37*F40+E37*E41 | H42: =H37*H39+G37*G40+F37*F41 | I42: =I37*I39+H37*H40+G37*G41 | J42: =J37*J39+I37*I40+H37*H41 | K42: =K37*K39+J37*J40+I37*I41 | L42: =L37*L39+K37*K40+J37*J41 | ... T42: =T37*T39+S37*S40+R37*R41 | U42: =SUM(C42:T42)
A43: Total des encaissements | C43: =C36+C42 | D43: =D36+D42 | E43: =E36+E42 | F43: =F36+F42 | G43: =G36+G42 | H43: =H36+H42 | I43: =I36+I42 | J43: =J36+J42 | ... T43: =T36+T42 | U43: =SUM(C43:T43)
A44: Stock en fin de mois (coût HT) | C44: ='Hypothèses'!C175*'Scénarios 18 mois'!D48 | D44: ='Hypothèses'!D175*'Scénarios 18 mois'!E48 | E44: ='Hypothèses'!E175*'Scénarios 18 mois'!F48 | F44: ='Hypothèses'!F175*'Scénarios 18 mois'!G48 | G44: ='Hypothèses'!G175*'Scénarios 18 mois'!H48 | H44: ='Hypothèses'!H175*'Scénarios 18 mois'!I48 | I44: ='Hypothèses'!I175*'Scénarios 18 mois'!J48 | J44: ='Hypothèses'!J175*'Scénarios 18 mois'!K48 | ... S44: ='Hypothèses'!S175*'Scénarios 18 mois'!T48 | T44: ='Hypothèses'!T175*'Scénarios 18 mois'!T48
A45: Achats de stock HT (payés à la commande) | C45: ='Scénarios 18 mois'!C48+C44 | D45: ='Scénarios 18 mois'!D48+D44-C44 | E45: ='Scénarios 18 mois'!E48+E44-D44 | F45: ='Scénarios 18 mois'!F48+F44-E44 | G45: ='Scénarios 18 mois'!G48+G44-F44 | H45: ='Scénarios 18 mois'!H48+H44-G44 | I45: ='Scénarios 18 mois'!I48+I44-H44 | J45: ='Scénarios 18 mois'!J48+J44-I44 | K45: ='Scénarios 18 mois'!K48+K44-J44 | ... T45: ='Scénarios 18 mois'!T48+T44-S44 | U45: =SUM(C45:T45)
A46: Achat en import groupé (TVA autoliquidée, 1 = oui) | C46: ='Hypothèses'!D171 | D46: ='Hypothèses'!E171 | E46: ='Hypothèses'!F171 | F46: ='Hypothèses'!G171 | G46: ='Hypothèses'!H171 | H46: ='Hypothèses'!I171 | I46: ='Hypothèses'!J171 | J46: ='Hypothèses'!K171 | ... S46: ='Hypothèses'!T171 | T46: ='Hypothèses'!T171
A47: TVA payée sur achats de micro-stock | C47: =h_TVA*C45*(1-C46) | D47: =h_TVA*D45*(1-D46) | E47: =h_TVA*E45*(1-E46) | F47: =h_TVA*F45*(1-F46) | G47: =h_TVA*G45*(1-G46) | H47: =h_TVA*H45*(1-H46) | I47: =h_TVA*I45*(1-I46) | J47: =h_TVA*J45*(1-J46) | ... T47: =h_TVA*T45*(1-T46) | U47: =SUM(C47:T47)
A48: Étiquettes, emballage, 3PL (TTC) | C48: ='Scénarios 18 mois'!C49*(1+h_TVA) | D48: ='Scénarios 18 mois'!D49*(1+h_TVA) | E48: ='Scénarios 18 mois'!E49*(1+h_TVA) | F48: ='Scénarios 18 mois'!F49*(1+h_TVA) | G48: ='Scénarios 18 mois'!G49*(1+h_TVA) | H48: ='Scénarios 18 mois'!H49*(1+h_TVA) | I48: ='Scénarios 18 mois'!I49*(1+h_TVA) | J48: ='Scénarios 18 mois'!J49*(1+h_TVA) | ... T48: ='Scénarios 18 mois'!T49*(1+h_TVA) | U48: =SUM(C48:T48)
A49: Publicité | C49: ='Scénarios 18 mois'!C55 | D49: ='Scénarios 18 mois'!D55 | E49: ='Scénarios 18 mois'!E55 | F49: ='Scénarios 18 mois'!F55 | G49: ='Scénarios 18 mois'!G55 | H49: ='Scénarios 18 mois'!H55 | I49: ='Scénarios 18 mois'!I55 | J49: ='Scénarios 18 mois'!J55 | ... T49: ='Scénarios 18 mois'!T55 | U49: =SUM(C49:T49)
A50: Échantillons créateurs | C50: ='Scénarios 18 mois'!C56 | D50: ='Scénarios 18 mois'!D56 | E50: ='Scénarios 18 mois'!E56 | F50: ='Scénarios 18 mois'!F56 | G50: ='Scénarios 18 mois'!G56 | H50: ='Scénarios 18 mois'!H56 | I50: ='Scénarios 18 mois'!I56 | J50: ='Scénarios 18 mois'!J56 | ... T50: ='Scénarios 18 mois'!T56 | U50: =SUM(C50:T50)
A51: Frais fixes et ponctuels | C51: ='Scénarios 18 mois'!C57 | D51: ='Scénarios 18 mois'!D57 | E51: ='Scénarios 18 mois'!E57 | F51: ='Scénarios 18 mois'!F57 | G51: ='Scénarios 18 mois'!G57 | H51: ='Scénarios 18 mois'!H57 | I51: ='Scénarios 18 mois'!I57 | J51: ='Scénarios 18 mois'!J57 | ... T51: ='Scénarios 18 mois'!T57 | U51: =SUM(C51:T51)
A52: Remboursements clients et SAV | C52: ='Scénarios 18 mois'!C53 | D52: ='Scénarios 18 mois'!D53 | E52: ='Scénarios 18 mois'!E53 | F52: ='Scénarios 18 mois'!F53 | G52: ='Scénarios 18 mois'!G53 | H52: ='Scénarios 18 mois'!H53 | I52: ='Scénarios 18 mois'!I53 | J52: ='Scénarios 18 mois'!J53 | ... T52: ='Scénarios 18 mois'!T53 | U52: =SUM(C52:T52)
A53: TVA déductible du mois | C53: =C47+h_TVA*'Scénarios 18 mois'!C49 | D53: =D47+h_TVA*'Scénarios 18 mois'!D49 | E53: =E47+h_TVA*'Scénarios 18 mois'!E49 | F53: =F47+h_TVA*'Scénarios 18 mois'!F49 | G53: =G47+h_TVA*'Scénarios 18 mois'!G49 | H53: =H47+h_TVA*'Scénarios 18 mois'!H49 | I53: =I47+h_TVA*'Scénarios 18 mois'!I49 | J53: =J47+h_TVA*'Scénarios 18 mois'!J49 | ... T53: =T47+h_TVA*'Scénarios 18 mois'!T49
A54: TVA nette reversée (mois suivant) | C54: =0 | D54: ='Scénarios 18 mois'!C47-C53 | E54: ='Scénarios 18 mois'!D47-D53 | F54: ='Scénarios 18 mois'!E47-E53 | G54: ='Scénarios 18 mois'!F47-F53 | H54: ='Scénarios 18 mois'!G47-G53 | I54: ='Scénarios 18 mois'!H47-H53 | J54: ='Scénarios 18 mois'!I47-I53 | K54: ='Scénarios 18 mois'!J47-J53 | ... T54: ='Scénarios 18 mois'!S47-S53 | U54: =SUM(C54:T54)
A55: IS payé (solde 2027 dû en mai 2028, hors horizon) | C55: =0 | D55: =0 | E55: =0 | F55: =0 | G55: =0 | H55: =0 | I55: =0 | J55: =0 | ... T55: =0
A56: Total des décaissements | C56: =C45+C47+C48+C49+C50+C51+C52+C54+C55 | D56: =D45+D47+D48+D49+D50+D51+D52+D54+D55 | E56: =E45+E47+E48+E49+E50+E51+E52+E54+E55 | F56: =F45+F47+F48+F49+F50+F51+F52+F54+F55 | G56: =G45+G47+G48+G49+G50+G51+G52+G54+G55 | H56: =H45+H47+H48+H49+H50+H51+H52+H54+H55 | I56: =I45+I47+I48+I49+I50+I51+I52+I54+I55 | J56: =J45+J47+J48+J49+J50+J51+J52+J54+J55 | ... T56: =T45+T47+T48+T49+T50+T51+T52+T54+T55 | U56: =SUM(C56:T56)
A57: Flux de trésorerie du mois | C57: =C43-C56 | D57: =D43-D56 | E57: =E43-E56 | F57: =F43-F56 | G57: =G43-G56 | H57: =H43-H56 | I57: =I43-I56 | J57: =J43-J56 | ... T57: =T43-T56 | U57: =SUM(C57:T57)
A58: Trésorerie en fin de mois (départ : h_TRESO_INITIALE) | C58: =h_TRESO_INITIALE+C57 | D58: =C58+D57 | E58: =D58+E57 | F58: =E58+F57 | G58: =F58+G57 | H58: =G58+H57 | I58: =H58+I57 | J58: =I58+J57 | K58: =J58+K57 | ... T58: =S58+T57
A59: Besoin de trésorerie (creux le plus bas, signe inversé) | C59: =-MIN(0,MIN(C58:T58))
A62: Scénario optimiste
A63: Ligne | C63: oct. 2026 | D63: nov. 2026 | E63: déc. 2026 | F63: janv. 2027 | G63: févr. 2027 | H63: mars 2027 | I63: avr. 2027 | J63: mai 2027 | K63: juin 2027 | L63: juil. 2027 | M63: août 2027 | N63: sept. 2027 | O63: oct. 2027 | P63: nov. 2027 | Q63: déc. 2027 | R63: janv. 2028 | S63: févr. 2028 | T63: mars 2028 | U63: Total
A64: Ventes du site nettes de frais de paiement (dues) | C64: ='Scénarios 18 mois'!C71*(ue_SITE_TTC-ue_SITE_PAY)+'Scénarios 18 mois'!C74*(ue_PUB_TTC-ue_PUB_PAY) | D64: ='Scénarios 18 mois'!D71*(ue_SITE_TTC-ue_SITE_PAY)+'Scénarios 18 mois'!D74*(ue_PUB_TTC-ue_PUB_PAY) | E64: ='Scénarios 18 mois'!E71*(ue_SITE_TTC-ue_SITE_PAY)+'Scénarios 18 mois'!E74*(ue_PUB_TTC-ue_PUB_PAY) | F64: ='Scénarios 18 mois'!F71*(ue_SITE_TTC-ue_SITE_PAY)+'Scénarios 18 mois'!F74*(ue_PUB_TTC-ue_PUB_PAY) | G64: ='Scénarios 18 mois'!G71*(ue_SITE_TTC-ue_SITE_PAY)+'Scénarios 18 mois'!G74*(ue_PUB_TTC-ue_PUB_PAY) | H64: ='Scénarios 18 mois'!H71*(ue_SITE_TTC-ue_SITE_PAY)+'Scénarios 18 mois'!H74*(ue_PUB_TTC-ue_PUB_PAY) | I64: ='Scénarios 18 mois'!I71*(ue_SITE_TTC-ue_SITE_PAY)+'Scénarios 18 mois'!I74*(ue_PUB_TTC-ue_PUB_PAY) | J64: ='Scénarios 18 mois'!J71*(ue_SITE_TTC-ue_SITE_PAY)+'Scénarios 18 mois'!J74*(ue_PUB_TTC-ue_PUB_PAY) | ... T64: ='Scénarios 18 mois'!T71*(ue_SITE_TTC-ue_SITE_PAY)+'Scénarios 18 mois'!T74*(ue_PUB_TTC-ue_PUB_PAY)
A65: Encaissement Stripe / Shopify Payments | C65: =C64*(1-'Hypothèses'!C197/30) | D65: =D64*(1-'Hypothèses'!D197/30)+C64*'Hypothèses'!C197/30 | E65: =E64*(1-'Hypothèses'!E197/30)+D64*'Hypothèses'!D197/30 | F65: =F64*(1-'Hypothèses'!F197/30)+E64*'Hypothèses'!E197/30 | G65: =G64*(1-'Hypothèses'!G197/30)+F64*'Hypothèses'!F197/30 | H65: =H64*(1-'Hypothèses'!H197/30)+G64*'Hypothèses'!G197/30 | I65: =I64*(1-'Hypothèses'!I197/30)+H64*'Hypothèses'!H197/30 | J65: =J64*(1-'Hypothèses'!J197/30)+I64*'Hypothèses'!I197/30 | K65: =K64*(1-'Hypothèses'!K197/30)+J64*'Hypothèses'!J197/30 | ... T65: =T64*(1-'Hypothèses'!T197/30)+S64*'Hypothèses'!S197/30 | U65: =SUM(C65:T65)
A66: Ventes TikTok Shop nettes de commissions (dues) | C66: =('Scénarios 18 mois'!C72+'Scénarios 18 mois'!C73)*ue_TTS_TTC*(1-'Hypothèses'!C191)-'Scénarios 18 mois'!C73*ue_TTS_TTC*h_CREA_COMM | D66: =('Scénarios 18 mois'!D72+'Scénarios 18 mois'!D73)*ue_TTS_TTC*(1-'Hypothèses'!D191)-'Scénarios 18 mois'!D73*ue_TTS_TTC*h_CREA_COMM | E66: =('Scénarios 18 mois'!E72+'Scénarios 18 mois'!E73)*ue_TTS_TTC*(1-'Hypothèses'!E191)-'Scénarios 18 mois'!E73*ue_TTS_TTC*h_CREA_COMM | F66: =('Scénarios 18 mois'!F72+'Scénarios 18 mois'!F73)*ue_TTS_TTC*(1-'Hypothèses'!F191)-'Scénarios 18 mois'!F73*ue_TTS_TTC*h_CREA_COMM | G66: =('Scénarios 18 mois'!G72+'Scénarios 18 mois'!G73)*ue_TTS_TTC*(1-'Hypothèses'!G191)-'Scénarios 18 mois'!G73*ue_TTS_TTC*h_CREA_COMM | H66: =('Scénarios 18 mois'!H72+'Scénarios 18 mois'!H73)*ue_TTS_TTC*(1-'Hypothèses'!H191)-'Scénarios 18 mois'!H73*ue_TTS_TTC*h_CREA_COMM | I66: =('Scénarios 18 mois'!I72+'Scénarios 18 mois'!I73)*ue_TTS_TTC*(1-'Hypothèses'!I191)-'Scénarios 18 mois'!I73*ue_TTS_TTC*h_CREA_COMM | J66: =('Scénarios 18 mois'!J72+'Scénarios 18 mois'!J73)*ue_TTS_TTC*(1-'Hypothèses'!J191)-'Scénarios 18 mois'!J73*ue_TTS_TTC*h_CREA_COMM | ... T66: =('Scénarios 18 mois'!T72+'Scénarios 18 mois'!T73)*ue_TTS_TTC*(1-'Hypothèses'!T191)-'Scénarios 18 mois'!T73*ue_TTS_TTC*h_CREA_COMM
A67: Délai d'encaissement TikTok Shop (jours) | C67: ='Hypothèses'!C198 | D67: ='Hypothèses'!D198 | E67: ='Hypothèses'!E198 | F67: ='Hypothèses'!F198 | G67: ='Hypothèses'!G198 | H67: ='Hypothèses'!H198 | I67: ='Hypothèses'!I198 | J67: ='Hypothèses'!J198 | ... T67: ='Hypothèses'!T198
A68: Part encaissée le mois même | C68: =MAX(0,1-C67/30) | D68: =MAX(0,1-D67/30) | E68: =MAX(0,1-E67/30) | F68: =MAX(0,1-F67/30) | G68: =MAX(0,1-G67/30) | H68: =MAX(0,1-H67/30) | I68: =MAX(0,1-I67/30) | J68: =MAX(0,1-J67/30) | ... T68: =MAX(0,1-T67/30)
A69: Part encaissée le mois suivant | C69: =IF(C67<=30,C67/30,(60-C67)/30) | D69: =IF(D67<=30,D67/30,(60-D67)/30) | E69: =IF(E67<=30,E67/30,(60-E67)/30) | F69: =IF(F67<=30,F67/30,(60-F67)/30) | G69: =IF(G67<=30,G67/30,(60-G67)/30) | H69: =IF(H67<=30,H67/30,(60-H67)/30) | I69: =IF(I67<=30,I67/30,(60-I67)/30) | J69: =IF(J67<=30,J67/30,(60-J67)/30) | ... T69: =IF(T67<=30,T67/30,(60-T67)/30)
A70: Part encaissée à M+2 | C70: =MAX(0,(C67-30)/30) | D70: =MAX(0,(D67-30)/30) | E70: =MAX(0,(E67-30)/30) | F70: =MAX(0,(F67-30)/30) | G70: =MAX(0,(G67-30)/30) | H70: =MAX(0,(H67-30)/30) | I70: =MAX(0,(I67-30)/30) | J70: =MAX(0,(J67-30)/30) | ... T70: =MAX(0,(T67-30)/30)
A71: Encaissement TikTok Shop | C71: =C66*C68 | D71: =D66*D68+C66*C69 | E71: =E66*E68+D66*D69+C66*C70 | F71: =F66*F68+E66*E69+D66*D70 | G71: =G66*G68+F66*F69+E66*E70 | H71: =H66*H68+G66*G69+F66*F70 | I71: =I66*I68+H66*H69+G66*G70 | J71: =J66*J68+I66*I69+H66*H70 | K71: =K66*K68+J66*J69+I66*I70 | L71: =L66*L68+K66*K69+J66*J70 | ... T71: =T66*T68+S66*S69+R66*R70 | U71: =SUM(C71:T71)
A72: Total des encaissements | C72: =C65+C71 | D72: =D65+D71 | E72: =E65+E71 | F72: =F65+F71 | G72: =G65+G71 | H72: =H65+H71 | I72: =I65+I71 | J72: =J65+J71 | ... T72: =T65+T71 | U72: =SUM(C72:T72)
A73: Stock en fin de mois (coût HT) | C73: ='Hypothèses'!C196*'Scénarios 18 mois'!D80 | D73: ='Hypothèses'!D196*'Scénarios 18 mois'!E80 | E73: ='Hypothèses'!E196*'Scénarios 18 mois'!F80 | F73: ='Hypothèses'!F196*'Scénarios 18 mois'!G80 | G73: ='Hypothèses'!G196*'Scénarios 18 mois'!H80 | H73: ='Hypothèses'!H196*'Scénarios 18 mois'!I80 | I73: ='Hypothèses'!I196*'Scénarios 18 mois'!J80 | J73: ='Hypothèses'!J196*'Scénarios 18 mois'!K80 | ... S73: ='Hypothèses'!S196*'Scénarios 18 mois'!T80 | T73: ='Hypothèses'!T196*'Scénarios 18 mois'!T80
A74: Achats de stock HT (payés à la commande) | C74: ='Scénarios 18 mois'!C80+C73 | D74: ='Scénarios 18 mois'!D80+D73-C73 | E74: ='Scénarios 18 mois'!E80+E73-D73 | F74: ='Scénarios 18 mois'!F80+F73-E73 | G74: ='Scénarios 18 mois'!G80+G73-F73 | H74: ='Scénarios 18 mois'!H80+H73-G73 | I74: ='Scénarios 18 mois'!I80+I73-H73 | J74: ='Scénarios 18 mois'!J80+J73-I73 | K74: ='Scénarios 18 mois'!K80+K73-J73 | ... T74: ='Scénarios 18 mois'!T80+T73-S73 | U74: =SUM(C74:T74)
A75: Achat en import groupé (TVA autoliquidée, 1 = oui) | C75: ='Hypothèses'!D192 | D75: ='Hypothèses'!E192 | E75: ='Hypothèses'!F192 | F75: ='Hypothèses'!G192 | G75: ='Hypothèses'!H192 | H75: ='Hypothèses'!I192 | I75: ='Hypothèses'!J192 | J75: ='Hypothèses'!K192 | ... S75: ='Hypothèses'!T192 | T75: ='Hypothèses'!T192
A76: TVA payée sur achats de micro-stock | C76: =h_TVA*C74*(1-C75) | D76: =h_TVA*D74*(1-D75) | E76: =h_TVA*E74*(1-E75) | F76: =h_TVA*F74*(1-F75) | G76: =h_TVA*G74*(1-G75) | H76: =h_TVA*H74*(1-H75) | I76: =h_TVA*I74*(1-I75) | J76: =h_TVA*J74*(1-J75) | ... T76: =h_TVA*T74*(1-T75) | U76: =SUM(C76:T76)
A77: Étiquettes, emballage, 3PL (TTC) | C77: ='Scénarios 18 mois'!C81*(1+h_TVA) | D77: ='Scénarios 18 mois'!D81*(1+h_TVA) | E77: ='Scénarios 18 mois'!E81*(1+h_TVA) | F77: ='Scénarios 18 mois'!F81*(1+h_TVA) | G77: ='Scénarios 18 mois'!G81*(1+h_TVA) | H77: ='Scénarios 18 mois'!H81*(1+h_TVA) | I77: ='Scénarios 18 mois'!I81*(1+h_TVA) | J77: ='Scénarios 18 mois'!J81*(1+h_TVA) | ... T77: ='Scénarios 18 mois'!T81*(1+h_TVA) | U77: =SUM(C77:T77)
A78: Publicité | C78: ='Scénarios 18 mois'!C87 | D78: ='Scénarios 18 mois'!D87 | E78: ='Scénarios 18 mois'!E87 | F78: ='Scénarios 18 mois'!F87 | G78: ='Scénarios 18 mois'!G87 | H78: ='Scénarios 18 mois'!H87 | I78: ='Scénarios 18 mois'!I87 | J78: ='Scénarios 18 mois'!J87 | ... T78: ='Scénarios 18 mois'!T87 | U78: =SUM(C78:T78)
A79: Échantillons créateurs | C79: ='Scénarios 18 mois'!C88 | D79: ='Scénarios 18 mois'!D88 | E79: ='Scénarios 18 mois'!E88 | F79: ='Scénarios 18 mois'!F88 | G79: ='Scénarios 18 mois'!G88 | H79: ='Scénarios 18 mois'!H88 | I79: ='Scénarios 18 mois'!I88 | J79: ='Scénarios 18 mois'!J88 | ... T79: ='Scénarios 18 mois'!T88 | U79: =SUM(C79:T79)
A80: Frais fixes et ponctuels | C80: ='Scénarios 18 mois'!C89 | D80: ='Scénarios 18 mois'!D89 | E80: ='Scénarios 18 mois'!E89 | F80: ='Scénarios 18 mois'!F89 | G80: ='Scénarios 18 mois'!G89 | H80: ='Scénarios 18 mois'!H89 | I80: ='Scénarios 18 mois'!I89 | J80: ='Scénarios 18 mois'!J89 | ... T80: ='Scénarios 18 mois'!T89 | U80: =SUM(C80:T80)
A81: Remboursements clients et SAV | C81: ='Scénarios 18 mois'!C85 | D81: ='Scénarios 18 mois'!D85 | E81: ='Scénarios 18 mois'!E85 | F81: ='Scénarios 18 mois'!F85 | G81: ='Scénarios 18 mois'!G85 | H81: ='Scénarios 18 mois'!H85 | I81: ='Scénarios 18 mois'!I85 | J81: ='Scénarios 18 mois'!J85 | ... T81: ='Scénarios 18 mois'!T85 | U81: =SUM(C81:T81)
A82: TVA déductible du mois | C82: =C76+h_TVA*'Scénarios 18 mois'!C81 | D82: =D76+h_TVA*'Scénarios 18 mois'!D81 | E82: =E76+h_TVA*'Scénarios 18 mois'!E81 | F82: =F76+h_TVA*'Scénarios 18 mois'!F81 | G82: =G76+h_TVA*'Scénarios 18 mois'!G81 | H82: =H76+h_TVA*'Scénarios 18 mois'!H81 | I82: =I76+h_TVA*'Scénarios 18 mois'!I81 | J82: =J76+h_TVA*'Scénarios 18 mois'!J81 | ... T82: =T76+h_TVA*'Scénarios 18 mois'!T81
A83: TVA nette reversée (mois suivant) | C83: =0 | D83: ='Scénarios 18 mois'!C79-C82 | E83: ='Scénarios 18 mois'!D79-D82 | F83: ='Scénarios 18 mois'!E79-E82 | G83: ='Scénarios 18 mois'!F79-F82 | H83: ='Scénarios 18 mois'!G79-G82 | I83: ='Scénarios 18 mois'!H79-H82 | J83: ='Scénarios 18 mois'!I79-I82 | K83: ='Scénarios 18 mois'!J79-J82 | ... T83: ='Scénarios 18 mois'!S79-S82 | U83: =SUM(C83:T83)
A84: IS payé (solde 2027 dû en mai 2028, hors horizon) | C84: =0 | D84: =0 | E84: =0 | F84: =0 | G84: =0 | H84: =0 | I84: =0 | J84: =0 | ... T84: =0
A85: Total des décaissements | C85: =C74+C76+C77+C78+C79+C80+C81+C83+C84 | D85: =D74+D76+D77+D78+D79+D80+D81+D83+D84 | E85: =E74+E76+E77+E78+E79+E80+E81+E83+E84 | F85: =F74+F76+F77+F78+F79+F80+F81+F83+F84 | G85: =G74+G76+G77+G78+G79+G80+G81+G83+G84 | H85: =H74+H76+H77+H78+H79+H80+H81+H83+H84 | I85: =I74+I76+I77+I78+I79+I80+I81+I83+I84 | J85: =J74+J76+J77+J78+J79+J80+J81+J83+J84 | ... T85: =T74+T76+T77+T78+T79+T80+T81+T83+T84 | U85: =SUM(C85:T85)
A86: Flux de trésorerie du mois | C86: =C72-C85 | D86: =D72-D85 | E86: =E72-E85 | F86: =F72-F85 | G86: =G72-G85 | H86: =H72-H85 | I86: =I72-I85 | J86: =J72-J85 | ... T86: =T72-T85 | U86: =SUM(C86:T86)
A87: Trésorerie en fin de mois (départ : h_TRESO_INITIALE) | C87: =h_TRESO_INITIALE+C86 | D87: =C87+D86 | E87: =D87+E86 | F87: =E87+F86 | G87: =F87+G86 | H87: =G87+H86 | I87: =H87+I86 | J87: =I87+J86 | K87: =J87+K86 | ... T87: =S87+T86
A88: Besoin de trésorerie (creux le plus bas, signe inversé) | C88: =-MIN(0,MIN(C87:T87))

Sheet Paliers
A1: Paliers de bénéfice net mensuel : ce qu'il faut réunir
A2: Paliers 1 et 2 : calcul ascendant à partir des unit economics. Paliers 3 et 4 : calcul descendant à partir d'une marge nette type. Bénéfice net = avant IS et rémunération du dirigeant.
A4: Indicateur | B4: Palier 1 — 1 k€ | C4: Palier 2 — 10 k€ | D4: Palier 3 — 100 k€ | E4: Palier 4 — 1 M€
A5: Bénéfice net visé (€ / mois) | B5: =1000 | C5: =10000 | D5: =100000 | E5: =1000000
A6: Marge par commande après publicité (paliers 1-2) ; bénéfice net par commande (paliers 3-4) (€) | B6: =ue_MIX_MARGE_MS | C6: =(1-h_P2_PART_PUB)*ue_MIX_MARGE_IMP+h_P2_PART_PUB*(ue_PUB_MARGE_AVANT_PUB_IMP-C8) | D6: =D5/D9 | E6: =E5/E9
A7: Frais fixes, personnel et échantillons (€ / mois) | B7: =(h_COMPTABLE+h_BANQUE+h_OUTILS+h_RC+h_DOMICILIATION+h_LEKO/12+h_MEDIATEUR/36+h_DOMAINE/12)+h_P1_ECH | C7: =h_P2_FIXES_AUTRES+h_P2_PERSONNEL+h_P2_ECH
A8: CPA cible (€) | C8: =ue_PUB_MARGE_AVANT_PUB_IMP/h_MER_MARGE
A9: Commandes par mois | B9: =(B5+B7)/B6 | C9: =(C5+C7)/C6 | D9: =D12/h_P3_PANIER | E9: =E12/h_P4_PANIER
A10: Commandes par jour | B10: =B9/30 | C10: =C9/30 | D10: =D9/30 | E10: =E9/30
A11: CA HT nécessaire (€ / mois) | B11: =B9*ue_MIX_HT | C11: =C9*((1-h_P2_PART_PUB)*ue_MIX_HT+h_P2_PART_PUB*ue_PUB_HT) | D11: =D5/h_P3_MARGE | E11: =E5/h_P4_MARGE
A12: CA TTC (€ / mois) | B12: =B9*ue_MIX_TTC | C12: =C9*((1-h_P2_PART_PUB)*ue_MIX_TTC+h_P2_PART_PUB*ue_PUB_TTC) | D12: =D11*(1+h_TVA) | E12: =E11*(1+h_TVA)
A13: Budget publicitaire (€ / mois) | B13: =0 | C13: =C9*h_P2_PART_PUB*C8 | D13: =h_P3_PUB*D11 | E13: =h_P4_PUB*E11
A14: Stock immobilisé (€) | B14: =h_COUV_MICRO*B9*ue_MIX_PROD_MS | C14: =h_COUV_IMPORT*C9*((1-h_P2_PART_PUB)*ue_MIX_PROD_IMP+h_P2_PART_PUB*ue_PUB_PROD_IMP) | D14: =h_COUV_IMPORT*h_P3_COGS*D11 | E14: =h_COUV_IMPORT*h_P4_COGS*E11
A15: Créances clients et plateformes (€) | B15: =B9*(1-h_MIX_SITE)*(ue_TTS_TTC*(1-h_TTS_COMM)-h_MIX_AFF/(1-h_MIX_SITE)*ue_TTS_TTC*h_CREA_COMM)*(h_TTS_LIVRAISON+h_TTS_STANDARD+h_TTS_VIREMENT)/30+B9*h_MIX_SITE*(ue_SITE_TTC-ue_SITE_PAY)*h_STRIPE_DELAI/30 | C15: =C9*(1-h_P2_PART_PUB)*(1-h_MIX_SITE)*(ue_TTS_TTC*(1-h_TTS_COMM)-h_MIX_AFF/(1-h_MIX_SITE)*ue_TTS_TTC*h_CREA_COMM)*(h_TTS_LIVRAISON+h_TTS_STANDARD+h_TTS_VIREMENT)/30+C9*((1-h_P2_PART_PUB)*h_MIX_SITE*(ue_SITE_TTC-ue_SITE_PAY)+h_P2_PART_PUB*(ue_PUB_TTC-ue_PUB_PAY))*h_STRIPE_DELAI/30 | D15: =h_PART_MARKETPLACE*D12*h_CREANCES_JOURS/30 | E15: =h_PART_MARKETPLACE*E12*h_CREANCES_JOURS/30
A16: Dettes TVA et fournisseurs (€) | B16: =B9*(ue_MIX_TTC-ue_MIX_HT)-h_TVA*B9*(ue_MIX_PROD_MS+ue_MIX_LOG_MS) | C16: =(C12-C11)-h_TVA*C9*((1-h_P2_PART_PUB)*ue_MIX_LOG_IMP+h_P2_PART_PUB*ue_PUB_LOG_IMP) | D16: =h_DETTES_FOURN_PART*h_P3_COGS*D11+h_TVA*D11*h_TVA_NETTE_RATIO | E16: =h_DETTES_FOURN_PART*h_P4_COGS*E11+h_TVA*E11*h_TVA_NETTE_RATIO
A17: Besoin en fonds de roulement (€) | B17: =B14+B15-B16 | C17: =C14+C15-C16 | D17: =D14+D15-D16 | E17: =E14+E15-E16
A18: Effectif | B18: Fondateur seul, 20-25 h par semaine | C18: 2 à 3 personnes : fondateur, assistant SAV à mi-temps, media buyer indépendant ; 3PL | D18: 8 à 15 personnes ; 20-40 références | E18: 50 à 100 personnes ; plusieurs gammes
A19: Probabilité (stratégie 04) | B19: 20-30 % à 6 mois ; 30-40 % à 12 mois | C19: 5-10 % à 24 mois | D19: 0,5-1,5 % à 4 ans | E19: ≤ 0,1 % à 8 ans
A20: Probabilité (lecture finance) | B20: 10-20 % à 12 mois : P(porte 1) 35-50 % × P(trajectoire réaliste ou mieux, porte 1 franchie) 30-40 % | C20: 3-5 % à 24 mois : P(porte 1) 35-50 % × P(trajectoire optimiste, porte 1 franchie) 8-10 % ; le CPA cible ≤ 16,70 € est le verrou | D20: 0,5-1 % à 4 ans | E20: ≤ 0,1 % à 8 ans
A21: Délai estimé | B21: 3 à 9 mois après les premières ventes (été 2027 dans le scénario réaliste) | C21: 9 à 18 mois après le palier 1 | D21: 18 à 36 mois après le palier 2 | E21: 3 à 5 ans après le palier 3
A22: Conditions de passage | B22: Porte 1 et porte 2 franchies ; ≈ 15 affiliés actifs ; 3 vidéos par jour ; marge moyenne ≥ 7,55 € | C22: Import groupé, 3PL, marque déposée, publicité rentable avec MER ≥ 1,2 × rentabilité, sortie de la franchise de TVA et de la micro-entreprise | D22: France < 50 % du CA ; Allemagne, Italie, Espagne ; Amazon UE ; financement de stock bancaire ou BPI | E22: 10 pays et plus, distribution physique, levée de fonds ou rachat de marques ; place l'entreprise dans le 1 % des sites qui font 78 % du CA

Sheet Sensibilité
A1: Sensibilité du bénéfice mensuel à ±20 % de chaque variable (tornado)
A2: Modèle réduit : bénéfice = Σ commandes × marge par canal − budget publicitaire − frais fixes − échantillons. Chaque ligne multiplie une seule variable par 0,8 ou 1,2. Prix ±20 % : les commandes restent constantes (effet sur la demande non modélisé). CPA ±20 % : budget constant, donc moins de commandes payantes.
A4: Palier 1 — scénario réaliste, sept. 2027
A5: Canal | B5: Commandes | C5: CA HT | D5: Produit | E5: Livraison | F5: Paiement % | G5: Paiement fixe | H5: Comm. TikTok | I5: Comm. créateur | J5: Provision
A6: Site organique | B6: ='Scénarios 18 mois'!N39 | C6: =ue_SITE_HT | D6: =ue_SITE_PROD_MS | E6: =ue_SITE_LOG_MS | F6: =h_STRIPE_PCT*ue_SITE_TTC | G6: =h_STRIPE_FIXE | H6: =0 | I6: =0 | J6: =h_PROV_RETOURS*C6
A7: TikTok Shop contenu propre | B7: ='Scénarios 18 mois'!N40 | C7: =ue_TTS_HT | D7: =ue_TTS_PROD_MS | E7: =ue_TTS_LOG_MS | F7: =0 | G7: =0 | H7: ='Hypothèses'!N170*ue_TTS_TTC | I7: =0 | J7: =h_PROV_RETOURS*C7
A8: TikTok Shop affiliés | B8: ='Scénarios 18 mois'!N41 | C8: =ue_TTS_HT | D8: =ue_TTS_PROD_MS | E8: =ue_TTS_LOG_MS | F8: =0 | G8: =0 | H8: ='Hypothèses'!N170*ue_TTS_TTC | I8: =h_CREA_COMM*ue_TTS_TTC | J8: =h_PROV_RETOURS*C8
A9: Site, publicité | B9: =0 | C9: =ue_PUB_HT | D9: =ue_PUB_PROD_MS | E9: =ue_PUB_LOG_MS | F9: =h_STRIPE_PCT*ue_PUB_TTC | G9: =h_STRIPE_FIXE | H9: =0 | I9: =0 | J9: =h_PROV_RETOURS*C9
A10: Frais fixes (€ / mois) | B10: ='Scénarios 18 mois'!N57
A11: Échantillons créateurs (€ / mois) | B11: ='Scénarios 18 mois'!N56
A12: CPA (€) | B12: =0
A13: Budget publicitaire (€ / mois) | B13: =B12*B9
A15: Variable | B15: Variation | C15: kVol | D15: kPrix | E15: kProd | F15: kLog | G15: kPay | H15: kTTS | I15: kCrea | J15: kRet | K15: kAff | L15: kFix | M15: kEch | N15: kCPA | O15: kPubVol | P15: Bénéfice mensuel | Q15: Écart vs base
A16: Base | B16: — | C16: 1 | D16: 1 | E16: 1 | F16: 1 | G16: 1 | H16: 1 | I16: 1 | J16: 1 | K16: 1 | L16: 1 | M16: 1 | N16: 1 | O16: 1 | P16: =B6*C16*(D16*C6-E16*D6-F16*E6-G16*(F6*D16+G6)-H16*H6*D16-I16*I6*D16-J16*J6*D16)+(B7+B8*(1-K16))*C16*(D16*C7-E16*D7-F16*E7-G16*(F7*D16+G7)-H16*H7*D16-I16*I7*D16-J16*J7*D16)+B8*C16*K16*(D16*C8-E16*D8-F16*E8-G16*(F8*D16+G8)-H16*H8*D16-I16*I8*D16-J16*J8*D16)+IF($B$12>0,$B$13*O16/($B$12*N16),0)*(D16*C9-E16*D9-F16*E9-G16*(F9*D16+G9)-H16*H9*D16-I16*I9*D16-J16*J9*D16)-$B$13*O16-L16*$B$10-M16*$B$11
A17: Volume de commandes organiques | B17: −20 % | C17: 0.8 | D17: 1 | E17: 1 | F17: 1 | G17: 1 | H17: 1 | I17: 1 | J17: 1 | K17: 1 | L17: 1 | M17: 1 | N17: 1 | O17: 1 | P17: =B6*C17*(D17*C6-E17*D6-F17*E6-G17*(F6*D17+G6)-H17*H6*D17-I17*I6*D17-J17*J6*D17)+(B7+B8*(1-K17))*C17*(D17*C7-E17*D7-F17*E7-G17*(F7*D17+G7)-H17*H7*D17-I17*I7*D17-J17*J7*D17)+B8*C17*K17*(D17*C8-E17*D8-F17*E8-G17*(F8*D17+G8)-H17*H8*D17-I17*I8*D17-J17*J8*D17)+IF($B$12>0,$B$13*O17/($B$12*N17),0)*(D17*C9-E17*D9-F17*E9-G17*(F9*D17+G9)-H17*H9*D17-I17*I9*D17-J17*J9*D17)-$B$13*O17-L17*$B$10-M17*$B$11 | Q17: =P17-P$16
A18: Volume de commandes organiques | B18: +20 % | C18: 1.2 | D18: 1 | E18: 1 | F18: 1 | G18: 1 | H18: 1 | I18: 1 | J18: 1 | K18: 1 | L18: 1 | M18: 1 | N18: 1 | O18: 1 | P18: =B6*C18*(D18*C6-E18*D6-F18*E6-G18*(F6*D18+G6)-H18*H6*D18-I18*I6*D18-J18*J6*D18)+(B7+B8*(1-K18))*C18*(D18*C7-E18*D7-F18*E7-G18*(F7*D18+G7)-H18*H7*D18-I18*I7*D18-J18*J7*D18)+B8*C18*K18*(D18*C8-E18*D8-F18*E8-G18*(F8*D18+G8)-H18*H8*D18-I18*I8*D18-J18*J8*D18)+IF($B$12>0,$B$13*O18/($B$12*N18),0)*(D18*C9-E18*D9-F18*E9-G18*(F9*D18+G9)-H18*H9*D18-I18*I9*D18-J18*J9*D18)-$B$13*O18-L18*$B$10-M18*$B$11 | Q18: =P18-P$16
A19: Prix de vente (tous produits) | B19: −20 % | C19: 1 | D19: 0.8 | E19: 1 | F19: 1 | G19: 1 | H19: 1 | I19: 1 | J19: 1 | K19: 1 | L19: 1 | M19: 1 | N19: 1 | O19: 1 | P19: =B6*C19*(D19*C6-E19*D6-F19*E6-G19*(F6*D19+G6)-H19*H6*D19-I19*I6*D19-J19*J6*D19)+(B7+B8*(1-K19))*C19*(D19*C7-E19*D7-F19*E7-G19*(F7*D19+G7)-H19*H7*D19-I19*I7*D19-J19*J7*D19)+B8*C19*K19*(D19*C8-E19*D8-F19*E8-G19*(F8*D19+G8)-H19*H8*D19-I19*I8*D19-J19*J8*D19)+IF($B$12>0,$B$13*O19/($B$12*N19),0)*(D19*C9-E19*D9-F19*E9-G19*(F9*D19+G9)-H19*H9*D19-I19*I9*D19-J19*J9*D19)-$B$13*O19-L19*$B$10-M19*$B$11 | Q19: =P19-P$16
A20: Prix de vente (tous produits) | B20: +20 % | C20: 1 | D20: 1.2 | E20: 1 | F20: 1 | G20: 1 | H20: 1 | I20: 1 | J20: 1 | K20: 1 | L20: 1 | M20: 1 | N20: 1 | O20: 1 | P20: =B6*C20*(D20*C6-E20*D6-F20*E6-G20*(F6*D20+G6)-H20*H6*D20-I20*I6*D20-J20*J6*D20)+(B7+B8*(1-K20))*C20*(D20*C7-E20*D7-F20*E7-G20*(F7*D20+G7)-H20*H7*D20-I20*I7*D20-J20*J7*D20)+B8*C20*K20*(D20*C8-E20*D8-F20*E8-G20*(F8*D20+G8)-H20*H8*D20-I20*I8*D20-J20*J8*D20)+IF($B$12>0,$B$13*O20/($B$12*N20),0)*(D20*C9-E20*D9-F20*E9-G20*(F9*D20+G9)-H20*H9*D20-I20*I9*D20-J20*J9*D20)-$B$13*O20-L20*$B$10-M20*$B$11 | Q20: =P20-P$16
A21: Coût produit et droits | B21: −20 % | C21: 1 | D21: 1 | E21: 0.8 | F21: 1 | G21: 1 | H21: 1 | I21: 1 | J21: 1 | K21: 1 | L21: 1 | M21: 1 | N21: 1 | O21: 1 | P21: =B6*C21*(D21*C6-E21*D6-F21*E6-G21*(F6*D21+G6)-H21*H6*D21-I21*I6*D21-J21*J6*D21)+(B7+B8*(1-K21))*C21*(D21*C7-E21*D7-F21*E7-G21*(F7*D21+G7)-H21*H7*D21-I21*I7*D21-J21*J7*D21)+B8*C21*K21*(D21*C8-E21*D8-F21*E8-G21*(F8*D21+G8)-H21*H8*D21-I21*I8*D21-J21*J8*D21)+IF($B$12>0,$B$13*O21/($B$12*N21),0)*(D21*C9-E21*D9-F21*E9-G21*(F9*D21+G9)-H21*H9*D21-I21*I9*D21-J21*J9*D21)-$B$13*O21-L21*$B$10-M21*$B$11 | Q21: =P21-P$16
A22: Coût produit et droits | B22: +20 % | C22: 1 | D22: 1 | E22: 1.2 | F22: 1 | G22: 1 | H22: 1 | I22: 1 | J22: 1 | K22: 1 | L22: 1 | M22: 1 | N22: 1 | O22: 1 | P22: =B6*C22*(D22*C6-E22*D6-F22*E6-G22*(F6*D22+G6)-H22*H6*D22-I22*I6*D22-J22*J6*D22)+(B7+B8*(1-K22))*C22*(D22*C7-E22*D7-F22*E7-G22*(F7*D22+G7)-H22*H7*D22-I22*I7*D22-J22*J7*D22)+B8*C22*K22*(D22*C8-E22*D8-F22*E8-G22*(F8*D22+G8)-H22*H8*D22-I22*I8*D22-J22*J8*D22)+IF($B$12>0,$B$13*O22/($B$12*N22),0)*(D22*C9-E22*D9-F22*E9-G22*(F9*D22+G9)-H22*H9*D22-I22*I9*D22-J22*J9*D22)-$B$13*O22-L22*$B$10-M22*$B$11 | Q22: =P22-P$16
A23: Livraison et emballage | B23: −20 % | C23: 1 | D23: 1 | E23: 1 | F23: 0.8 | G23: 1 | H23: 1 | I23: 1 | J23: 1 | K23: 1 | L23: 1 | M23: 1 | N23: 1 | O23: 1 | P23: =B6*C23*(D23*C6-E23*D6-F23*E6-G23*(F6*D23+G6)-H23*H6*D23-I23*I6*D23-J23*J6*D23)+(B7+B8*(1-K23))*C23*(D23*C7-E23*D7-F23*E7-G23*(F7*D23+G7)-H23*H7*D23-I23*I7*D23-J23*J7*D23)+B8*C23*K23*(D23*C8-E23*D8-F23*E8-G23*(F8*D23+G8)-H23*H8*D23-I23*I8*D23-J23*J8*D23)+IF($B$12>0,$B$13*O23/($B$12*N23),0)*(D23*C9-E23*D9-F23*E9-G23*(F9*D23+G9)-H23*H9*D23-I23*I9*D23-J23*J9*D23)-$B$13*O23-L23*$B$10-M23*$B$11 | Q23: =P23-P$16
A24: Livraison et emballage | B24: +20 % | C24: 1 | D24: 1 | E24: 1 | F24: 1.2 | G24: 1 | H24: 1 | I24: 1 | J24: 1 | K24: 1 | L24: 1 | M24: 1 | N24: 1 | O24: 1 | P24: =B6*C24*(D24*C6-E24*D6-F24*E6-G24*(F6*D24+G6)-H24*H6*D24-I24*I6*D24-J24*J6*D24)+(B7+B8*(1-K24))*C24*(D24*C7-E24*D7-F24*E7-G24*(F7*D24+G7)-H24*H7*D24-I24*I7*D24-J24*J7*D24)+B8*C24*K24*(D24*C8-E24*D8-F24*E8-G24*(F8*D24+G8)-H24*H8*D24-I24*I8*D24-J24*J8*D24)+IF($B$12>0,$B$13*O24/($B$12*N24),0)*(D24*C9-E24*D9-F24*E9-G24*(F9*D24+G9)-H24*H9*D24-I24*I9*D24-J24*J9*D24)-$B$13*O24-L24*$B$10-M24*$B$11 | Q24: =P24-P$16
A25: Frais de paiement | B25: −20 % | C25: 1 | D25: 1 | E25: 1 | F25: 1 | G25: 0.8 | H25: 1 | I25: 1 | J25: 1 | K25: 1 | L25: 1 | M25: 1 | N25: 1 | O25: 1 | P25: =B6*C25*(D25*C6-E25*D6-F25*E6-G25*(F6*D25+G6)-H25*H6*D25-I25*I6*D25-J25*J6*D25)+(B7+B8*(1-K25))*C25*(D25*C7-E25*D7-F25*E7-G25*(F7*D25+G7)-H25*H7*D25-I25*I7*D25-J25*J7*D25)+B8*C25*K25*(D25*C8-E25*D8-F25*E8-G25*(F8*D25+G8)-H25*H8*D25-I25*I8*D25-J25*J8*D25)+IF($B$12>0,$B$13*O25/($B$12*N25),0)*(D25*C9-E25*D9-F25*E9-G25*(F9*D25+G9)-H25*H9*D25-I25*I9*D25-J25*J9*D25)-$B$13*O25-L25*$B$10-M25*$B$11 | Q25: =P25-P$16
A26: Frais de paiement | B26: +20 % | C26: 1 | D26: 1 | E26: 1 | F26: 1 | G26: 1.2 | H26: 1 | I26: 1 | J26: 1 | K26: 1 | L26: 1 | M26: 1 | N26: 1 | O26: 1 | P26: =B6*C26*(D26*C6-E26*D6-F26*E6-G26*(F6*D26+G6)-H26*H6*D26-I26*I6*D26-J26*J6*D26)+(B7+B8*(1-K26))*C26*(D26*C7-E26*D7-F26*E7-G26*(F7*D26+G7)-H26*H7*D26-I26*I7*D26-J26*J7*D26)+B8*C26*K26*(D26*C8-E26*D8-F26*E8-G26*(F8*D26+G8)-H26*H8*D26-I26*I8*D26-J26*J8*D26)+IF($B$12>0,$B$13*O26/($B$12*N26),0)*(D26*C9-E26*D9-F26*E9-G26*(F9*D26+G9)-H26*H9*D26-I26*I9*D26-J26*J9*D26)-$B$13*O26-L26*$B$10-M26*$B$11 | Q26: =P26-P$16
A27: Commission TikTok Shop | B27: −20 % | C27: 1 | D27: 1 | E27: 1 | F27: 1 | G27: 1 | H27: 0.8 | I27: 1 | J27: 1 | K27: 1 | L27: 1 | M27: 1 | N27: 1 | O27: 1 | P27: =B6*C27*(D27*C6-E27*D6-F27*E6-G27*(F6*D27+G6)-H27*H6*D27-I27*I6*D27-J27*J6*D27)+(B7+B8*(1-K27))*C27*(D27*C7-E27*D7-F27*E7-G27*(F7*D27+G7)-H27*H7*D27-I27*I7*D27-J27*J7*D27)+B8*C27*K27*(D27*C8-E27*D8-F27*E8-G27*(F8*D27+G8)-H27*H8*D27-I27*I8*D27-J27*J8*D27)+IF($B$12>0,$B$13*O27/($B$12*N27),0)*(D27*C9-E27*D9-F27*E9-G27*(F9*D27+G9)-H27*H9*D27-I27*I9*D27-J27*J9*D27)-$B$13*O27-L27*$B$10-M27*$B$11 | Q27: =P27-P$16
A28: Commission TikTok Shop | B28: +20 % | C28: 1 | D28: 1 | E28: 1 | F28: 1 | G28: 1 | H28: 1.2 | I28: 1 | J28: 1 | K28: 1 | L28: 1 | M28: 1 | N28: 1 | O28: 1 | P28: =B6*C28*(D28*C6-E28*D6-F28*E6-G28*(F6*D28+G6)-H28*H6*D28-I28*I6*D28-J28*J6*D28)+(B7+B8*(1-K28))*C28*(D28*C7-E28*D7-F28*E7-G28*(F7*D28+G7)-H28*H7*D28-I28*I7*D28-J28*J7*D28)+B8*C28*K28*(D28*C8-E28*D8-F28*E8-G28*(F8*D28+G8)-H28*H8*D28-I28*I8*D28-J28*J8*D28)+IF($B$12>0,$B$13*O28/($B$12*N28),0)*(D28*C9-E28*D9-F28*E9-G28*(F9*D28+G9)-H28*H9*D28-I28*I9*D28-J28*J9*D28)-$B$13*O28-L28*$B$10-M28*$B$11 | Q28: =P28-P$16
A29: Commission des créateurs | B29: −20 % | C29: 1 | D29: 1 | E29: 1 | F29: 1 | G29: 1 | H29: 1 | I29: 0.8 | J29: 1 | K29: 1 | L29: 1 | M29: 1 | N29: 1 | O29: 1 | P29: =B6*C29*(D29*C6-E29*D6-F29*E6-G29*(F6*D29+G6)-H29*H6*D29-I29*I6*D29-J29*J6*D29)+(B7+B8*(1-K29))*C29*(D29*C7-E29*D7-F29*E7-G29*(F7*D29+G7)-H29*H7*D29-I29*I7*D29-J29*J7*D29)+B8*C29*K29*(D29*C8-E29*D8-F29*E8-G29*(F8*D29+G8)-H29*H8*D29-I29*I8*D29-J29*J8*D29)+IF($B$12>0,$B$13*O29/($B$12*N29),0)*(D29*C9-E29*D9-F29*E9-G29*(F9*D29+G9)-H29*H9*D29-I29*I9*D29-J29*J9*D29)-$B$13*O29-L29*$B$10-M29*$B$11 | Q29: =P29-P$16
A30: Commission des créateurs | B30: +20 % | C30: 1 | D30: 1 | E30: 1 | F30: 1 | G30: 1 | H30: 1 | I30: 1.2 | J30: 1 | K30: 1 | L30: 1 | M30: 1 | N30: 1 | O30: 1 | P30: =B6*C30*(D30*C6-E30*D6-F30*E6-G30*(F6*D30+G6)-H30*H6*D30-I30*I6*D30-J30*J6*D30)+(B7+B8*(1-K30))*C30*(D30*C7-E30*D7-F30*E7-G30*(F7*D30+G7)-H30*H7*D30-I30*I7*D30-J30*J7*D30)+B8*C30*K30*(D30*C8-E30*D8-F30*E8-G30*(F8*D30+G8)-H30*H8*D30-I30*I8*D30-J30*J8*D30)+IF($B$12>0,$B$13*O30/($B$12*N30),0)*(D30*C9-E30*D9-F30*E9-G30*(F9*D30+G9)-H30*H9*D30-I30*I9*D30-J30*J9*D30)-$B$13*O30-L30*$B$10-M30*$B$11 | Q30: =P30-P$16
A31: Retours, SAV et litiges | B31: −20 % | C31: 1 | D31: 1 | E31: 1 | F31: 1 | G31: 1 | H31: 1 | I31: 1 | J31: 0.8 | K31: 1 | L31: 1 | M31: 1 | N31: 1 | O31: 1 | P31: =B6*C31*(D31*C6-E31*D6-F31*E6-G31*(F6*D31+G6)-H31*H6*D31-I31*I6*D31-J31*J6*D31)+(B7+B8*(1-K31))*C31*(D31*C7-E31*D7-F31*E7-G31*(F7*D31+G7)-H31*H7*D31-I31*I7*D31-J31*J7*D31)+B8*C31*K31*(D31*C8-E31*D8-F31*E8-G31*(F8*D31+G8)-H31*H8*D31-I31*I8*D31-J31*J8*D31)+IF($B$12>0,$B$13*O31/($B$12*N31),0)*(D31*C9-E31*D9-F31*E9-G31*(F9*D31+G9)-H31*H9*D31-I31*I9*D31-J31*J9*D31)-$B$13*O31-L31*$B$10-M31*$B$11 | Q31: =P31-P$16
A32: Retours, SAV et litiges | B32: +20 % | C32: 1 | D32: 1 | E32: 1 | F32: 1 | G32: 1 | H32: 1 | I32: 1 | J32: 1.2 | K32: 1 | L32: 1 | M32: 1 | N32: 1 | O32: 1 | P32: =B6*C32*(D32*C6-E32*D6-F32*E6-G32*(F6*D32+G6)-H32*H6*D32-I32*I6*D32-J32*J6*D32)+(B7+B8*(1-K32))*C32*(D32*C7-E32*D7-F32*E7-G32*(F7*D32+G7)-H32*H7*D32-I32*I7*D32-J32*J7*D32)+B8*C32*K32*(D32*C8-E32*D8-F32*E8-G32*(F8*D32+G8)-H32*H8*D32-I32*I8*D32-J32*J8*D32)+IF($B$12>0,$B$13*O32/($B$12*N32),0)*(D32*C9-E32*D9-F32*E9-G32*(F9*D32+G9)-H32*H9*D32-I32*I9*D32-J32*J9*D32)-$B$13*O32-L32*$B$10-M32*$B$11 | Q32: =P32-P$16
A33: Part des ventes par affiliés | B33: −20 % | C33: 1 | D33: 1 | E33: 1 | F33: 1 | G33: 1 | H33: 1 | I33: 1 | J33: 1 | K33: 0.8 | L33: 1 | M33: 1 | N33: 1 | O33: 1 | P33: =B6*C33*(D33*C6-E33*D6-F33*E6-G33*(F6*D33+G6)-H33*H6*D33-I33*I6*D33-J33*J6*D33)+(B7+B8*(1-K33))*C33*(D33*C7-E33*D7-F33*E7-G33*(F7*D33+G7)-H33*H7*D33-I33*I7*D33-J33*J7*D33)+B8*C33*K33*(D33*C8-E33*D8-F33*E8-G33*(F8*D33+G8)-H33*H8*D33-I33*I8*D33-J33*J8*D33)+IF($B$12>0,$B$13*O33/($B$12*N33),0)*(D33*C9-E33*D9-F33*E9-G33*(F9*D33+G9)-H33*H9*D33-I33*I9*D33-J33*J9*D33)-$B$13*O33-L33*$B$10-M33*$B$11 | Q33: =P33-P$16
A34: Part des ventes par affiliés | B34: +20 % | C34: 1 | D34: 1 | E34: 1 | F34: 1 | G34: 1 | H34: 1 | I34: 1 | J34: 1 | K34: 1.2 | L34: 1 | M34: 1 | N34: 1 | O34: 1 | P34: =B6*C34*(D34*C6-E34*D6-F34*E6-G34*(F6*D34+G6)-H34*H6*D34-I34*I6*D34-J34*J6*D34)+(B7+B8*(1-K34))*C34*(D34*C7-E34*D7-F34*E7-G34*(F7*D34+G7)-H34*H7*D34-I34*I7*D34-J34*J7*D34)+B8*C34*K34*(D34*C8-E34*D8-F34*E8-G34*(F8*D34+G8)-H34*H8*D34-I34*I8*D34-J34*J8*D34)+IF($B$12>0,$B$13*O34/($B$12*N34),0)*(D34*C9-E34*D9-F34*E9-G34*(F9*D34+G9)-H34*H9*D34-I34*I9*D34-J34*J9*D34)-$B$13*O34-L34*$B$10-M34*$B$11 | Q34: =P34-P$16
A35: Frais fixes | B35: −20 % | C35: 1 | D35: 1 | E35: 1 | F35: 1 | G35: 1 | H35: 1 | I35: 1 | J35: 1 | K35: 1 | L35: 0.8 | M35: 1 | N35: 1 | O35: 1 | P35: =B6*C35*(D35*C6-E35*D6-F35*E6-G35*(F6*D35+G6)-H35*H6*D35-I35*I6*D35-J35*J6*D35)+(B7+B8*(1-K35))*C35*(D35*C7-E35*D7-F35*E7-G35*(F7*D35+G7)-H35*H7*D35-I35*I7*D35-J35*J7*D35)+B8*C35*K35*(D35*C8-E35*D8-F35*E8-G35*(F8*D35+G8)-H35*H8*D35-I35*I8*D35-J35*J8*D35)+IF($B$12>0,$B$13*O35/($B$12*N35),0)*(D35*C9-E35*D9-F35*E9-G35*(F9*D35+G9)-H35*H9*D35-I35*I9*D35-J35*J9*D35)-$B$13*O35-L35*$B$10-M35*$B$11 | Q35: =P35-P$16
A36: Frais fixes | B36: +20 % | C36: 1 | D36: 1 | E36: 1 | F36: 1 | G36: 1 | H36: 1 | I36: 1 | J36: 1 | K36: 1 | L36: 1.2 | M36: 1 | N36: 1 | O36: 1 | P36: =B6*C36*(D36*C6-E36*D6-F36*E6-G36*(F6*D36+G6)-H36*H6*D36-I36*I6*D36-J36*J6*D36)+(B7+B8*(1-K36))*C36*(D36*C7-E36*D7-F36*E7-G36*(F7*D36+G7)-H36*H7*D36-I36*I7*D36-J36*J7*D36)+B8*C36*K36*(D36*C8-E36*D8-F36*E8-G36*(F8*D36+G8)-H36*H8*D36-I36*I8*D36-J36*J8*D36)+IF($B$12>0,$B$13*O36/($B$12*N36),0)*(D36*C9-E36*D9-F36*E9-G36*(F9*D36+G9)-H36*H9*D36-I36*I9*D36-J36*J9*D36)-$B$13*O36-L36*$B$10-M36*$B$11 | Q36: =P36-P$16
A37: Échantillons créateurs | B37: −20 % | C37: 1 | D37: 1 | E37: 1 | F37: 1 | G37: 1 | H37: 1 | I37: 1 | J37: 1 | K37: 1 | L37: 1 | M37: 0.8 | N37: 1 | O37: 1 | P37: =B6*C37*(D37*C6-E37*D6-F37*E6-G37*(F6*D37+G6)-H37*H6*D37-I37*I6*D37-J37*J6*D37)+(B7+B8*(1-K37))*C37*(D37*C7-E37*D7-F37*E7-G37*(F7*D37+G7)-H37*H7*D37-I37*I7*D37-J37*J7*D37)+B8*C37*K37*(D37*C8-E37*D8-F37*E8-G37*(F8*D37+G8)-H37*H8*D37-I37*I8*D37-J37*J8*D37)+IF($B$12>0,$B$13*O37/($B$12*N37),0)*(D37*C9-E37*D9-F37*E9-G37*(F9*D37+G9)-H37*H9*D37-I37*I9*D37-J37*J9*D37)-$B$13*O37-L37*$B$10-M37*$B$11 | Q37: =P37-P$16
A38: Échantillons créateurs | B38: +20 % | C38: 1 | D38: 1 | E38: 1 | F38: 1 | G38: 1 | H38: 1 | I38: 1 | J38: 1 | K38: 1 | L38: 1 | M38: 1.2 | N38: 1 | O38: 1 | P38: =B6*C38*(D38*C6-E38*D6-F38*E6-G38*(F6*D38+G6)-H38*H6*D38-I38*I6*D38-J38*J6*D38)+(B7+B8*(1-K38))*C38*(D38*C7-E38*D7-F38*E7-G38*(F7*D38+G7)-H38*H7*D38-I38*I7*D38-J38*J7*D38)+B8*C38*K38*(D38*C8-E38*D8-F38*E8-G38*(F8*D38+G8)-H38*H8*D38-I38*I8*D38-J38*J8*D38)+IF($B$12>0,$B$13*O38/($B$12*N38),0)*(D38*C9-E38*D9-F38*E9-G38*(F9*D38+G9)-H38*H9*D38-I38*I9*D38-J38*J9*D38)-$B$13*O38-L38*$B$10-M38*$B$11 | Q38: =P38-P$16
A41: Palier 2 — 10 000 € de bénéfice (import groupé, 3PL, publicité)
A42: Canal | B42: Commandes | C42: CA HT | D42: Produit | E42: Livraison | F42: Paiement % | G42: Paiement fixe | H42: Comm. TikTok | I42: Comm. créateur | J42: Provision
A43: Site organique | B43: ='Paliers'!C9*(1-h_P2_PART_PUB)*h_MIX_SITE | C43: =ue_SITE_HT | D43: =ue_SITE_PROD_IMP | E43: =ue_SITE_LOG_IMP | F43: =h_STRIPE_PCT*ue_SITE_TTC | G43: =h_STRIPE_FIXE | H43: =0 | I43: =0 | J43: =h_PROV_RETOURS*C43
A44: TikTok Shop contenu propre | B44: ='Paliers'!C9*(1-h_P2_PART_PUB)*h_MIX_PROPRE | C44: =ue_TTS_HT | D44: =ue_TTS_PROD_IMP | E44: =ue_TTS_LOG_IMP | F44: =0 | G44: =0 | H44: =h_TTS_COMM*ue_TTS_TTC | I44: =0 | J44: =h_PROV_RETOURS*C44
A45: TikTok Shop affiliés | B45: ='Paliers'!C9*(1-h_P2_PART_PUB)*h_MIX_AFF | C45: =ue_TTS_HT | D45: =ue_TTS_PROD_IMP | E45: =ue_TTS_LOG_IMP | F45: =0 | G45: =0 | H45: =h_TTS_COMM*ue_TTS_TTC | I45: =h_CREA_COMM*ue_TTS_TTC | J45: =h_PROV_RETOURS*C45
A46: Site, publicité | B46: ='Paliers'!C9*h_P2_PART_PUB | C46: =ue_PUB_HT | D46: =ue_PUB_PROD_IMP | E46: =ue_PUB_LOG_IMP | F46: =h_STRIPE_PCT*ue_PUB_TTC | G46: =h_STRIPE_FIXE | H46: =0 | I46: =0 | J46: =h_PROV_RETOURS*C46
A47: Frais fixes (€ / mois) | B47: =h_P2_FIXES_AUTRES+h_P2_PERSONNEL
A48: Échantillons créateurs (€ / mois) | B48: =h_P2_ECH
A49: CPA (€) | B49: ='Paliers'!C8
A50: Budget publicitaire (€ / mois) | B50: =B49*B46
A52: Variable | B52: Variation | C52: kVol | D52: kPrix | E52: kProd | F52: kLog | G52: kPay | H52: kTTS | I52: kCrea | J52: kRet | K52: kAff | L52: kFix | M52: kEch | N52: kCPA | O52: kPubVol | P52: Bénéfice mensuel | Q52: Écart vs base
A53: Base | B53: — | C53: 1 | D53: 1 | E53: 1 | F53: 1 | G53: 1 | H53: 1 | I53: 1 | J53: 1 | K53: 1 | L53: 1 | M53: 1 | N53: 1 | O53: 1 | P53: =B43*C53*(D53*C43-E53*D43-F53*E43-G53*(F43*D53+G43)-H53*H43*D53-I53*I43*D53-J53*J43*D53)+(B44+B45*(1-K53))*C53*(D53*C44-E53*D44-F53*E44-G53*(F44*D53+G44)-H53*H44*D53-I53*I44*D53-J53*J44*D53)+B45*C53*K53*(D53*C45-E53*D45-F53*E45-G53*(F45*D53+G45)-H53*H45*D53-I53*I45*D53-J53*J45*D53)+IF($B$49>0,$B$50*O53/($B$49*N53),0)*(D53*C46-E53*D46-F53*E46-G53*(F46*D53+G46)-H53*H46*D53-I53*I46*D53-J53*J46*D53)-$B$50*O53-L53*$B$47-M53*$B$48
A54: Volume de commandes organiques | B54: −20 % | C54: 0.8 | D54: 1 | E54: 1 | F54: 1 | G54: 1 | H54: 1 | I54: 1 | J54: 1 | K54: 1 | L54: 1 | M54: 1 | N54: 1 | O54: 1 | P54: =B43*C54*(D54*C43-E54*D43-F54*E43-G54*(F43*D54+G43)-H54*H43*D54-I54*I43*D54-J54*J43*D54)+(B44+B45*(1-K54))*C54*(D54*C44-E54*D44-F54*E44-G54*(F44*D54+G44)-H54*H44*D54-I54*I44*D54-J54*J44*D54)+B45*C54*K54*(D54*C45-E54*D45-F54*E45-G54*(F45*D54+G45)-H54*H45*D54-I54*I45*D54-J54*J45*D54)+IF($B$49>0,$B$50*O54/($B$49*N54),0)*(D54*C46-E54*D46-F54*E46-G54*(F46*D54+G46)-H54*H46*D54-I54*I46*D54-J54*J46*D54)-$B$50*O54-L54*$B$47-M54*$B$48 | Q54: =P54-P$53
A55: Volume de commandes organiques | B55: +20 % | C55: 1.2 | D55: 1 | E55: 1 | F55: 1 | G55: 1 | H55: 1 | I55: 1 | J55: 1 | K55: 1 | L55: 1 | M55: 1 | N55: 1 | O55: 1 | P55: =B43*C55*(D55*C43-E55*D43-F55*E43-G55*(F43*D55+G43)-H55*H43*D55-I55*I43*D55-J55*J43*D55)+(B44+B45*(1-K55))*C55*(D55*C44-E55*D44-F55*E44-G55*(F44*D55+G44)-H55*H44*D55-I55*I44*D55-J55*J44*D55)+B45*C55*K55*(D55*C45-E55*D45-F55*E45-G55*(F45*D55+G45)-H55*H45*D55-I55*I45*D55-J55*J45*D55)+IF($B$49>0,$B$50*O55/($B$49*N55),0)*(D55*C46-E55*D46-F55*E46-G55*(F46*D55+G46)-H55*H46*D55-I55*I46*D55-J55*J46*D55)-$B$50*O55-L55*$B$47-M55*$B$48 | Q55: =P55-P$53
A56: Prix de vente (tous produits) | B56: −20 % | C56: 1 | D56: 0.8 | E56: 1 | F56: 1 | G56: 1 | H56: 1 | I56: 1 | J56: 1 | K56: 1 | L56: 1 | M56: 1 | N56: 1 | O56: 1 | P56: =B43*C56*(D56*C43-E56*D43-F56*E43-G56*(F43*D56+G43)-H56*H43*D56-I56*I43*D56-J56*J43*D56)+(B44+B45*(1-K56))*C56*(D56*C44-E56*D44-F56*E44-G56*(F44*D56+G44)-H56*H44*D56-I56*I44*D56-J56*J44*D56)+B45*C56*K56*(D56*C45-E56*D45-F56*E45-G56*(F45*D56+G45)-H56*H45*D56-I56*I45*D56-J56*J45*D56)+IF($B$49>0,$B$50*O56/($B$49*N56),0)*(D56*C46-E56*D46-F56*E46-G56*(F46*D56+G46)-H56*H46*D56-I56*I46*D56-J56*J46*D56)-$B$50*O56-L56*$B$47-M56*$B$48 | Q56: =P56-P$53
A57: Prix de vente (tous produits) | B57: +20 % | C57: 1 | D57: 1.2 | E57: 1 | F57: 1 | G57: 1 | H57: 1 | I57: 1 | J57: 1 | K57: 1 | L57: 1 | M57: 1 | N57: 1 | O57: 1 | P57: =B43*C57*(D57*C43-E57*D43-F57*E43-G57*(F43*D57+G43)-H57*H43*D57-I57*I43*D57-J57*J43*D57)+(B44+B45*(1-K57))*C57*(D57*C44-E57*D44-F57*E44-G57*(F44*D57+G44)-H57*H44*D57-I57*I44*D57-J57*J44*D57)+B45*C57*K57*(D57*C45-E57*D45-F57*E45-G57*(F45*D57+G45)-H57*H45*D57-I57*I45*D57-J57*J45*D57)+IF($B$49>0,$B$50*O57/($B$49*N57),0)*(D57*C46-E57*D46-F57*E46-G57*(F46*D57+G46)-H57*H46*D57-I57*I46*D57-J57*J46*D57)-$B$50*O57-L57*$B$47-M57*$B$48 | Q57: =P57-P$53
A58: Coût produit et droits | B58: −20 % | C58: 1 | D58: 1 | E58: 0.8 | F58: 1 | G58: 1 | H58: 1 | I58: 1 | J58: 1 | K58: 1 | L58: 1 | M58: 1 | N58: 1 | O58: 1 | P58: =B43*C58*(D58*C43-E58*D43-F58*E43-G58*(F43*D58+G43)-H58*H43*D58-I58*I43*D58-J58*J43*D58)+(B44+B45*(1-K58))*C58*(D58*C44-E58*D44-F58*E44-G58*(F44*D58+G44)-H58*H44*D58-I58*I44*D58-J58*J44*D58)+B45*C58*K58*(D58*C45-E58*D45-F58*E45-G58*(F45*D58+G45)-H58*H45*D58-I58*I45*D58-J58*J45*D58)+IF($B$49>0,$B$50*O58/($B$49*N58),0)*(D58*C46-E58*D46-F58*E46-G58*(F46*D58+G46)-H58*H46*D58-I58*I46*D58-J58*J46*D58)-$B$50*O58-L58*$B$47-M58*$B$48 | Q58: =P58-P$53
A59: Coût produit et droits | B59: +20 % | C59: 1 | D59: 1 | E59: 1.2 | F59: 1 | G59: 1 | H59: 1 | I59: 1 | J59: 1 | K59: 1 | L59: 1 | M59: 1 | N59: 1 | O59: 1 | P59: =B43*C59*(D59*C43-E59*D43-F59*E43-G59*(F43*D59+G43)-H59*H43*D59-I59*I43*D59-J59*J43*D59)+(B44+B45*(1-K59))*C59*(D59*C44-E59*D44-F59*E44-G59*(F44*D59+G44)-H59*H44*D59-I59*I44*D59-J59*J44*D59)+B45*C59*K59*(D59*C45-E59*D45-F59*E45-G59*(F45*D59+G45)-H59*H45*D59-I59*I45*D59-J59*J45*D59)+IF($B$49>0,$B$50*O59/($B$49*N59),0)*(D59*C46-E59*D46-F59*E46-G59*(F46*D59+G46)-H59*H46*D59-I59*I46*D59-J59*J46*D59)-$B$50*O59-L59*$B$47-M59*$B$48 | Q59: =P59-P$53
A60: Livraison et emballage | B60: −20 % | C60: 1 | D60: 1 | E60: 1 | F60: 0.8 | G60: 1 | H60: 1 | I60: 1 | J60: 1 | K60: 1 | L60: 1 | M60: 1 | N60: 1 | O60: 1 | P60: =B43*C60*(D60*C43-E60*D43-F60*E43-G60*(F43*D60+G43)-H60*H43*D60-I60*I43*D60-J60*J43*D60)+(B44+B45*(1-K60))*C60*(D60*C44-E60*D44-F60*E44-G60*(F44*D60+G44)-H60*H44*D60-I60*I44*D60-J60*J44*D60)+B45*C60*K60*(D60*C45-E60*D45-F60*E45-G60*(F45*D60+G45)-H60*H45*D60-I60*I45*D60-J60*J45*D60)+IF($B$49>0,$B$50*O60/($B$49*N60),0)*(D60*C46-E60*D46-F60*E46-G60*(F46*D60+G46)-H60*H46*D60-I60*I46*D60-J60*J46*D60)-$B$50*O60-L60*$B$47-M60*$B$48 | Q60: =P60-P$53
A61: Livraison et emballage | B61: +20 % | C61: 1 | D61: 1 | E61: 1 | F61: 1.2 | G61: 1 | H61: 1 | I61: 1 | J61: 1 | K61: 1 | L61: 1 | M61: 1 | N61: 1 | O61: 1 | P61: =B43*C61*(D61*C43-E61*D43-F61*E43-G61*(F43*D61+G43)-H61*H43*D61-I61*I43*D61-J61*J43*D61)+(B44+B45*(1-K61))*C61*(D61*C44-E61*D44-F61*E44-G61*(F44*D61+G44)-H61*H44*D61-I61*I44*D61-J61*J44*D61)+B45*C61*K61*(D61*C45-E61*D45-F61*E45-G61*(F45*D61+G45)-H61*H45*D61-I61*I45*D61-J61*J45*D61)+IF($B$49>0,$B$50*O61/($B$49*N61),0)*(D61*C46-E61*D46-F61*E46-G61*(F46*D61+G46)-H61*H46*D61-I61*I46*D61-J61*J46*D61)-$B$50*O61-L61*$B$47-M61*$B$48 | Q61: =P61-P$53
A62: Frais de paiement | B62: −20 % | C62: 1 | D62: 1 | E62: 1 | F62: 1 | G62: 0.8 | H62: 1 | I62: 1 | J62: 1 | K62: 1 | L62: 1 | M62: 1 | N62: 1 | O62: 1 | P62: =B43*C62*(D62*C43-E62*D43-F62*E43-G62*(F43*D62+G43)-H62*H43*D62-I62*I43*D62-J62*J43*D62)+(B44+B45*(1-K62))*C62*(D62*C44-E62*D44-F62*E44-G62*(F44*D62+G44)-H62*H44*D62-I62*I44*D62-J62*J44*D62)+B45*C62*K62*(D62*C45-E62*D45-F62*E45-G62*(F45*D62+G45)-H62*H45*D62-I62*I45*D62-J62*J45*D62)+IF($B$49>0,$B$50*O62/($B$49*N62),0)*(D62*C46-E62*D46-F62*E46-G62*(F46*D62+G46)-H62*H46*D62-I62*I46*D62-J62*J46*D62)-$B$50*O62-L62*$B$47-M62*$B$48 | Q62: =P62-P$53
A63: Frais de paiement | B63: +20 % | C63: 1 | D63: 1 | E63: 1 | F63: 1 | G63: 1.2 | H63: 1 | I63: 1 | J63: 1 | K63: 1 | L63: 1 | M63: 1 | N63: 1 | O63: 1 | P63: =B43*C63*(D63*C43-E63*D43-F63*E43-G63*(F43*D63+G43)-H63*H43*D63-I63*I43*D63-J63*J43*D63)+(B44+B45*(1-K63))*C63*(D63*C44-E63*D44-F63*E44-G63*(F44*D63+G44)-H63*H44*D63-I63*I44*D63-J63*J44*D63)+B45*C63*K63*(D63*C45-E63*D45-F63*E45-G63*(F45*D63+G45)-H63*H45*D63-I63*I45*D63-J63*J45*D63)+IF($B$49>0,$B$50*O63/($B$49*N63),0)*(D63*C46-E63*D46-F63*E46-G63*(F46*D63+G46)-H63*H46*D63-I63*I46*D63-J63*J46*D63)-$B$50*O63-L63*$B$47-M63*$B$48 | Q63: =P63-P$53
A64: Commission TikTok Shop | B64: −20 % | C64: 1 | D64: 1 | E64: 1 | F64: 1 | G64: 1 | H64: 0.8 | I64: 1 | J64: 1 | K64: 1 | L64: 1 | M64: 1 | N64: 1 | O64: 1 | P64: =B43*C64*(D64*C43-E64*D43-F64*E43-G64*(F43*D64+G43)-H64*H43*D64-I64*I43*D64-J64*J43*D64)+(B44+B45*(1-K64))*C64*(D64*C44-E64*D44-F64*E44-G64*(F44*D64+G44)-H64*H44*D64-I64*I44*D64-J64*J44*D64)+B45*C64*K64*(D64*C45-E64*D45-F64*E45-G64*(F45*D64+G45)-H64*H45*D64-I64*I45*D64-J64*J45*D64)+IF($B$49>0,$B$50*O64/($B$49*N64),0)*(D64*C46-E64*D46-F64*E46-G64*(F46*D64+G46)-H64*H46*D64-I64*I46*D64-J64*J46*D64)-$B$50*O64-L64*$B$47-M64*$B$48 | Q64: =P64-P$53
A65: Commission TikTok Shop | B65: +20 % | C65: 1 | D65: 1 | E65: 1 | F65: 1 | G65: 1 | H65: 1.2 | I65: 1 | J65: 1 | K65: 1 | L65: 1 | M65: 1 | N65: 1 | O65: 1 | P65: =B43*C65*(D65*C43-E65*D43-F65*E43-G65*(F43*D65+G43)-H65*H43*D65-I65*I43*D65-J65*J43*D65)+(B44+B45*(1-K65))*C65*(D65*C44-E65*D44-F65*E44-G65*(F44*D65+G44)-H65*H44*D65-I65*I44*D65-J65*J44*D65)+B45*C65*K65*(D65*C45-E65*D45-F65*E45-G65*(F45*D65+G45)-H65*H45*D65-I65*I45*D65-J65*J45*D65)+IF($B$49>0,$B$50*O65/($B$49*N65),0)*(D65*C46-E65*D46-F65*E46-G65*(F46*D65+G46)-H65*H46*D65-I65*I46*D65-J65*J46*D65)-$B$50*O65-L65*$B$47-M65*$B$48 | Q65: =P65-P$53
A66: Commission des créateurs | B66: −20 % | C66: 1 | D66: 1 | E66: 1 | F66: 1 | G66: 1 | H66: 1 | I66: 0.8 | J66: 1 | K66: 1 | L66: 1 | M66: 1 | N66: 1 | O66: 1 | P66: =B43*C66*(D66*C43-E66*D43-F66*E43-G66*(F43*D66+G43)-H66*H43*D66-I66*I43*D66-J66*J43*D66)+(B44+B45*(1-K66))*C66*(D66*C44-E66*D44-F66*E44-G66*(F44*D66+G44)-H66*H44*D66-I66*I44*D66-J66*J44*D66)+B45*C66*K66*(D66*C45-E66*D45-F66*E45-G66*(F45*D66+G45)-H66*H45*D66-I66*I45*D66-J66*J45*D66)+IF($B$49>0,$B$50*O66/($B$49*N66),0)*(D66*C46-E66*D46-F66*E46-G66*(F46*D66+G46)-H66*H46*D66-I66*I46*D66-J66*J46*D66)-$B$50*O66-L66*$B$47-M66*$B$48 | Q66: =P66-P$53
A67: Commission des créateurs | B67: +20 % | C67: 1 | D67: 1 | E67: 1 | F67: 1 | G67: 1 | H67: 1 | I67: 1.2 | J67: 1 | K67: 1 | L67: 1 | M67: 1 | N67: 1 | O67: 1 | P67: =B43*C67*(D67*C43-E67*D43-F67*E43-G67*(F43*D67+G43)-H67*H43*D67-I67*I43*D67-J67*J43*D67)+(B44+B45*(1-K67))*C67*(D67*C44-E67*D44-F67*E44-G67*(F44*D67+G44)-H67*H44*D67-I67*I44*D67-J67*J44*D67)+B45*C67*K67*(D67*C45-E67*D45-F67*E45-G67*(F45*D67+G45)-H67*H45*D67-I67*I45*D67-J67*J45*D67)+IF($B$49>0,$B$50*O67/($B$49*N67),0)*(D67*C46-E67*D46-F67*E46-G67*(F46*D67+G46)-H67*H46*D67-I67*I46*D67-J67*J46*D67)-$B$50*O67-L67*$B$47-M67*$B$48 | Q67: =P67-P$53
A68: Retours, SAV et litiges | B68: −20 % | C68: 1 | D68: 1 | E68: 1 | F68: 1 | G68: 1 | H68: 1 | I68: 1 | J68: 0.8 | K68: 1 | L68: 1 | M68: 1 | N68: 1 | O68: 1 | P68: =B43*C68*(D68*C43-E68*D43-F68*E43-G68*(F43*D68+G43)-H68*H43*D68-I68*I43*D68-J68*J43*D68)+(B44+B45*(1-K68))*C68*(D68*C44-E68*D44-F68*E44-G68*(F44*D68+G44)-H68*H44*D68-I68*I44*D68-J68*J44*D68)+B45*C68*K68*(D68*C45-E68*D45-F68*E45-G68*(F45*D68+G45)-H68*H45*D68-I68*I45*D68-J68*J45*D68)+IF($B$49>0,$B$50*O68/($B$49*N68),0)*(D68*C46-E68*D46-F68*E46-G68*(F46*D68+G46)-H68*H46*D68-I68*I46*D68-J68*J46*D68)-$B$50*O68-L68*$B$47-M68*$B$48 | Q68: =P68-P$53
A69: Retours, SAV et litiges | B69: +20 % | C69: 1 | D69: 1 | E69: 1 | F69: 1 | G69: 1 | H69: 1 | I69: 1 | J69: 1.2 | K69: 1 | L69: 1 | M69: 1 | N69: 1 | O69: 1 | P69: =B43*C69*(D69*C43-E69*D43-F69*E43-G69*(F43*D69+G43)-H69*H43*D69-I69*I43*D69-J69*J43*D69)+(B44+B45*(1-K69))*C69*(D69*C44-E69*D44-F69*E44-G69*(F44*D69+G44)-H69*H44*D69-I69*I44*D69-J69*J44*D69)+B45*C69*K69*(D69*C45-E69*D45-F69*E45-G69*(F45*D69+G45)-H69*H45*D69-I69*I45*D69-J69*J45*D69)+IF($B$49>0,$B$50*O69/($B$49*N69),0)*(D69*C46-E69*D46-F69*E46-G69*(F46*D69+G46)-H69*H46*D69-I69*I46*D69-J69*J46*D69)-$B$50*O69-L69*$B$47-M69*$B$48 | Q69: =P69-P$53
A70: Part des ventes par affiliés | B70: −20 % | C70: 1 | D70: 1 | E70: 1 | F70: 1 | G70: 1 | H70: 1 | I70: 1 | J70: 1 | K70: 0.8 | L70: 1 | M70: 1 | N70: 1 | O70: 1 | P70: =B43*C70*(D70*C43-E70*D43-F70*E43-G70*(F43*D70+G43)-H70*H43*D70-I70*I43*D70-J70*J43*D70)+(B44+B45*(1-K70))*C70*(D70*C44-E70*D44-F70*E44-G70*(F44*D70+G44)-H70*H44*D70-I70*I44*D70-J70*J44*D70)+B45*C70*K70*(D70*C45-E70*D45-F70*E45-G70*(F45*D70+G45)-H70*H45*D70-I70*I45*D70-J70*J45*D70)+IF($B$49>0,$B$50*O70/($B$49*N70),0)*(D70*C46-E70*D46-F70*E46-G70*(F46*D70+G46)-H70*H46*D70-I70*I46*D70-J70*J46*D70)-$B$50*O70-L70*$B$47-M70*$B$48 | Q70: =P70-P$53
A71: Part des ventes par affiliés | B71: +20 % | C71: 1 | D71: 1 | E71: 1 | F71: 1 | G71: 1 | H71: 1 | I71: 1 | J71: 1 | K71: 1.2 | L71: 1 | M71: 1 | N71: 1 | O71: 1 | P71: =B43*C71*(D71*C43-E71*D43-F71*E43-G71*(F43*D71+G43)-H71*H43*D71-I71*I43*D71-J71*J43*D71)+(B44+B45*(1-K71))*C71*(D71*C44-E71*D44-F71*E44-G71*(F44*D71+G44)-H71*H44*D71-I71*I44*D71-J71*J44*D71)+B45*C71*K71*(D71*C45-E71*D45-F71*E45-G71*(F45*D71+G45)-H71*H45*D71-I71*I45*D71-J71*J45*D71)+IF($B$49>0,$B$50*O71/($B$49*N71),0)*(D71*C46-E71*D46-F71*E46-G71*(F46*D71+G46)-H71*H46*D71-I71*I46*D71-J71*J46*D71)-$B$50*O71-L71*$B$47-M71*$B$48 | Q71: =P71-P$53
A72: Frais fixes | B72: −20 % | C72: 1 | D72: 1 | E72: 1 | F72: 1 | G72: 1 | H72: 1 | I72: 1 | J72: 1 | K72: 1 | L72: 0.8 | M72: 1 | N72: 1 | O72: 1 | P72: =B43*C72*(D72*C43-E72*D43-F72*E43-G72*(F43*D72+G43)-H72*H43*D72-I72*I43*D72-J72*J43*D72)+(B44+B45*(1-K72))*C72*(D72*C44-E72*D44-F72*E44-G72*(F44*D72+G44)-H72*H44*D72-I72*I44*D72-J72*J44*D72)+B45*C72*K72*(D72*C45-E72*D45-F72*E45-G72*(F45*D72+G45)-H72*H45*D72-I72*I45*D72-J72*J45*D72)+IF($B$49>0,$B$50*O72/($B$49*N72),0)*(D72*C46-E72*D46-F72*E46-G72*(F46*D72+G46)-H72*H46*D72-I72*I46*D72-J72*J46*D72)-$B$50*O72-L72*$B$47-M72*$B$48 | Q72: =P72-P$53
A73: Frais fixes | B73: +20 % | C73: 1 | D73: 1 | E73: 1 | F73: 1 | G73: 1 | H73: 1 | I73: 1 | J73: 1 | K73: 1 | L73: 1.2 | M73: 1 | N73: 1 | O73: 1 | P73: =B43*C73*(D73*C43-E73*D43-F73*E43-G73*(F43*D73+G43)-H73*H43*D73-I73*I43*D73-J73*J43*D73)+(B44+B45*(1-K73))*C73*(D73*C44-E73*D44-F73*E44-G73*(F44*D73+G44)-H73*H44*D73-I73*I44*D73-J73*J44*D73)+B45*C73*K73*(D73*C45-E73*D45-F73*E45-G73*(F45*D73+G45)-H73*H45*D73-I73*I45*D73-J73*J45*D73)+IF($B$49>0,$B$50*O73/($B$49*N73),0)*(D73*C46-E73*D46-F73*E46-G73*(F46*D73+G46)-H73*H46*D73-I73*I46*D73-J73*J46*D73)-$B$50*O73-L73*$B$47-M73*$B$48 | Q73: =P73-P$53
A74: Échantillons créateurs | B74: −20 % | C74: 1 | D74: 1 | E74: 1 | F74: 1 | G74: 1 | H74: 1 | I74: 1 | J74: 1 | K74: 1 | L74: 1 | M74: 0.8 | N74: 1 | O74: 1 | P74: =B43*C74*(D74*C43-E74*D43-F74*E43-G74*(F43*D74+G43)-H74*H43*D74-I74*I43*D74-J74*J43*D74)+(B44+B45*(1-K74))*C74*(D74*C44-E74*D44-F74*E44-G74*(F44*D74+G44)-H74*H44*D74-I74*I44*D74-J74*J44*D74)+B45*C74*K74*(D74*C45-E74*D45-F74*E45-G74*(F45*D74+G45)-H74*H45*D74-I74*I45*D74-J74*J45*D74)+IF($B$49>0,$B$50*O74/($B$49*N74),0)*(D74*C46-E74*D46-F74*E46-G74*(F46*D74+G46)-H74*H46*D74-I74*I46*D74-J74*J46*D74)-$B$50*O74-L74*$B$47-M74*$B$48 | Q74: =P74-P$53
A75: Échantillons créateurs | B75: +20 % | C75: 1 | D75: 1 | E75: 1 | F75: 1 | G75: 1 | H75: 1 | I75: 1 | J75: 1 | K75: 1 | L75: 1 | M75: 1.2 | N75: 1 | O75: 1 | P75: =B43*C75*(D75*C43-E75*D43-F75*E43-G75*(F43*D75+G43)-H75*H43*D75-I75*I43*D75-J75*J43*D75)+(B44+B45*(1-K75))*C75*(D75*C44-E75*D44-F75*E44-G75*(F44*D75+G44)-H75*H44*D75-I75*I44*D75-J75*J44*D75)+B45*C75*K75*(D75*C45-E75*D45-F75*E45-G75*(F45*D75+G45)-H75*H45*D75-I75*I45*D75-J75*J45*D75)+IF($B$49>0,$B$50*O75/($B$49*N75),0)*(D75*C46-E75*D46-F75*E46-G75*(F46*D75+G46)-H75*H46*D75-I75*I46*D75-J75*J46*D75)-$B$50*O75-L75*$B$47-M75*$B$48 | Q75: =P75-P$53
A76: CPA publicitaire | B76: −20 % | C76: 1 | D76: 1 | E76: 1 | F76: 1 | G76: 1 | H76: 1 | I76: 1 | J76: 1 | K76: 1 | L76: 1 | M76: 1 | N76: 0.8 | O76: 1 | P76: =B43*C76*(D76*C43-E76*D43-F76*E43-G76*(F43*D76+G43)-H76*H43*D76-I76*I43*D76-J76*J43*D76)+(B44+B45*(1-K76))*C76*(D76*C44-E76*D44-F76*E44-G76*(F44*D76+G44)-H76*H44*D76-I76*I44*D76-J76*J44*D76)+B45*C76*K76*(D76*C45-E76*D45-F76*E45-G76*(F45*D76+G45)-H76*H45*D76-I76*I45*D76-J76*J45*D76)+IF($B$49>0,$B$50*O76/($B$49*N76),0)*(D76*C46-E76*D46-F76*E46-G76*(F46*D76+G46)-H76*H46*D76-I76*I46*D76-J76*J46*D76)-$B$50*O76-L76*$B$47-M76*$B$48 | Q76: =P76-P$53
A77: CPA publicitaire | B77: +20 % | C77: 1 | D77: 1 | E77: 1 | F77: 1 | G77: 1 | H77: 1 | I77: 1 | J77: 1 | K77: 1 | L77: 1 | M77: 1 | N77: 1.2 | O77: 1 | P77: =B43*C77*(D77*C43-E77*D43-F77*E43-G77*(F43*D77+G43)-H77*H43*D77-I77*I43*D77-J77*J43*D77)+(B44+B45*(1-K77))*C77*(D77*C44-E77*D44-F77*E44-G77*(F44*D77+G44)-H77*H44*D77-I77*I44*D77-J77*J44*D77)+B45*C77*K77*(D77*C45-E77*D45-F77*E45-G77*(F45*D77+G45)-H77*H45*D77-I77*I45*D77-J77*J45*D77)+IF($B$49>0,$B$50*O77/($B$49*N77),0)*(D77*C46-E77*D46-F77*E46-G77*(F46*D77+G46)-H77*H46*D77-I77*I46*D77-J77*J46*D77)-$B$50*O77-L77*$B$47-M77*$B$48 | Q77: =P77-P$53
A78: Budget publicitaire | B78: −20 % | C78: 1 | D78: 1 | E78: 1 | F78: 1 | G78: 1 | H78: 1 | I78: 1 | J78: 1 | K78: 1 | L78: 1 | M78: 1 | N78: 1 | O78: 0.8 | P78: =B43*C78*(D78*C43-E78*D43-F78*E43-G78*(F43*D78+G43)-H78*H43*D78-I78*I43*D78-J78*J43*D78)+(B44+B45*(1-K78))*C78*(D78*C44-E78*D44-F78*E44-G78*(F44*D78+G44)-H78*H44*D78-I78*I44*D78-J78*J44*D78)+B45*C78*K78*(D78*C45-E78*D45-F78*E45-G78*(F45*D78+G45)-H78*H45*D78-I78*I45*D78-J78*J45*D78)+IF($B$49>0,$B$50*O78/($B$49*N78),0)*(D78*C46-E78*D46-F78*E46-G78*(F46*D78+G46)-H78*H46*D78-I78*I46*D78-J78*J46*D78)-$B$50*O78-L78*$B$47-M78*$B$48 | Q78: =P78-P$53
A79: Budget publicitaire | B79: +20 % | C79: 1 | D79: 1 | E79: 1 | F79: 1 | G79: 1 | H79: 1 | I79: 1 | J79: 1 | K79: 1 | L79: 1 | M79: 1 | N79: 1 | O79: 1.2 | P79: =B43*C79*(D79*C43-E79*D43-F79*E43-G79*(F43*D79+G43)-H79*H43*D79-I79*I43*D79-J79*J43*D79)+(B44+B45*(1-K79))*C79*(D79*C44-E79*D44-F79*E44-G79*(F44*D79+G44)-H79*H44*D79-I79*I44*D79-J79*J44*D79)+B45*C79*K79*(D79*C45-E79*D45-F79*E45-G79*(F45*D79+G45)-H79*H45*D79-I79*I45*D79-J79*J45*D79)+IF($B$49>0,$B$50*O79/($B$49*N79),0)*(D79*C46-E79*D46-F79*E46-G79*(F46*D79+G46)-H79*H46*D79-I79*I46*D79-J79*J46*D79)-$B$50*O79-L79*$B$47-M79*$B$48 | Q79: =P79-P$53
